Workbook

Sheet RESUMO DO PROJETO
A1: RESUMO DO PROJETO — pra outro Claude/chat continuar de onde parei
A3: Esse resumo existe porque essa conversa já passou de 1 semana e o usuário (Rod) bateu limite de anexo no chat atual. O objetivo é: quem ler isso (outro Claude, em outro chat) deve conseguir continuar o trabalho com ~90% do contexto que o Claude anterior tinha. Leia isso INTEIRO antes de mexer em qualquer coisa. Depois, sempre CONFIRME contra o código/planilha real antes de assumir que algo funciona — esse projeto tem um histórico forte de "achei que funcionava, mas não funcionava" (ver seção de Armadilhas).
A5: 1. O QUE É O JOGO
A6: RPG solo em Telegram, bot chamado "Zeyrith RPG" (ou nome similar no BotFather), tema "A Infecção que Segura o Mundo" — pós-apocalíptico de fantasia, uma corrupção/Infecção Carmesim que espalhou pelo continente. 14 Tiers de progressão (Sucata Enferrujada → Estelar/Cósmico), 5 Atos narrativos, 7 Polos/Reinos, 8 Classes jogáveis. É PVE solo — qualquer pessoa que mandar /start pro bot ganha personagem próprio e isolado (não é preciso nenhum trabalho extra pra "multiplayer casual" nesse sentido — cada telegram_id é um personagem separado). Multiplayer/cooperativo de verdade (Fase 7) foi DECIDIDO e ADIADO, não é bug nem esquecimento.
A8: 2. ARQUITETURA — MUITO IMPORTANTE ENTENDER ISSO PRIMEIRO
A9: A PLANILHA é a fonte de verdade de todo dado de jogo (monstro, item, missão, local, etc). O BOT (Python/Telegram) só lê esse dado, nunca inventa. O fluxo é sempre o mesmo, nessa ordem: 1) Editar a planilha balanceamento_rpg-13.xlsx (ou -13-31.xlsx, os nomes variaram ao longo da conversa, sempre confirme qual está sendo usado). 2) Rodar `python3 db/export_json.py` — isso abre a planilha com LibreOffice headless (`soffice --headless --calc --convert-to xlsx`) pra RECALCULAR fórmulas antes de ler os valores (openpyxl sozinho não recalcula fórmula), e escreve `data/game_data.json`. 3) Rodar a importação (`from db.import_data import importar; importar()`) — isso lê o JSON e escreve no banco (SQLite local pra teste, Postgres/Neon em produção via Render). 4) SEMPRE testar o handler de verdade depois (chamando a função async com mocks), nunca assumir que "deve funcionar" só porque o dado foi importado. Pra achar erro de fórmula na planilha (tipo #REF!, #N/A), sempre recalcular com LibreOffice headless e contar erros — o número de baseline validado é 10 erros conhecidos (FILTER() incompatível com LibreOffice, funciona no Google Sheets, não é bug real).
A11: 3. ARMADILHAS CONHECIDAS — LEIA ISSO OU VAI PERDER TEMPO REPETINDO ERRO
A12: ⚠️ ACENTO: a mesma informação (nome de Tier, nome de tipo de arma, etc) às vezes aparece COM acento numa aba da planilha e SEM acento em outra. Ex: Tier.nome usa sempre SEM acento ("Aco Elfico", "Ferro Orquico", "Ebano") em TODO o sistema (Bestiário, Missões, Locais), mas outras abas (Crafting-Receitas, Recursos Naturais) às vezes trazem o nome COM acento ou em formato diferente ("Tier 8 (Ferro Órquico)", "Tier 1" numérico puro). Isso já causou pelo menos 4 bugs reais diferentes nessa conversa. Sempre que ligar duas tabelas pelo nome de Tier/tipo, ou normalize os dois lados (tem uma função `_normalizar()` em game/economia.py que remove acento) ou confirme os valores reais direto no banco antes de assumir que o JOIN vai bater.
A14: ⚠️ TELEGRAM SÓ ACEITA 1 RESPOSTA POR CLIQUE (callback_query.answer()): se o código chama `await query.answer()` (vazio) e DEPOIS chama `await query.answer("mensagem", show_alert=True)` no mesmo fluxo (sem branch/return entre elas), a SEGUNDA chamada é silenciosamente ignorada pelo Telegram. Esse bug apareceu em 11 funções diferentes numa única varredura. O padrão correto é: só chamar answer() UMA VEZ por execução, e se tem caminho de erro vs sucesso, cada um deve ter sua PRÓPRIA chamada de answer() (nunca as duas no mesmo caminho).
A16: ⚠️ REAPROVEITAR query.data: vários handlers terminam chamando outro handler pra "atualizar a tela" (ex: `confirmar_compra` chama `listar_compra` no final). Se o handler chamado espera fazer `query.data.split("_")` num formato diferente do que originou a ação, ele lê o ID errado como se fosse outra coisa (ex: um ID de compra virando "tipo" de categoria por engano). Sempre que isso acontecer, sobrescreva `query.data` manualmente pro formato certo ANTES de chamar o outro handler.
A18: ⚠️ SESSÃO DO SQLALCHEMY: nunca acesse atributo de objeto do banco (`objeto.campo`) depois de `session.close()`. Sempre extraia pra variável Python simples ANTES de fechar a sessão. Já causou bug real mais de uma vez.
A20: ⚠️ Armadura usa coluna `slot`, Arma usa coluna `tipo` — são nomes diferentes pro "mesmo conceito" (Espada/Peitoral/etc). Fácil esquecer e tentar `.tipo` numa Armadura (dá AttributeError).
... A46: Rod não programa — trabalha só pela planilha + conversa aqui. Esse é o CHECKLIST de como toda resposta deve funcionar, não é opcional, é o que ele mais valoriza no processo: 1) SEMPRE testar de verdade (rodar o handler com mock/sessão real) antes de dizer que algo funciona. Nunca assumir só de ler o código. 2) Quando for mudar uma tela/fluxo, editar a PLANILHA e o PYTHON juntos, na mesma resposta. 3) Depois de qualquer mudança visual, mostrar um MOCKUP com o TEXTO REAL que saiu do teste — nunca um mockup inventado/imaginado. 4) Mostrar esse mockup sempre NO FINAL da resposta, não no meio. 5) Se aparecer algo estranho no caminho que não foi pedido, investigar e resolver também, avisando que foi achado no caminho. 6) Não reenviar os arquivos toda hora — só quando ele pedir ou quando terminar um bloco grande de mudanças. 7) Em decisão de design (não bug), propor número/desenho concreto pra aprovar, em vez de pergunta aberta. Esse fluxo (testar → achar bug real → consertar planilha+python → testar de novo → mockup com dado real → aprovação → próximo item) é a espinha dorsal de como essa conversa toda funcionou por mais de uma semana. Seguir isso é mais importante que qualquer feature individual.

Sheet Indice Geral
A1: A Infecção que Segura o Mundo — Índice Geral (fechado 28/08)
A2: Todas as mecânicas, blocos fechados, e onde achar cada coisa. Comece aqui se estiver perdido.
A4: Sistema | B4: Onde está | C4: Status
A5: Progressão de Nível/Dano/Defesa | B5: Curva Mestra, Tiers | C5: ✅ Fechado
A6: Bestiário (123 monstros) | B6: Bestiario | C6: ✅ Fechado — efeitos, fraqueza, materiais
A7: Armas (308) / Armaduras (252) | B7: Armas, Armaduras | C7: ✅ Fechado — Variação, Mod.Variação, Preço
A8: Lendários/Artefatos (79) | B8: Artefatos e Relíquias | C8: ✅ Fechado — Dano/Defesa Base, flag Combate
A9: Missões (115+) | B9: Missoes | C9: ✅ Fechado — Facção/Reputação nas 13 principais
A10: Crafting (210 receitas) | B10: Crafting - Receitas | C10: ✅ Fechado — 4 níveis de fricção
A11: Materiais (157) | B11: Recursos Naturais | C11: ✅ Fechado — identidade visual, troféus
A12: Economia/Preço | B12: Economia, Cidades e NPCs | C12: ✅ Fechado — fórmula única
A13: Perigo/Atenção/Exploração | B13: Mundo - Locais, Regras e Fórmulas | C13: ✅ Fechado
A14: Descanso/Marcos de Nível | B14: Regras e Fórmulas | C14: ✅ Fechado
A15: Facções/Relação com NPC | B15: Reinos e Facções, Regras e Fórmulas | C15: ✅ Fechado
... A29: Bestiário Expandido (Tier 1 piloto) | B29: Bestiario, Monstros Raros | C29: ✅ Tier 1: 8→28 monstros. Meta final: ~400-470 nos 14 tiers. Tiers 2-14 pendentes.
A30: PENDENTE: Backfill de Papel de Combate + Condição de Spawn nos ~115 monstros originais (pre-existentes) dos Tiers 2-14. Fazer depois que a expansao completa (Tiers 1-14) terminar.
A31: PENDENTE (em espera, aguardando decisao): sistema de 10-15 missoes por Tier com bloqueio por Honra/Reputacao (Comum/Veterano/Lendario), 6 categorias por Tier (Principal/Caca/Coleta/Elite/Social/Exploracao). Hoje so existe 1 Principal por tier + pouquissimas secundarias (Tier1 tem so 2). Precisa de decisao antes de expandir.
A32: RESOLVIDO 03/09: Mundo-Locais reconciliada com o Bestiario. 32 locais formais, cobrindo todos os 29 nomes que os 470 monstros referenciam (1 excecao legitima: referencia dupla Estrada/Acampamento, ambos ja existentes).

Sheet Codex
A1: Codex — tudo que o jogador aprende e fica salvo pra sempre (estilo Crimson Desert)
A2: Isso é o TEMPLATE de estrutura pro app (Telegram Mini App) — o estado real de cada jogador (o que ele já descobriu) mora no banco de dados do app, não aqui. Essa aba mostra O QUE existe pra ser descoberto.
A4: Categoria do Codex | B4: Fonte (aba da planilha) | C4: Quantidade total | D4: Como é aprendido | E4: Fica salvo como
A5: Receitas Aprendidas | B5: Crafting - Receitas | C5: 210 receitas-base + variantes Nível 2-4 | D5: Ler 1x a Receita física (consumida no uso) | E5: Permanente — nunca mais precisa comprar de novo
A6: Bestiário (Knowledge) | B6: Bestiario | C6: 470 criaturas, 0-5 de Knowledge cada | D6: Observar / combater / estudar cadáver / NPC / livro | E6: Nível de Knowledge fica salvo, nunca regride
A7: Materiais Identificados | B7: Recursos Naturais | C7: 600 materiais | D7: Teste INT/SAB, NPC especialista, ou quest | E7: Uma vez identificado, sempre reconhecido
A8: NPCs (Relação) | B8: Cidades e NPCs (35 nomeados) | C8: 35 NPCs | D8: Ações (não presente) — sobe por consequência real | E8: Nível de relação fica salvo, inclusive traição
A9: Facções (Reputação) | B9: Reinos e Facções | C9: 7 facções | D9: Escolhas de quest (221 já mapeadas) | E9: -100 a +100, permanente
A10: Locais Descobertos | B10: Mundo - Locais | C10: 53 locais | D10: Explorar/chegar no local pela primeira vez | E10: Mapa revela permanentemente
A11: Títulos Conquistados | B11: Titulos | C11: 17 títulos (mais podem ser criados) | D11: Cumprir a condição (Proficiência 100, Bestiário, Reputação etc.) | E11: Exibido no personagem pra sempre
A12: Lendários/Artefatos Encontrados | B12: Artefatos e Relíquias | C12: 93 itens únicos | D12: Loot ou recompensa de quest | E12: Registrado mesmo se vendido/perdido depois
A13: Lore/Fragmentos do Aspecto | B13: Fragmentos do Aspecto | C13: 5 fragmentos (1 por Ato) | D13: Derrotar o boss que carrega cada um | E13: Progresso da história principal, visível no Codex
A14: Ferramentas de Coleta | B14: Crafting - Receitas | C14: 84 (14 tiers x 3 ferramentas x Padrão/Refinada) | D14: Comprar Receita + craftar na Forja | E14: Permanente, mostra no Codex de Ferramentas
A15: Comida/Bebida | B15: Crafting - Receitas | C15: 14 (1 por tier) | D15: Comprar Receita + craftar em qualquer Fogueira | E15: Buff temporário, receita fica permanente
... A17: Consumíveis (Poção, Antídoto, Veneno) | B17: Consumiveis | C17: 56 (4x14) + 14 Viais de Veneno = 70 | D17: Comprar ou craftar | E17: Não é permanente — item consumível, cada um se gasta ao usar

Sheet Regras e Fórmulas
A1: REGRAS DE MESA — cola rápida (motor completo está nas abas Curva Mestra / Armas / Armaduras / Bestiario)
A3: 1. Resolução de ataque
A4: d20 + Bônus de Ataque(atacante) >= Defesa(alvo) -> acerta
A5: Regra de dado: natural 1 = sempre erra<br>natural 20 = sempre acerta
A6: Chance de acerto = (21 - (Defesa alvo - seu Bônus Ataque)) / 20, entre 5% e 95%
A8: 2. Dano
A9: Dano = ARREDONDA(DanoBaseTier(Tier,Raridade) x ModTipo x ModVariação, 0) — ver detalhe completo na Seção 8
A10: Adaga x0,8 (ver Seção 8: 25% chance de golpe extra a 50% do dano — NÃO é 2 ataques garantidos)<br>Espada x1,0<br>Machado x1,2<br>Maça x1,1
A11: Arco x0,9 (sempre 2 mãos)<br>Manopla x0,85 (sem golpe extra — Atordoamento é a identidade dela)<br>Cetro x0,7
A14: 3. Defesa
A15: Defesa = soma dos 8 slots equipados + mod. DES
A16: Peso de cada slot no orçamento de Defesa do tier:
... A159: Colunas novas em Missoes: Categoria, Requisito_Honra, Requisito_Nivel, Requisito_Quest_Previa, Requisito_Faccao, Requisito_Condicao_Texto, Recompensa_Item.

Sheet Motor do Mestre
A1: Motor do Mestre — gera encontro, loot, quests e cidade em 1 clique
A2: Mude o Tier abaixo e edite a célula (ou F9) pra sortear de novo.
A4: TIER DO GRUPO: | B4: Sucata Enferrujada
A6: 1. ENCONTRO SORTEADO
A7: Rolagem de Papel (d100) | B7: =RANDBETWEEN(1,100)
A8: Papel sorteado (55% Comum / 30% Elite / 15% Boss) | B8: =ifs($B$7<=55,"Comum",$B$7<=85,"Elite",TRUE(),"Boss")
A9: Monstro sorteado | B9: =INDEX(filter(Bestiario!$B$12:$B$700,Bestiario!$A$12:$A$700=$B$4,Bestiario!$C$12:$C$700=$B$8),RANDBETWEEN(1,COUNTIFS(Bestiario!$A$12:$A$700,$B$4,Bestiario!$C$12:$C$700,$B$8)))
A10: Nível | B10: =IFERROR(INDEX(Bestiario!$D$12:$D$700,MATCH($B$9,Bestiario!$B$12:$B$700,0)),"")
A11: HP | B11: =IFERROR(INDEX(Bestiario!$E$12:$E$700,MATCH($B$9,Bestiario!$B$12:$B$700,0)),"")
A12: Dano | B12: =IFERROR(INDEX(Bestiario!$F$12:$F$700,MATCH($B$9,Bestiario!$B$12:$B$700,0)),"")
A13: Defesa | B13: =IFERROR(INDEX(Bestiario!$G$12:$G$700,MATCH($B$9,Bestiario!$B$12:$B$700,0)),"")
A14: Golpe Especial | B14: =IFERROR(INDEX(Bestiario!$I$12:$I$700,MATCH($B$9,Bestiario!$B$12:$B$700,0)),"")
A15: Efeito do Golpe | B15: =IFERROR(INDEX(Bestiario!$J$12:$J$700,MATCH($B$9,Bestiario!$B$12:$B$700,0)),"")
A17: 2. LOOT SORTEADO
A18: Tipo de Arma | B18: =INDEX(Armas!$A$5:$A$11,RANDBETWEEN(1,7))
A19: Rolagem de Raridade (d100) | B19: =RANDBETWEEN(1,100)
A20: Raridade (60% Comum / 30% Raro / 10% Lendário) | B20: =ifs($B$19<=60,"Comum",$B$19<=90,"Raro",TRUE(),"Lendario")
A21: Nº do Tier atual (auxiliar) | B21: =MATCH($B$4,Tiers!$B$9:$B$22,0)
A22: Variação sorteada (se Comum/Raro) | B22: =IF($B$20="Lendario","(ver linha de Lendário abaixo)",INDEX(filter(Armas!$C$15:$C$322,Armas!$A$15:$A$322=$B$4,Armas!$B$15:$B$322=$B$18),RANDBETWEEN(1,COUNTIFS(Armas!$A$15:$A$322,$B$4,Armas!$B$15:$B$322,$B$18))))
A23: Dano do item (Comum ou Raro) | B23: =IFERROR(IF($B$20="Comum",INDEX(Armas!$I$15:$I$322,MATCH($B$22,Armas!$C$15:$C$322,0)),IF($B$20="Raro",INDEX(Armas!$J$15:$J$322,MATCH($B$22,Armas!$C$15:$C$322,0)),"")),"")
A24: Efeito Especial do item | B24: =IFERROR(INDEX(Armas!$D$15:$D$322,MATCH($B$22,Armas!$C$15:$C$322,0)),"")
A25: Lendário sorteado (se Lendario) | B25: =IF($B$20<>"Lendario","",IFERROR(INDEX(filter('Artefatos e Relíquias'!$C$5:$C$90,'Artefatos e Relíquias'!$L$5:$L$90="Lendário",LEFT('Artefatos e Relíquias'!$D$5:$D$90,4)="Arma",ISNUMBER(SEARCH("Tier "&$B$21&" ",'Artefatos e Relíquias'!$E$5:$E$90))),RANDBETWEEN(1,COUNTIFS('Artefatos e Relíquias'!$L$5:$L$90,"Lendário",'Artefatos e Relíquias'!$D$5:$D$90,"Arma*",'Artefatos e Relíquias'!$E$5:$E$90,"*Tier "&$B$21&" *"))),"(nenhum Lendário de arma cadastrado nesse tier)"))
A26: Descrição final | B26: =IF($B$20="Lendario","1 "&$B$25,"1 "&$B$18&" — "&$B$22&" ("&$B$20&") — Dano "&$B$23&IF($B$24<>"",", Efeito: "&$B$24,""))
A30: 3. MISSÕES DISPONÍVEIS NESTE TIER
A31: Nome | B31: Tipo | C31: Objetivo | D31: Recompensa
A32: =IFERROR(filter(Missoes!$B$16:$E$400,Missoes!$A$16:$A$400=$B$4),"(nenhuma cadastrada)")
A67: LOCAL ATUAL (pra Perigo): | B67: Vila Inicial
A68: Perigo do Local (1-5) | B68: =IFERROR(INDEX('Mundo - Locais'!$L$5:$L$130,MATCH($B$67,'Mundo - Locais'!$A$5:$A$130,0)),3)
A69: 4. CIDADE / MERCADOR DA REGIÃO
A70: Cidade | B70: Teto de Tier p/ Venda | C70: Custo de Descanso (Ouro) | D70: Descrição
A71: =IFERROR(filter('Cidades e NPCs'!$A$20:$A$26,ISNUMBER(SEARCH($B$4,'Cidades e NPCs'!$B$20:$B$26))),"") | B71: =IFERROR(filter('Cidades e NPCs'!$F$20:$F$26,ISNUMBER(SEARCH($B$4,'Cidades e NPCs'!$B$20:$B$26))),"") | C71: =IFERROR(filter('Cidades e NPCs'!$G$20:$G$26,ISNUMBER(SEARCH($B$4,'Cidades e NPCs'!$B$20:$B$26))),"") | D71: =IFERROR(filter('Cidades e NPCs'!$E$20:$E$26,ISNUMBER(SEARCH($B$4,'Cidades e NPCs'!$B$20:$B$26))),"")
A73: 5. ENCONTRO ALEATÓRIO DE EXPLORAÇÃO (1d100) | D73: Perigo | E73: Nada até | F73: Comum até | G73: Elite até | H73: AmeaçaSup até | I73: Boss até
A74: Rolagem (1d100) | B74: =RANDBETWEEN(1,100) | D74: 1 | E74: 70 | F74: 90 | G74: 97 | H74: 99 | I74: 99
A75: Resultado (tabela de Perigo do local selecionado) | B75: =ifs($B$74<=INDEX($E$74:$E$78,MATCH($B$68,$D$74:$D$78,0)),"Nada acontece",$B$74<=INDEX($F$74:$F$78,MATCH($B$68,$D$74:$D$78,0)),"Monstro Comum do tier atual",$B$74<=INDEX($G$74:$G$78,MATCH($B$68,$D$74:$D$78,0)),"Monstro Elite do tier atual",$B$74<=INDEX($H$74:$H$78,MATCH($B$68,$D$74:$D$78,0)),"Ameaça Superior (próximo tier)",$B$74<=INDEX($I$74:$I$78,MATCH($B$68,$D$74:$D$78,0)),"Emboscada de Boss do tier atual",TRUE(),"Achado raro (loot sem combate)") | D75: 2 | E75: 60 | F75: 83 | G75: 94 | H75: 98 | I75: 99
A76: Tier a usar no sorteio | B76: =IF($B$75="Ameaça Superior (próximo tier)",IFERROR(INDEX(Tiers!$B$9:$B$22,MATCH($B$4,Tiers!$B$9:$B$22,0)+1),"(já é o último tier)"),$B$4) | D76: 3 | E76: 50 | F76: 75 | G76: 87 | H76: 95 | I76: 99
A77: Papel a sortear | B77: =ifs($B$75="Monstro Comum do tier atual","Comum",$B$75="Monstro Elite do tier atual","Elite",$B$75="Ameaça Superior (próximo tier)","Elite",$B$75="Emboscada de Boss do tier atual","Boss",TRUE(),"") | D77: 4 | E77: 35 | F77: 63 | G77: 80 | H77: 93 | I77: 99
A78: Monstro sorteado (se aplicável) | B78: =IF($B$77="","— (sem combate neste resultado)",INDEX(filter(Bestiario!$B$12:$B$718,Bestiario!$A$12:$A$718=$B$76,Bestiario!$C$12:$C$718=$B$77),RANDBETWEEN(1,COUNTIFS(Bestiario!$A$12:$A$718,$B$76,Bestiario!$C$12:$C$718,$B$77)))) | D78: 5 | E78: 20 | F78: 45 | G78: 65 | H78: 85 | I78: 97

Sheet Curva Mestra
A1: Curva Mestra de Progressão
A2: Parametros em azul podem ser ajustados - tudo abaixo recalcula automaticamente.
A4: Parametro | B4: Valor | C4: O que controla | K4: Parametro XP | L4: Valor | N4: Parametro Mana | O4: Valor
A5: HP_base | B5: 18 | C5: HP inicial no nivel 1 (parte fixa) | K5: XP_base | L5: 50 | N5: Mana_base | O5: 10
A6: HP_lin | B6: 6 | C6: Crescimento linear de HP por nivel | K6: XP_lin | L6: 20 | N6: Mana_lin | O6: 4
A7: HP_quad | B7: 0.35 | C7: Crescimento acelerado de HP (nivel ao quadrado) | K7: XP_quad | L7: 3 | N7: Mana_quad | O7: 0.5
A8: Mult_MonstroComum | B8: 0.5 | C8: HP do monstro comum = HP jogador x este valor
A9: Mult_MonstroElite | B9: 1.2 | C9: HP do monstro elite = HP jogador x este valor
A10: Mult_MonstroBoss | B10: 1.35 | C10: HP do boss = HP jogador x este valor
A11: Mult_MonstroCosmico | B11: 2.2 | C11: HP de entidade cosmica = HP jogador x este valor
A12: Divisor_DanoArma | B12: 5 | C12: Dano de arma padrao = HP monstro comum / este valor
A13: Defesa_base | B13: 5 | C13: Defesa esperada no nivel 1
A14: Defesa_lin | B14: 0.9 | C14: Crescimento de Defesa por nivel
A15: AtqBonus_base | B15: 2 | C15: Bonus de ataque no nivel 1
A16: AtqBonus_lin | B16: 0.9 | C16: Crescimento do bonus de ataque por nivel
A18: Tabela por Nivel (1 a 75)
A19: Nivel | B19: HP Jogador | C19: Dano Arma Padrao (comum) | D19: Defesa Esperada | E19: Bonus de Ataque | F19: HP Monstro Comum | G19: HP Monstro Elite | H19: HP Monstro Boss | I19: HP Entidade Cosmica | J19: XP p/ Prox. Nivel | M19: Mana Jogador
A20: 1 | B20: =ROUND($B$5+$B$6*A20+$B$7*A20^2,0) | C20: =ROUND(F20/$B$12,0) | D20: =ROUND($B$13+$B$14*A20,0) | E20: =ROUND($B$15+$B$16*A20,0) | F20: =ROUND(B20*$B$8,0) | G20: =ROUND(B20*$B$9,0) | H20: =ROUND(B20*$B$10,0) | I20: =ROUND(B20*$B$11,0) | J20: =ROUND($L$5+$L$6*A20+$L$7*A20^2,0) | M20: =ROUND($O$5+$O$6*A20+$O$7*A20^2,0)
A21: 2 | B21: =ROUND($B$5+$B$6*A21+$B$7*A21^2,0) | C21: =ROUND(F21/$B$12,0) | D21: =ROUND($B$13+$B$14*A21,0) | E21: =ROUND($B$15+$B$16*A21,0) | F21: =ROUND(B21*$B$8,0) | G21: =ROUND(B21*$B$9,0) | H21: =ROUND(B21*$B$10,0) | I21: =ROUND(B21*$B$11,0) | J21: =ROUND($L$5+$L$6*A21+$L$7*A21^2,0) | M21: =ROUND($O$5+$O$6*A21+$O$7*A21^2,0)
A22: 3 | B22: =ROUND($B$5+$B$6*A22+$B$7*A22^2,0) | C22: =ROUND(F22/$B$12,0) | D22: =ROUND($B$13+$B$14*A22,0) | E22: =ROUND($B$15+$B$16*A22,0) | F22: =ROUND(B22*$B$8,0) | G22: =ROUND(B22*$B$9,0) | H22: =ROUND(B22*$B$10,0) | I22: =ROUND(B22*$B$11,0) | J22: =ROUND($L$5+$L$6*A22+$L$7*A22^2,0) | M22: =ROUND($O$5+$O$6*A22+$O$7*A22^2,0)
A23: 4 | B23: =ROUND($B$5+$B$6*A23+$B$7*A23^2,0) | C23: =ROUND(F23/$B$12,0) | D23: =ROUND($B$13+$B$14*A23,0) | E23: =ROUND($B$15+$B$16*A23,0) | F23: =ROUND(B23*$B$8,0) | G23: =ROUND(B23*$B$9,0) | H23: =ROUND(B23*$B$10,0) | I23: =ROUND(B23*$B$11,0) | J23: =ROUND($L$5+$L$6*A23+$L$7*A23^2,0) | M23: =ROUND($O$5+$O$6*A23+$O$7*A23^2,0)
A24: 5 | B24: =ROUND($B$5+$B$6*A24+$B$7*A24^2,0) | C24: =ROUND(F24/$B$12,0) | D24: =ROUND($B$13+$B$14*A24,0) | E24: =ROUND($B$15+$B$16*A24,0) | F24: =ROUND(B24*$B$8,0) | G24: =ROUND(B24*$B$9,0) | H24: =ROUND(B24*$B$10,0) | I24: =ROUND(B24*$B$11,0) | J24: =ROUND($L$5+$L$6*A24+$L$7*A24^2,0) | M24: =ROUND($O$5+$O$6*A24+$O$7*A24^2,0)
A25: 6 | B25: =ROUND($B$5+$B$6*A25+$B$7*A25^2,0) | C25: =ROUND(F25/$B$12,0) | D25: =ROUND($B$13+$B$14*A25,0) | E25: =ROUND($B$15+$B$16*A25,0) | F25: =ROUND(B25*$B$8,0) | G25: =ROUND(B25*$B$9,0) | H25: =ROUND(B25*$B$10,0) | I25: =ROUND(B25*$B$11,0) | J25: =ROUND($L$5+$L$6*A25+$L$7*A25^2,0) | M25: =ROUND($O$5+$O$6*A25+$O$7*A25^2,0)
A26: 7 | B26: =ROUND($B$5+$B$6*A26+$B$7*A26^2,0) | C26: =ROUND(F26/$B$12,0) | D26: =ROUND($B$13+$B$14*A26,0) | E26: =ROUND($B$15+$B$16*A26,0) | F26: =ROUND(B26*$B$8,0) | G26: =ROUND(B26*$B$9,0) | H26: =ROUND(B26*$B$10,0) | I26: =ROUND(B26*$B$11,0) | J26: =ROUND($L$5+$L$6*A26+$L$7*A26^2,0) | M26: =ROUND($O$5+$O$6*A26+$O$7*A26^2,0)
A27: 8 | B27: =ROUND($B$5+$B$6*A27+$B$7*A27^2,0) | C27: =ROUND(F27/$B$12,0) | D27: =ROUND($B$13+$B$14*A27,0) | E27: =ROUND($B$15+$B$16*A27,0) | F27: =ROUND(B27*$B$8,0) | G27: =ROUND(B27*$B$9,0) | H27: =ROUND(B27*$B$10,0) | I27: =ROUND(B27*$B$11,0) | J27: =ROUND($L$5+$L$6*A27+$L$7*A27^2,0) | M27: =ROUND($O$5+$O$6*A27+$O$7*A27^2,0)
A28: 9 | B28: =ROUND($B$5+$B$6*A28+$B$7*A28^2,0) | C28: =ROUND(F28/$B$12,0) | D28: =ROUND($B$13+$B$14*A28,0) | E28: =ROUND($B$15+$B$16*A28,0) | F28: =ROUND(B28*$B$8,0) | G28: =ROUND(B28*$B$9,0) | H28: =ROUND(B28*$B$10,0) | I28: =ROUND(B28*$B$11,0) | J28: =ROUND($L$5+$L$6*A28+$L$7*A28^2,0) | M28: =ROUND($O$5+$O$6*A28+$O$7*A28^2,0)
A29: 10 | B29: =ROUND($B$5+$B$6*A29+$B$7*A29^2,0) | C29: =ROUND(F29/$B$12,0) | D29: =ROUND($B$13+$B$14*A29,0) | E29: =ROUND($B$15+$B$16*A29,0) | F29: =ROUND(B29*$B$8,0) | G29: =ROUND(B29*$B$9,0) | H29: =ROUND(B29*$B$10,0) | I29: =ROUND(B29*$B$11,0) | J29: =ROUND($L$5+$L$6*A29+$L$7*A29^2,0) | M29: =ROUND($O$5+$O$6*A29+$O$7*A29^2,0)
A30: 11 | B30: =ROUND($B$5+$B$6*A30+$B$7*A30^2,0) | C30: =ROUND(F30/$B$12,0) | D30: =ROUND($B$13+$B$14*A30,0) | E30: =ROUND($B$15+$B$16*A30,0) | F30: =ROUND(B30*$B$8,0) | G30: =ROUND(B30*$B$9,0) | H30: =ROUND(B30*$B$10,0) | I30: =ROUND(B30*$B$11,0) | J30: =ROUND($L$5+$L$6*A30+$L$7*A30^2,0) | M30: =ROUND($O$5+$O$6*A30+$O$7*A30^2,0)
A31: 12 | B31: =ROUND($B$5+$B$6*A31+$B$7*A31^2,0) | C31: =ROUND(F31/$B$12,0) | D31: =ROUND($B$13+$B$14*A31,0) | E31: =ROUND($B$15+$B$16*A31,0) | F31: =ROUND(B31*$B$8,0) | G31: =ROUND(B31*$B$9,0) | H31: =ROUND(B31*$B$10,0) | I31: =ROUND(B31*$B$11,0) | J31: =ROUND($L$5+$L$6*A31+$L$7*A31^2,0) | M31: =ROUND($O$5+$O$6*A31+$O$7*A31^2,0)
... A94: 75 | B94: =ROUND($B$5+$B$6*A94+$B$7*A94^2,0) | C94: =ROUND(F94/$B$12,0) | D94: =ROUND($B$13+$B$14*A94,0) | E94: =ROUND($B$15+$B$16*A94,0) | F94: =ROUND(B94*$B$8,0) | G94: =ROUND(B94*$B$9,0) | H94: =ROUND(B94*$B$10,0) | I94: =ROUND(B94*$B$11,0) | J94: =ROUND($L$5+$L$6*A94+$L$7*A94^2,0) | M94: =ROUND($O$5+$O$6*A94+$O$7*A94^2,0)
A97: Modificador de Atributo (regra universal)
A98: Modificador = FLOOR((Atributo-10)/2). Atributo 10 = modificador 0 (bate com a Curva Mestra padrao).
A99: - FOR (Forca): soma no Bonus de Ataque corpo-a-corpo (Espada, Adaga, Machado, Maca, Manopla).
A100: - DES (Destreza): soma no Bonus de Ataque a distancia (Arco) e em rolagens de Fuga.
A101: - CON (Constituicao): soma HP extra = Modificador de CON x Nivel do personagem.
A102: - INT (Inteligencia): soma no dano de Habilidades/Magia (ver aba Magia e Habilidades).
A103: - SAB (Sabedoria): soma em rolagens de Percepcao (ler perigo antes de um combate).
A104: - CAR (Carisma): reduz preco de compra em lojas em 2% por ponto de modificador.
A105: Atributo | B105: Modificador
A106: 1 | B106: =INT((A106-10)/2)
A107: 2 | B107: =INT((A107-10)/2)
A108: 3 | B108: =INT((A108-10)/2)
A109: 4 | B109: =INT((A109-10)/2)
A110: 5 | B110: =INT((A110-10)/2)
A111: 6 | B111: =INT((A111-10)/2)
A112: 7 | B112: =INT((A112-10)/2)
A113: 8 | B113: =INT((A113-10)/2)
A114: 9 | B114: =INT((A114-10)/2)
A115: 10 | B115: =INT((A115-10)/2)
A116: 11 | B116: =INT((A116-10)/2)
A117: 12 | B117: =INT((A117-10)/2)
... A125: 20 | B125: =INT((A125-10)/2)

Sheet Tiers
A1: Tabela de Tiers de Equipamento
A2: Dano calculado automaticamente a partir da Curva Mestra, no nivel medio do tier.
A4: Multiplicador Raro | B4: 1.15
A5: Multiplicador Lendario | B5: 1.3
A8: # | B8: Tier | C8: Nivel Min | D8: Nivel Max | E8: Nivel Ref. | F8: Cor (hex) | G8: Dano Comum | H8: Dano Raro | I8: Dano Lendario | J8: Local de Obtenção | K8: Historia do Material | L8: Habilidade Lendaria (so na versao Lendario)
A9: 1 | B9: Sucata Enferrujada | C9: 1 | D9: 5 | E9: =ROUND((C9+D9)/2,0) | F9: #8B4A2B | G9: =ROUND(INDEX('Curva Mestra'!$C$20:$C$94,MATCH(E9,'Curva Mestra'!$A$20:$A$94,0)),0) | H9: =ROUND(G9*$B$4,0) | I9: =ROUND(G9*$B$5,0) | J9: Estrada dos Bandidos (loot de bandidos) — encontrado livremente, sem requisito | K9: Ferro velho demais ate pra derreter de novo - mas ainda corta, e e o que se tem. | L9: Sem propriedade especial - resistente o bastante pra nao quebrar facil.
A10: 2 | B10: Bronze | C10: 6 | D10: 10 | E10: =ROUND((C10+D10)/2,0) | F10: #B5651D | G10: =ROUND(INDEX('Curva Mestra'!$C$20:$C$94,MATCH(E10,'Curva Mestra'!$A$20:$A$94,0)),0) | H10: =ROUND(G10*$B$4,0) | I10: =ROUND(G10*$B$5,0) | J10: Mina de Bronze (Valória) | K10: As primeiras minas da regiao. Ninguem lembra quem cavou primeiro - so quem nunca saiu. | L10: Reduz o custo de descanso na estalagem em 10%.
A11: 3 | B11: Ferro | C11: 11 | D11: 15 | E11: =ROUND((C11+D11)/2,0) | F11: #6E7378 | G11: =ROUND(INDEX('Curva Mestra'!$C$20:$C$94,MATCH(E11,'Curva Mestra'!$A$20:$A$94,0)),0) | H11: =ROUND(G11*$B$4,0) | I11: =ROUND(G11*$B$5,0) | J11: Ruínas da Antiga Forja (Cinzenta) — requer forja construída (primeiro marco de crafting) | K11: Forjado as pressas quando bandidos deixaram de ser o unico perigo na estrada. | L11: +1 de Ataque adicional (fabricacao confiavel).
A12: 4 | B12: Prata | C12: 16 | D12: 20 | E12: =ROUND((C12+D12)/2,0) | F12: #C7C7CC | G12: =ROUND(INDEX('Curva Mestra'!$C$20:$C$94,MATCH(E12,'Curva Mestra'!$A$20:$A$94,0)),0) | H12: =ROUND(G12*$B$4,0) | I12: =ROUND(G12*$B$5,0) | J12: Criptas de Prata (Cinzenta) — minerado em meio a mortos-vivos (bônus vs. undead) | K12: Prateado o bastante pra brilhar na escuridao das criptas - o que atrai tanto quanto afasta. | L12: +50% de dano contra mortos-vivos.
A13: 5 | B13: Aco Elfico | C13: 21 | D13: 25 | E13: =ROUND((C13+D13)/2,0) | F13: #7A8B4A | G13: =ROUND(INDEX('Curva Mestra'!$C$20:$C$94,MATCH(E13,'Curva Mestra'!$A$20:$A$94,0)),0) | H13: =ROUND(G13*$B$4,0) | I13: =ROUND(G13*$B$5,0) | J13: Ruínas Élficas (Ecoril) — comércio com ruínas élficas ou saque de elite específico | K13: Dobrado, nao martelado. Os elfos nunca explicaram a diferenca a ninguem de fora. | L13: Ignora 2 pontos de Defesa de inimigos com armadura pesada.
A14: 6 | B14: Mecanismo Anao | C14: 26 | D14: 30 | E14: =ROUND((C14+D14)/2,0) | F14: #C08A3E | G14: =ROUND(INDEX('Curva Mestra'!$C$20:$C$94,MATCH(E14,'Curva Mestra'!$A$20:$A$94,0)),0) | H14: =ROUND(G14*$B$4,0) | I14: =ROUND(G14*$B$5,0) | J14: Câmara Mecânica Anã (Ecoril) — dungeon anã com puzzle mecânico | K14: Engrenagem sobre engrenagem - os anoes pararam de contar quantas pecas um machado precisa. | L14: 1x por combate, repete um ataque que errou.
A15: 7 | B15: Vidro Vulcanico | C15: 31 | D15: 35 | E15: =ROUND((C15+D15)/2,0) | F15: #4FA89B | G15: =ROUND(INDEX('Curva Mestra'!$C$20:$C$94,MATCH(E15,'Curva Mestra'!$A$20:$A$94,0)),0) | H15: =ROUND(G15*$B$4,0) | I15: =ROUND(G15*$B$5,0) | J15: Fenda Vulcânica Ativa (Rocha Alta) — mineral raro perto de fendas vulcânicas ativas | K15: Formado onde a rocha derretida encontrou o ar frio demais rapido demais. Corta como promessa quebrada. | L15: Ataques tem 10% de chance de causar Queimadura (2 de dano/turno por 2 turnos).
A16: 8 | B16: Ferro Orquico | C16: 36 | D16: 40 | E16: =ROUND((C16+D16)/2,0) | F16: #4B5320 | G16: =ROUND(INDEX('Curva Mestra'!$C$20:$C$94,MATCH(E16,'Curva Mestra'!$A$20:$A$94,0)),0) | H16: =ROUND(G16*$B$4,0) | I16: =ROUND(G16*$B$5,0) | J16: Acampamento Orc (Rocha Alta) — só dropa do chefe do bando (não se compra/mina) | K16: Nao se mina - se toma. Cada peca ja teve dono antes de ser sua. | L16: +2 de dano contra alvos Elite ou Boss.
A17: 9 | B17: Mithril | C17: 41 | D17: 45 | E17: =ROUND((C17+D17)/2,0) | F17: #6FA8DC | G17: =ROUND(INDEX('Curva Mestra'!$C$20:$C$94,MATCH(E17,'Curva Mestra'!$A$20:$A$94,0)),0) | H17: =ROUND(G17*$B$4,0) | I17: =ROUND(G17*$B$5,0) | J17: Cavernas Profundas de Mithril (Abismar) — guardadas por elemental | K17: Leve como se nao devesse existir. Ninguem sabe dizer se e metal ou memoria de metal. | L17: Reduz em 1 o custo de Mana de habilidades, se equipado por um conjurador.
A18: 10 | B18: Ebano | C18: 46 | D18: 50 | E18: =ROUND((C18+D18)/2,0) | F18: #2E2A3D | G18: =ROUND(INDEX('Curva Mestra'!$C$20:$C$94,MATCH(E18,'Curva Mestra'!$A$20:$A$94,0)),0) | H18: =ROUND(G18*$B$4,0) | I18: =ROUND(G18*$B$5,0) | J18: Fenda Vulcânica Morta (Abismar) | K18: Do outro lado da mesma fenda que deu o vidro - so que fria, morta, silenciosa. | L18: Ataques a noite ou no escuro causam +15% de dano.
A19: 11 | B19: Adamantina | C19: 51 | D19: 56 | E19: =ROUND((C19+D19)/2,0) | F19: #6E0E23 | G19: =ROUND(INDEX('Curva Mestra'!$C$20:$C$94,MATCH(E19,'Curva Mestra'!$A$20:$A$94,0)),0) | H19: =ROUND(G19*$B$4,0) | I19: =ROUND(G19*$B$5,0) | J19: Covil do Titã (Alto Bastião) — só dropa de bosses de tier | K19: Nao se encontra. Se herda de quem perdeu a luta pra guardar. | L19: Ignora a primeira reducao de dano por Defesa em cada combate.
A20: 12 | B20: Osso de Dragao | C20: 57 | D20: 62 | E20: =ROUND((C20+D20)/2,0) | F20: #E8DCC4 | G20: =ROUND(INDEX('Curva Mestra'!$C$20:$C$94,MATCH(E20,'Curva Mestra'!$A$20:$A$94,0)),0) | H20: =ROUND(G20*$B$4,0) | I20: =ROUND(G20*$B$5,0) | J20: Covil do Dragão Ancião (Alto Bastião) — exige abater um dragão | K20: Ainda quente ao toque, anos depois da ultima respiracao do dono. | L20: +3 de dano contra Dragoes e criaturas Cosmicas.
... A22: 14 | B22: Estelar / Cosmico | C22: 70 | D22: 75 | E22: =ROUND((C22+D22)/2,0) | F22: #8E44AD | G22: =ROUND(INDEX('Curva Mestra'!$C$20:$C$94,MATCH(E22,'Curva Mestra'!$A$20:$A$94,0)),0) | H22: =ROUND(G22*$B$4,0) | I22: =ROUND(G22*$B$5,0) | J22: Portal Estelar (O Limiar) — só loot de entidades | K22: Nao veio deste mundo, e talvez esteja tentando voltar pra casa atraves de voce. | L22: Ignora completamente a Defesa do alvo, uma vez por combate.

Sheet Como Usar
A1: Como Usar Esta Planilha
A3: 1. Curva Mestra - e o motor de tudo. Define quanto HP um personagem/monstro tem em
A4: cada nivel, e qual o dano de arma padrao esperado. Se algo parecer fraco ou forte
A5: demais durante o jogo real, ajuste os parametros em azul no topo dessa aba - todos
A6: os 75 niveis recalculam sozinhos.
A8: 2. Tiers - cada um dos 14 tiers de equipamento busca automaticamente o dano correspondente
A9: ao seu nivel medio na Curva Mestra. Raro e Lendario sao multiplicadores sobre o dano
A10: comum (ajustaveis em B4 e B5 no topo da aba Tiers).
A12: 3. Cores - a coluna Cor (hex) ja esta pintada com a cor real de cada tier. Use esse
A13: hex direto no design das cartas/HUD dos itens.
A15: 4. Convencao de cores do texto:
A16: - Azul = numero que voce pode/deve ajustar (parametro)
... A23: seu amigo chegar.

Sheet Armas
A1: Catalogo Completo de Armas
A2: Dano puxado automaticamente da aba Tiers. Ajuste os modificadores em azul abaixo.
A4: Tipo de Arma | B4: Multiplicador | C4: Ataques por Turno | D4: Nota | E4: Pode 2 Maos? | F4: Bonus Dano (2 maos)
A5: Adaga | B5: 0.8 | C5: 1 | D5: Ver Regras e Fórmulas Seção 8: 25% chance de golpe extra a 50% do dano ao acertar (não é multiplicação fixa) | E5: Nao | F5: 1
A6: Espada | B6: 1 | C6: 1 | D6: Equilibrada - referencia do sistema | E6: Sim (opcional) | F6: 1.2
A7: Machado | B7: 1.2 | C7: 1 | D7: Maior dano bruto do sistema — sem penalidade de ataque | E7: Sim (opcional) | F7: 1.25
A8: Maca | B8: 1.1 | C8: 1 | D8: Impacto/controle — afinidade com Ignora Defesa só em Variações específicas com esse efeito | E8: Sim (opcional) | F8: 1.2
A9: Arco | B9: 0.9 | C9: 1 | D9: Ataca a distancia, seguranca | E9: Sempre (obrigatorio) | F9: 1
A10: Manopla | B10: 0.85 | C10: 1 | D10: Sem golpe adicional — identidade é Atordoamento (20% de chance ao acertar) | E10: Nao | F10: 1
A11: Cetro | B11: 0.7 | C11: 1 | D11: Soma no dano magico, se houver magia no sistema | E11: Nao | F11: 1
A14: Tier | B14: Tipo | C14: Variação (nome completo) | D14: Efeito Especial | E14: Lore | F14: Dano Base Comum | G14: Dano Base Raro | H14: Mod. Tipo | I14: Dano Comum | J14: Dano Raro | K14: Mod. Variação | L14: Preço Venda Comum | M14: Preço Venda Raro
A15: Sucata Enferrujada | B15: Espada | C15: Espada de Sucata Enferrujada | E15: Lâmina de sucata amarrada com arame — corta, mas reclama a cada golpe. | F15: =INDEX(Tiers!$G$9:$G$22,MATCH($A15,Tiers!$B$9:$B$22,0)) | G15: =INDEX(Tiers!$H$9:$H$22,MATCH($A15,Tiers!$B$9:$B$22,0)) | H15: =INDEX($B$5:$B$11,MATCH($B15,$A$5:$A$11,0)) | I15: =ROUND(F15*H15*K15,0) | J15: =ROUND(G15*H15*K15,0) | K15: 1 | L15: =ROUND(I15*8,0) | M15: =ROUND(J15*10,0)
A16: Sucata Enferrujada | B16: Espada | C16: Espada Trincada | E16: Rachada perto do cabo; ainda serve, ninguém sabe até quando. | F16: =INDEX(Tiers!$G$9:$G$22,MATCH($A16,Tiers!$B$9:$B$22,0)) | G16: =INDEX(Tiers!$H$9:$H$22,MATCH($A16,Tiers!$B$9:$B$22,0)) | H16: =INDEX($B$5:$B$11,MATCH($B16,$A$5:$A$11,0)) | I16: =ROUND(F16*H16*K16,0) | J16: =ROUND(G16*H16*K16,0) | K16: 1 | L16: =ROUND(I16*8,0) | M16: =ROUND(J16*10,0)
A17: Sucata Enferrujada | B17: Espada | C17: Espada Serrilhada | D17: Sangramento | E17: Dentes de serra improvisados — não corta limpo, mas não deixa esquecer. | F17: =INDEX(Tiers!$G$9:$G$22,MATCH($A17,Tiers!$B$9:$B$22,0)) | G17: =INDEX(Tiers!$H$9:$H$22,MATCH($A17,Tiers!$B$9:$B$22,0)) | H17: =INDEX($B$5:$B$11,MATCH($B17,$A$5:$A$11,0)) | I17: =ROUND(F17*H17*K17,0) | J17: =ROUND(G17*H17*K17,0) | K17: 0.95 | L17: =ROUND(I17*8,0) | M17: =ROUND(J17*10,0)
A18: Sucata Enferrujada | B18: Espada | C18: Espada de Poda Afiada | E18: Ferramenta de colheita virada arma — mata com o que sobrou da lavoura. | F18: =INDEX(Tiers!$G$9:$G$22,MATCH($A18,Tiers!$B$9:$B$22,0)) | G18: =INDEX(Tiers!$H$9:$H$22,MATCH($A18,Tiers!$B$9:$B$22,0)) | H18: =INDEX($B$5:$B$11,MATCH($B18,$A$5:$A$11,0)) | I18: =ROUND(F18*H18*K18,0) | J18: =ROUND(G18*H18*K18,0) | K18: 1 | L18: =ROUND(I18*8,0) | M18: =ROUND(J18*10,0)
A19: Sucata Enferrujada | B19: Machado | C19: Machado de Sucata | E19: Cabeça de metal retorcido presa num cabo qualquer — pesa o bastante pra doer. | F19: =INDEX(Tiers!$G$9:$G$22,MATCH($A19,Tiers!$B$9:$B$22,0)) | G19: =INDEX(Tiers!$H$9:$H$22,MATCH($A19,Tiers!$B$9:$B$22,0)) | H19: =INDEX($B$5:$B$11,MATCH($B19,$A$5:$A$11,0)) | I19: =ROUND(F19*H19*K19,0) | J19: =ROUND(G19*H19*K19,0) | K19: 1 | L19: =ROUND(I19*8,0) | M19: =ROUND(J19*10,0)
A20: Sucata Enferrujada | B20: Machado | C20: Machado Cego | D20: Ignora Defesa | E20: Já não corta, só esmaga — e isso já basta. | F20: =INDEX(Tiers!$G$9:$G$22,MATCH($A20,Tiers!$B$9:$B$22,0)) | G20: =INDEX(Tiers!$H$9:$H$22,MATCH($A20,Tiers!$B$9:$B$22,0)) | H20: =INDEX($B$5:$B$11,MATCH($B20,$A$5:$A$11,0)) | I20: =ROUND(F20*H20*K20,0) | J20: =ROUND(G20*H20*K20,0) | K20: 0.96 | L20: =ROUND(I20*8,0) | M20: =ROUND(J20*10,0)
A21: Sucata Enferrujada | B21: Machado | C21: Machado de Lenhador Reforçado | E21: Feito pra árvore, adaptado pra carne. | F21: =INDEX(Tiers!$G$9:$G$22,MATCH($A21,Tiers!$B$9:$B$22,0)) | G21: =INDEX(Tiers!$H$9:$H$22,MATCH($A21,Tiers!$B$9:$B$22,0)) | H21: =INDEX($B$5:$B$11,MATCH($B21,$A$5:$A$11,0)) | I21: =ROUND(F21*H21*K21,0) | J21: =ROUND(G21*H21*K21,0) | K21: 1.05 | L21: =ROUND(I21*8,0) | M21: =ROUND(J21*10,0)
A22: Sucata Enferrujada | B22: Machado | C22: Machado Duplo Improvisado | E22: Duas lâminas de sucata soldadas — desequilibrado, mas assusta. | F22: =INDEX(Tiers!$G$9:$G$22,MATCH($A22,Tiers!$B$9:$B$22,0)) | G22: =INDEX(Tiers!$H$9:$H$22,MATCH($A22,Tiers!$B$9:$B$22,0)) | H22: =INDEX($B$5:$B$11,MATCH($B22,$A$5:$A$11,0)) | I22: =ROUND(F22*H22*K22,0) | J22: =ROUND(G22*H22*K22,0) | K22: 1.05 | L22: =ROUND(I22*8,0) | M22: =ROUND(J22*10,0)
A23: Sucata Enferrujada | B23: Arco | C23: Arco de Sucata | E23: Vergas de metal fino dobradas até quase quebrar. | F23: =INDEX(Tiers!$G$9:$G$22,MATCH($A23,Tiers!$B$9:$B$22,0)) | G23: =INDEX(Tiers!$H$9:$H$22,MATCH($A23,Tiers!$B$9:$B$22,0)) | H23: =INDEX($B$5:$B$11,MATCH($B23,$A$5:$A$11,0)) | I23: =ROUND(F23*H23*K23,0) | J23: =ROUND(G23*H23*K23,0) | K23: 1 | L23: =ROUND(I23*8,0) | M23: =ROUND(J23*10,0)
A24: Sucata Enferrujada | B24: Arco | C24: Arco de Corda Puída | E24: A corda já rompeu duas vezes — sempre foi remendada a tempo. | F24: =INDEX(Tiers!$G$9:$G$22,MATCH($A24,Tiers!$B$9:$B$22,0)) | G24: =INDEX(Tiers!$H$9:$H$22,MATCH($A24,Tiers!$B$9:$B$22,0)) | H24: =INDEX($B$5:$B$11,MATCH($B24,$A$5:$A$11,0)) | I24: =ROUND(F24*H24*K24,0) | J24: =ROUND(G24*H24*K24,0) | K24: 1 | L24: =ROUND(I24*8,0) | M24: =ROUND(J24*10,0)
A25: Sucata Enferrujada | B25: Arco | C25: Arco Caçador de Javali | E25: Talhado pra caçar o que ronda a vila. | F25: =INDEX(Tiers!$G$9:$G$22,MATCH($A25,Tiers!$B$9:$B$22,0)) | G25: =INDEX(Tiers!$H$9:$H$22,MATCH($A25,Tiers!$B$9:$B$22,0)) | H25: =INDEX($B$5:$B$11,MATCH($B25,$A$5:$A$11,0)) | I25: =ROUND(F25*H25*K25,0) | J25: =ROUND(G25*H25*K25,0) | K25: 1 | L25: =ROUND(I25*8,0) | M25: =ROUND(J25*10,0)
A26: Sucata Enferrujada | B26: Arco | C26: Arco Torto | E26: Não atira reto, mas quem usa há tempo já aprendeu a mirar torto também. | F26: =INDEX(Tiers!$G$9:$G$22,MATCH($A26,Tiers!$B$9:$B$22,0)) | G26: =INDEX(Tiers!$H$9:$H$22,MATCH($A26,Tiers!$B$9:$B$22,0)) | H26: =INDEX($B$5:$B$11,MATCH($B26,$A$5:$A$11,0)) | I26: =ROUND(F26*H26*K26,0) | J26: =ROUND(G26*H26*K26,0) | K26: 1 | L26: =ROUND(I26*8,0) | M26: =ROUND(J26*10,0)
A27: Sucata Enferrujada | B27: Adaga | C27: Adaga de Sucata | E27: Pequena, feia, e afiada o bastante pra doer o suficiente. | F27: =INDEX(Tiers!$G$9:$G$22,MATCH($A27,Tiers!$B$9:$B$22,0)) | G27: =INDEX(Tiers!$H$9:$H$22,MATCH($A27,Tiers!$B$9:$B$22,0)) | H27: =INDEX($B$5:$B$11,MATCH($B27,$A$5:$A$11,0)) | I27: =ROUND(F27*H27*K27,0) | J27: =ROUND(G27*H27*K27,0) | K27: 1 | L27: =ROUND(I27*8,0) | M27: =ROUND(J27*10,0)
A28: Sucata Enferrujada | B28: Adaga | C28: Adaga de Cozinha Reaproveitada | E28: Servia pra cortar pão. Agora corta outra coisa. | F28: =INDEX(Tiers!$G$9:$G$22,MATCH($A28,Tiers!$B$9:$B$22,0)) | G28: =INDEX(Tiers!$H$9:$H$22,MATCH($A28,Tiers!$B$9:$B$22,0)) | H28: =INDEX($B$5:$B$11,MATCH($B28,$A$5:$A$11,0)) | I28: =ROUND(F28*H28*K28,0) | J28: =ROUND(G28*H28*K28,0) | K28: 1 | L28: =ROUND(I28*8,0) | M28: =ROUND(J28*10,0)
A29: Sucata Enferrujada | B29: Adaga | C29: Adaga Curva | E29: Boa pra cortar corda. Melhor ainda pra cortar tendão. | F29: =INDEX(Tiers!$G$9:$G$22,MATCH($A29,Tiers!$B$9:$B$22,0)) | G29: =INDEX(Tiers!$H$9:$H$22,MATCH($A29,Tiers!$B$9:$B$22,0)) | H29: =INDEX($B$5:$B$11,MATCH($B29,$A$5:$A$11,0)) | I29: =ROUND(F29*H29*K29,0) | J29: =ROUND(G29*H29*K29,0) | K29: 1 | L29: =ROUND(I29*8,0) | M29: =ROUND(J29*10,0)
A30: Sucata Enferrujada | B30: Maca | C30: Maça de Sucata | E30: Cabeça pesada, cabo curto — não erra por falta de força. | F30: =INDEX(Tiers!$G$9:$G$22,MATCH($A30,Tiers!$B$9:$B$22,0)) | G30: =INDEX(Tiers!$H$9:$H$22,MATCH($A30,Tiers!$B$9:$B$22,0)) | H30: =INDEX($B$5:$B$11,MATCH($B30,$A$5:$A$11,0)) | I30: =ROUND(F30*H30*K30,0) | J30: =ROUND(G30*H30*K30,0) | K30: 1 | L30: =ROUND(I30*8,0) | M30: =ROUND(J30*10,0)
A31: Sucata Enferrujada | B31: Maca | C31: Maça Cravejada | D31: Sangramento | E31: Pregos tortos saindo de todo lado — ninguém perguntou se doía fazer. | F31: =INDEX(Tiers!$G$9:$G$22,MATCH($A31,Tiers!$B$9:$B$22,0)) | G31: =INDEX(Tiers!$H$9:$H$22,MATCH($A31,Tiers!$B$9:$B$22,0)) | H31: =INDEX($B$5:$B$11,MATCH($B31,$A$5:$A$11,0)) | I31: =ROUND(F31*H31*K31,0) | J31: =ROUND(G31*H31*K31,0) | K31: 0.96 | L31: =ROUND(I31*8,0) | M31: =ROUND(J31*10,0)
A32: Sucata Enferrujada | B32: Maca | C32: Maça de Ferreiro Improvisada | E32: Era martelo de bigorna. Agora é a última coisa que alguém vê. | F32: =INDEX(Tiers!$G$9:$G$22,MATCH($A32,Tiers!$B$9:$B$22,0)) | G32: =INDEX(Tiers!$H$9:$H$22,MATCH($A32,Tiers!$B$9:$B$22,0)) | H32: =INDEX($B$5:$B$11,MATCH($B32,$A$5:$A$11,0)) | I32: =ROUND(F32*H32*K32,0) | J32: =ROUND(G32*H32*K32,0) | K32: 1 | L32: =ROUND(I32*8,0) | M32: =ROUND(J32*10,0)
A33: Sucata Enferrujada | B33: Manopla | C33: Manopla de Sucata | E33: Placas de metal amarradas nos nós dos dedos. | F33: =INDEX(Tiers!$G$9:$G$22,MATCH($A33,Tiers!$B$9:$B$22,0)) | G33: =INDEX(Tiers!$H$9:$H$22,MATCH($A33,Tiers!$B$9:$B$22,0)) | H33: =INDEX($B$5:$B$11,MATCH($B33,$A$5:$A$11,0)) | I33: =ROUND(F33*H33*K33,0) | J33: =ROUND(G33*H33*K33,0) | K33: 1 | L33: =ROUND(I33*8,0) | M33: =ROUND(J33*10,0)
A34: Sucata Enferrujada | B34: Manopla | C34: Manopla Cravada | E34: Pontas de prego viradas pra fora — aperto de mão que ninguém pede duas vezes. | F34: =INDEX(Tiers!$G$9:$G$22,MATCH($A34,Tiers!$B$9:$B$22,0)) | G34: =INDEX(Tiers!$H$9:$H$22,MATCH($A34,Tiers!$B$9:$B$22,0)) | H34: =INDEX($B$5:$B$11,MATCH($B34,$A$5:$A$11,0)) | I34: =ROUND(F34*H34*K34,0) | J34: =ROUND(G34*H34*K34,0) | K34: 1 | L34: =ROUND(I34*8,0) | M34: =ROUND(J34*10,0)
A35: Sucata Enferrujada | B35: Cetro | C35: Cetro de Sucata | E35: Vara de metal com um cristal quebrado preso na ponta. | F35: =INDEX(Tiers!$G$9:$G$22,MATCH($A35,Tiers!$B$9:$B$22,0)) | G35: =INDEX(Tiers!$H$9:$H$22,MATCH($A35,Tiers!$B$9:$B$22,0)) | H35: =INDEX($B$5:$B$11,MATCH($B35,$A$5:$A$11,0)) | I35: =ROUND(F35*H35*K35,0) | J35: =ROUND(G35*H35*K35,0) | K35: 1 | L35: =ROUND(I35*8,0) | M35: =ROUND(J35*10,0)
A36: Sucata Enferrujada | B36: Cetro | C36: Cetro Rachado | E36: O cristal tá trincado. Ainda assim, funciona. | F36: =INDEX(Tiers!$G$9:$G$22,MATCH($A36,Tiers!$B$9:$B$22,0)) | G36: =INDEX(Tiers!$H$9:$H$22,MATCH($A36,Tiers!$B$9:$B$22,0)) | H36: =INDEX($B$5:$B$11,MATCH($B36,$A$5:$A$11,0)) | I36: =ROUND(F36*H36*K36,0) | J36: =ROUND(G36*H36*K36,0) | K36: 1 | L36: =ROUND(I36*8,0) | M36: =ROUND(J36*10,0)
A37: Bronze | B37: Espada | C37: Espada de Bronze | E37: Fundida em molde de areia, ainda cheira a fumaça da forja. | F37: =INDEX(Tiers!$G$9:$G$22,MATCH($A37,Tiers!$B$9:$B$22,0)) | G37: =INDEX(Tiers!$H$9:$H$22,MATCH($A37,Tiers!$B$9:$B$22,0)) | H37: =INDEX($B$5:$B$11,MATCH($B37,$A$5:$A$11,0)) | I37: =ROUND(F37*H37*K37,0) | J37: =ROUND(G37*H37*K37,0) | K37: 1 | L37: =ROUND(I37*8,0) | M37: =ROUND(J37*10,0)
A38: Bronze | B38: Espada | C38: Espada da Guilda | E38: Gravada com o selo dos Picaretas Negros — paga o dobro em juros de sangue. | F38: =INDEX(Tiers!$G$9:$G$22,MATCH($A38,Tiers!$B$9:$B$22,0)) | G38: =INDEX(Tiers!$H$9:$H$22,MATCH($A38,Tiers!$B$9:$B$22,0)) | H38: =INDEX($B$5:$B$11,MATCH($B38,$A$5:$A$11,0)) | I38: =ROUND(F38*H38*K38,0) | J38: =ROUND(G38*H38*K38,0) | K38: 1 | L38: =ROUND(I38*8,0) | M38: =ROUND(J38*10,0)
A39: Bronze | B39: Espada | C39: Espada Presa em Correntes | E39: Vinha acorrentada num carregamento que nunca chegou ao destino. | F39: =INDEX(Tiers!$G$9:$G$22,MATCH($A39,Tiers!$B$9:$B$22,0)) | G39: =INDEX(Tiers!$H$9:$H$22,MATCH($A39,Tiers!$B$9:$B$22,0)) | H39: =INDEX($B$5:$B$11,MATCH($B39,$A$5:$A$11,0)) | I39: =ROUND(F39*H39*K39,0) | J39: =ROUND(G39*H39*K39,0) | K39: 1 | L39: =ROUND(I39*8,0) | M39: =ROUND(J39*10,0)
A40: Bronze | B40: Espada | C40: Espada de Fundição Rápida | E40: Esfriou rápido demais pra ficar boa — mas ficou afiada. | F40: =INDEX(Tiers!$G$9:$G$22,MATCH($A40,Tiers!$B$9:$B$22,0)) | G40: =INDEX(Tiers!$H$9:$H$22,MATCH($A40,Tiers!$B$9:$B$22,0)) | H40: =INDEX($B$5:$B$11,MATCH($B40,$A$5:$A$11,0)) | I40: =ROUND(F40*H40*K40,0) | J40: =ROUND(G40*H40*K40,0) | K40: 1 | L40: =ROUND(I40*8,0) | M40: =ROUND(J40*10,0)
A41: Bronze | B41: Machado | C41: Machado de Bronze | E41: Peso justo pra quebrar rocha ou crânio, sem preferência. | F41: =INDEX(Tiers!$G$9:$G$22,MATCH($A41,Tiers!$B$9:$B$22,0)) | G41: =INDEX(Tiers!$H$9:$H$22,MATCH($A41,Tiers!$B$9:$B$22,0)) | H41: =INDEX($B$5:$B$11,MATCH($B41,$A$5:$A$11,0)) | I41: =ROUND(F41*H41*K41,0) | J41: =ROUND(G41*H41*K41,0) | K41: 1 | L41: =ROUND(I41*8,0) | M41: =ROUND(J41*10,0)
A42: Bronze | B42: Machado | C42: Machado de Mineiro Adaptado | E42: Trocou pedra por carne no dia em que os túneis pararam de ser seguros. | F42: =INDEX(Tiers!$G$9:$G$22,MATCH($A42,Tiers!$B$9:$B$22,0)) | G42: =INDEX(Tiers!$H$9:$H$22,MATCH($A42,Tiers!$B$9:$B$22,0)) | H42: =INDEX($B$5:$B$11,MATCH($B42,$A$5:$A$11,0)) | I42: =ROUND(F42*H42*K42,0) | J42: =ROUND(G42*H42*K42,0) | K42: 1 | L42: =ROUND(I42*8,0) | M42: =ROUND(J42*10,0)
A43: Bronze | B43: Machado | C43: Machado com Cabo de Cobre | E43: O metal do cabo range a cada golpe, como se reclamasse do trabalho extra. | F43: =INDEX(Tiers!$G$9:$G$22,MATCH($A43,Tiers!$B$9:$B$22,0)) | G43: =INDEX(Tiers!$H$9:$H$22,MATCH($A43,Tiers!$B$9:$B$22,0)) | H43: =INDEX($B$5:$B$11,MATCH($B43,$A$5:$A$11,0)) | I43: =ROUND(F43*H43*K43,0) | J43: =ROUND(G43*H43*K43,0) | K43: 1 | L43: =ROUND(I43*8,0) | M43: =ROUND(J43*10,0)
... A52: Bronze | B52: Maca | C52: Maça de Bronze | E52: Cabeça maciça, sem enfeite — a Guilda não paga por estética. | F52: =INDEX(Tiers!$G$9:$G$22,MATCH($A52,Tiers!$B$9:$B$22,0)) | G52: =INDEX(Tiers!$H$9:$H$22,MATCH($A52,Tiers!$B$9:$B$22,0)) | H52: =INDEX($B$5:$B$11,MATCH($B52,$A$5:$A$11,0)) | I52: =ROUND(F52*H52*K52,0) | J52: =ROUND(G52*H52*K52,0) | K52: 1 | L52: =ROUND(I52*8,0) | M52: =ROUND(J52*10,0)
A53: Bronze | B53: Maca | C53: Maça de Picareta Adaptada | D53: Atordoamento | E53: Era ferramenta de mina. Continua sendo, só que agora a rocha sangra. | F53: =INDEX(Tiers!$G$9:$G$22,MATCH($A53,Tiers!$B$9:$B$22,0)) | G53: =INDEX(Tiers!$H$9:$H$22,MATCH($A53,Tiers!$B$9:$B$22,0)) | H53: =INDEX($B$5:$B$11,MATCH($B53,$A$5:$A$11,0)) | I53: =ROUND(F53*H53*K53,0) | J53: =ROUND(G53*H53*K53,0) | K53: 0.96 | L53: =ROUND(I53*8,0) | M53: =ROUND(J53*10,0)
A54: Bronze | B54: Maca | C54: Maça do Peso Justo | E54: Calibrada pra render o máximo de dano por moeda gasta na forja. | F54: =INDEX(Tiers!$G$9:$G$22,MATCH($A54,Tiers!$B$9:$B$22,0)) | G54: =INDEX(Tiers!$H$9:$H$22,MATCH($A54,Tiers!$B$9:$B$22,0)) | H54: =INDEX($B$5:$B$11,MATCH($B54,$A$5:$A$11,0)) | I54: =ROUND(F54*H54*K54,0) | J54: =ROUND(G54*H54*K54,0) | K54: 1 | L54: =ROUND(I54*8,0) | M54: =ROUND(J54*10,0)
A55: Bronze | B55: Manopla | C55: Manopla de Bronze | E55: Nós reforçados, prontos pro trabalho — ou pra briga. | F55: =INDEX(Tiers!$G$9:$G$22,MATCH($A55,Tiers!$B$9:$B$22,0)) | G55: =INDEX(Tiers!$H$9:$H$22,MATCH($A55,Tiers!$B$9:$B$22,0)) | H55: =INDEX($B$5:$B$11,MATCH($B55,$A$5:$A$11,0)) | I55: =ROUND(F55*H55*K55,0) | J55: =ROUND(G55*H55*K55,0) | K55: 1 | L55: =ROUND(I55*8,0) | M55: =ROUND(J55*10,0)
A56: Bronze | B56: Manopla | C56: Manopla de Corrente Curta | D56: Atordoamento | E56: Feita de elos de corrente cortados, ainda com marca de ferrugem. | F56: =INDEX(Tiers!$G$9:$G$22,MATCH($A56,Tiers!$B$9:$B$22,0)) | G56: =INDEX(Tiers!$H$9:$H$22,MATCH($A56,Tiers!$B$9:$B$22,0)) | H56: =INDEX($B$5:$B$11,MATCH($B56,$A$5:$A$11,0)) | I56: =ROUND(F56*H56*K56,0) | J56: =ROUND(G56*H56*K56,0) | K56: 0.97 | L56: =ROUND(I56*8,0) | M56: =ROUND(J56*10,0)
A57: Bronze | B57: Cetro | C57: Cetro de Bronze | E57: Vara maciça, sem gema — a Guilda nunca investiu em magia de verdade. | F57: =INDEX(Tiers!$G$9:$G$22,MATCH($A57,Tiers!$B$9:$B$22,0)) | G57: =INDEX(Tiers!$H$9:$H$22,MATCH($A57,Tiers!$B$9:$B$22,0)) | H57: =INDEX($B$5:$B$11,MATCH($B57,$A$5:$A$11,0)) | I57: =ROUND(F57*H57*K57,0) | J57: =ROUND(G57*H57*K57,0) | K57: 1 | L57: =ROUND(I57*8,0) | M57: =ROUND(J57*10,0)
A58: Bronze | B58: Cetro | C58: Cetro do Contador da Guilda | E58: Usado mais pra assinar contrato do que pra conjurar — mas funciona pros dois. | F58: =INDEX(Tiers!$G$9:$G$22,MATCH($A58,Tiers!$B$9:$B$22,0)) | G58: =INDEX(Tiers!$H$9:$H$22,MATCH($A58,Tiers!$B$9:$B$22,0)) | H58: =INDEX($B$5:$B$11,MATCH($B58,$A$5:$A$11,0)) | I58: =ROUND(F58*H58*K58,0) | J58: =ROUND(G58*H58*K58,0) | K58: 1 | L58: =ROUND(I58*8,0) | M58: =ROUND(J58*10,0)
A59: Ferro | B59: Espada | C59: Espada de Ferro | E59: Forjada em brasa pesada — sólida, confiável, sem enfeite. | F59: =INDEX(Tiers!$G$9:$G$22,MATCH($A59,Tiers!$B$9:$B$22,0)) | G59: =INDEX(Tiers!$H$9:$H$22,MATCH($A59,Tiers!$B$9:$B$22,0)) | H59: =INDEX($B$5:$B$11,MATCH($B59,$A$5:$A$11,0)) | I59: =ROUND(F59*H59*K59,0) | J59: =ROUND(G59*H59*K59,0) | K59: 1 | L59: =ROUND(I59*8,0) | M59: =ROUND(J59*10,0)
A60: Ferro | B60: Espada | C60: Espada da Guarda Caída | E60: Tem o brasão da guarda gravado, já quase apagado pelo tempo. | F60: =INDEX(Tiers!$G$9:$G$22,MATCH($A60,Tiers!$B$9:$B$22,0)) | G60: =INDEX(Tiers!$H$9:$H$22,MATCH($A60,Tiers!$B$9:$B$22,0)) | H60: =INDEX($B$5:$B$11,MATCH($B60,$A$5:$A$11,0)) | I60: =ROUND(F60*H60*K60,0) | J60: =ROUND(G60*H60*K60,0) | K60: 1 | L60: =ROUND(I60*8,0) | M60: =ROUND(J60*10,0)
A61: Ferro | B61: Espada | C61: Espada Cravada na Pedra | E61: Ficou presa numa rocha da forja por tempo demais — saiu, mas nunca mais brilhou igual. | F61: =INDEX(Tiers!$G$9:$G$22,MATCH($A61,Tiers!$B$9:$B$22,0)) | G61: =INDEX(Tiers!$H$9:$H$22,MATCH($A61,Tiers!$B$9:$B$22,0)) | H61: =INDEX($B$5:$B$11,MATCH($B61,$A$5:$A$11,0)) | I61: =ROUND(F61*H61*K61,0) | J61: =ROUND(G61*H61*K61,0) | K61: 1 | L61: =ROUND(I61*8,0) | M61: =ROUND(J61*10,0)
A62: Ferro | B62: Espada | C62: Espada de Duelo | E62: Fina o bastante pra impressionar, pesada o bastante pra matar. | F62: =INDEX(Tiers!$G$9:$G$22,MATCH($A62,Tiers!$B$9:$B$22,0)) | G62: =INDEX(Tiers!$H$9:$H$22,MATCH($A62,Tiers!$B$9:$B$22,0)) | H62: =INDEX($B$5:$B$11,MATCH($B62,$A$5:$A$11,0)) | I62: =ROUND(F62*H62*K62,0) | J62: =ROUND(G62*H62*K62,0) | K62: 1 | L62: =ROUND(I62*8,0) | M62: =ROUND(J62*10,0)
A63: Ferro | B63: Machado | C63: Machado de Ferro | E63: Peso confiável, sem segredo — corta o que a picareta não alcança. | F63: =INDEX(Tiers!$G$9:$G$22,MATCH($A63,Tiers!$B$9:$B$22,0)) | G63: =INDEX(Tiers!$H$9:$H$22,MATCH($A63,Tiers!$B$9:$B$22,0)) | H63: =INDEX($B$5:$B$11,MATCH($B63,$A$5:$A$11,0)) | I63: =ROUND(F63*H63*K63,0) | J63: =ROUND(G63*H63*K63,0) | K63: 1 | L63: =ROUND(I63*8,0) | M63: =ROUND(J63*10,0)
A64: Ferro | B64: Machado | C64: Machado de Sentinela | E64: Usado por quem ficava de guarda na muralha, antes da muralha cair. | F64: =INDEX(Tiers!$G$9:$G$22,MATCH($A64,Tiers!$B$9:$B$22,0)) | G64: =INDEX(Tiers!$H$9:$H$22,MATCH($A64,Tiers!$B$9:$B$22,0)) | H64: =INDEX($B$5:$B$11,MATCH($B64,$A$5:$A$11,0)) | I64: =ROUND(F64*H64*K64,0) | J64: =ROUND(G64*H64*K64,0) | K64: 1 | L64: =ROUND(I64*8,0) | M64: =ROUND(J64*10,0)
A65: Ferro | B65: Machado | C65: Machado Perfurante | D65: Ignora Defesa | E65: Ponta fina o bastante pra passar entre placas de armadura. | F65: =INDEX(Tiers!$G$9:$G$22,MATCH($A65,Tiers!$B$9:$B$22,0)) | G65: =INDEX(Tiers!$H$9:$H$22,MATCH($A65,Tiers!$B$9:$B$22,0)) | H65: =INDEX($B$5:$B$11,MATCH($B65,$A$5:$A$11,0)) | I65: =ROUND(F65*H65*K65,0) | J65: =ROUND(G65*H65*K65,0) | K65: 0.96 | L65: =ROUND(I65*8,0) | M65: =ROUND(J65*10,0)
A66: Ferro | B66: Machado | C66: Machado Cerimonial Quebrado | E66: Servia pra juramentos. Ninguém jura mais nada por aqui. | F66: =INDEX(Tiers!$G$9:$G$22,MATCH($A66,Tiers!$B$9:$B$22,0)) | G66: =INDEX(Tiers!$H$9:$H$22,MATCH($A66,Tiers!$B$9:$B$22,0)) | H66: =INDEX($B$5:$B$11,MATCH($B66,$A$5:$A$11,0)) | I66: =ROUND(F66*H66*K66,0) | J66: =ROUND(G66*H66*K66,0) | K66: 1 | L66: =ROUND(I66*8,0) | M66: =ROUND(J66*10,0)
A67: Ferro | B67: Arco | C67: Arco de Ferro | E67: Reforçado nas pontas, pesado na mão — feito pra durar mais que o atirador. | F67: =INDEX(Tiers!$G$9:$G$22,MATCH($A67,Tiers!$B$9:$B$22,0)) | G67: =INDEX(Tiers!$H$9:$H$22,MATCH($A67,Tiers!$B$9:$B$22,0)) | H67: =INDEX($B$5:$B$11,MATCH($B67,$A$5:$A$11,0)) | I67: =ROUND(F67*H67*K67,0) | J67: =ROUND(G67*H67*K67,0) | K67: 1 | L67: =ROUND(I67*8,0) | M67: =ROUND(J67*10,0)
A68: Ferro | B68: Arco | C68: Arco de Caça da Guarnição | E68: Usado pelos batedores da guarda, antes de pararem de patrulhar. | F68: =INDEX(Tiers!$G$9:$G$22,MATCH($A68,Tiers!$B$9:$B$22,0)) | G68: =INDEX(Tiers!$H$9:$H$22,MATCH($A68,Tiers!$B$9:$B$22,0)) | H68: =INDEX($B$5:$B$11,MATCH($B68,$A$5:$A$11,0)) | I68: =ROUND(F68*H68*K68,0) | J68: =ROUND(G68*H68*K68,0) | K68: 1 | L68: =ROUND(I68*8,0) | M68: =ROUND(J68*10,0)
A69: Ferro | B69: Arco | C69: Arco Perfurante | D69: Ignora Defesa | E69: Pontas de flecha fina o bastante pra passar entre elos de malha. | F69: =INDEX(Tiers!$G$9:$G$22,MATCH($A69,Tiers!$B$9:$B$22,0)) | G69: =INDEX(Tiers!$H$9:$H$22,MATCH($A69,Tiers!$B$9:$B$22,0)) | H69: =INDEX($B$5:$B$11,MATCH($B69,$A$5:$A$11,0)) | I69: =ROUND(F69*H69*K69,0) | J69: =ROUND(G69*H69*K69,0) | K69: 0.97 | L69: =ROUND(I69*8,0) | M69: =ROUND(J69*10,0)
A70: Ferro | B70: Arco | C70: Arco Rangente | E70: Faz barulho a cada disparo — quem usa aprendeu a não se importar. | F70: =INDEX(Tiers!$G$9:$G$22,MATCH($A70,Tiers!$B$9:$B$22,0)) | G70: =INDEX(Tiers!$H$9:$H$22,MATCH($A70,Tiers!$B$9:$B$22,0)) | H70: =INDEX($B$5:$B$11,MATCH($B70,$A$5:$A$11,0)) | I70: =ROUND(F70*H70*K70,0) | J70: =ROUND(G70*H70*K70,0) | K70: 1 | L70: =ROUND(I70*8,0) | M70: =ROUND(J70*10,0)
A71: Ferro | B71: Adaga | C71: Adaga de Ferro | E71: Curta, direta, sem frescura. | F71: =INDEX(Tiers!$G$9:$G$22,MATCH($A71,Tiers!$B$9:$B$22,0)) | G71: =INDEX(Tiers!$H$9:$H$22,MATCH($A71,Tiers!$B$9:$B$22,0)) | H71: =INDEX($B$5:$B$11,MATCH($B71,$A$5:$A$11,0)) | I71: =ROUND(F71*H71*K71,0) | J71: =ROUND(G71*H71*K71,0) | K71: 1 | L71: =ROUND(I71*8,0) | M71: =ROUND(J71*10,0)
A72: Ferro | B72: Adaga | C72: Adaga de Oficial | E72: Pertencia a alguém com patente. A patente não sobreviveu. | F72: =INDEX(Tiers!$G$9:$G$22,MATCH($A72,Tiers!$B$9:$B$22,0)) | G72: =INDEX(Tiers!$H$9:$H$22,MATCH($A72,Tiers!$B$9:$B$22,0)) | H72: =INDEX($B$5:$B$11,MATCH($B72,$A$5:$A$11,0)) | I72: =ROUND(F72*H72*K72,0) | J72: =ROUND(G72*H72*K72,0) | K72: 1 | L72: =ROUND(I72*8,0) | M72: =ROUND(J72*10,0)
A73: Ferro | B73: Adaga | C73: Adaga Perfurante | D73: Ignora Defesa | E73: Fina o bastante pra passar por uma junta de armadura. | F73: =INDEX(Tiers!$G$9:$G$22,MATCH($A73,Tiers!$B$9:$B$22,0)) | G73: =INDEX(Tiers!$H$9:$H$22,MATCH($A73,Tiers!$B$9:$B$22,0)) | H73: =INDEX($B$5:$B$11,MATCH($B73,$A$5:$A$11,0)) | I73: =ROUND(F73*H73*K73,0) | J73: =ROUND(G73*H73*K73,0) | K73: 0.94 | L73: =ROUND(I73*8,0) | M73: =ROUND(J73*10,0)
A74: Ferro | B74: Maca | C74: Maça de Ferro | E74: Cabeça sólida, sem enfeite — machuca por peso, não por corte. | F74: =INDEX(Tiers!$G$9:$G$22,MATCH($A74,Tiers!$B$9:$B$22,0)) | G74: =INDEX(Tiers!$H$9:$H$22,MATCH($A74,Tiers!$B$9:$B$22,0)) | H74: =INDEX($B$5:$B$11,MATCH($B74,$A$5:$A$11,0)) | I74: =ROUND(F74*H74*K74,0) | J74: =ROUND(G74*H74*K74,0) | K74: 1 | L74: =ROUND(I74*8,0) | M74: =ROUND(J74*10,0)
A75: Ferro | B75: Maca | C75: Maça de Guarnição | E75: Usada em treino de recruta — poucos treinos terminaram sem sangue. | F75: =INDEX(Tiers!$G$9:$G$22,MATCH($A75,Tiers!$B$9:$B$22,0)) | G75: =INDEX(Tiers!$H$9:$H$22,MATCH($A75,Tiers!$B$9:$B$22,0)) | H75: =INDEX($B$5:$B$11,MATCH($B75,$A$5:$A$11,0)) | I75: =ROUND(F75*H75*K75,0) | J75: =ROUND(G75*H75*K75,0) | K75: 1 | L75: =ROUND(I75*8,0) | M75: =ROUND(J75*10,0)
A76: Ferro | B76: Maca | C76: Maça Rachada | E76: Já bateu demais. Ainda bate. | F76: =INDEX(Tiers!$G$9:$G$22,MATCH($A76,Tiers!$B$9:$B$22,0)) | G76: =INDEX(Tiers!$H$9:$H$22,MATCH($A76,Tiers!$B$9:$B$22,0)) | H76: =INDEX($B$5:$B$11,MATCH($B76,$A$5:$A$11,0)) | I76: =ROUND(F76*H76*K76,0) | J76: =ROUND(G76*H76*K76,0) | K76: 1 | L76: =ROUND(I76*8,0) | M76: =ROUND(J76*10,0)
A77: Ferro | B77: Manopla | C77: Manopla de Ferro | E77: Nós reforçados com placas — dói em quem bate, dói mais em quem apanha. | F77: =INDEX(Tiers!$G$9:$G$22,MATCH($A77,Tiers!$B$9:$B$22,0)) | G77: =INDEX(Tiers!$H$9:$H$22,MATCH($A77,Tiers!$B$9:$B$22,0)) | H77: =INDEX($B$5:$B$11,MATCH($B77,$A$5:$A$11,0)) | I77: =ROUND(F77*H77*K77,0) | J77: =ROUND(G77*H77*K77,0) | K77: 1 | L77: =ROUND(I77*8,0) | M77: =ROUND(J77*10,0)
A78: Ferro | B78: Manopla | C78: Manopla de Sentinela | E78: Usada por quem fazia ronda à noite, sozinho, com medo real. | F78: =INDEX(Tiers!$G$9:$G$22,MATCH($A78,Tiers!$B$9:$B$22,0)) | G78: =INDEX(Tiers!$H$9:$H$22,MATCH($A78,Tiers!$B$9:$B$22,0)) | H78: =INDEX($B$5:$B$11,MATCH($B78,$A$5:$A$11,0)) | I78: =ROUND(F78*H78*K78,0) | J78: =ROUND(G78*H78*K78,0) | K78: 1 | L78: =ROUND(I78*8,0) | M78: =ROUND(J78*10,0)
A79: Ferro | B79: Cetro | C79: Cetro de Ferro | E79: Vara pesada, cristal embutido — sem luxo, só função. | F79: =INDEX(Tiers!$G$9:$G$22,MATCH($A79,Tiers!$B$9:$B$22,0)) | G79: =INDEX(Tiers!$H$9:$H$22,MATCH($A79,Tiers!$B$9:$B$22,0)) | H79: =INDEX($B$5:$B$11,MATCH($B79,$A$5:$A$11,0)) | I79: =ROUND(F79*H79*K79,0) | J79: =ROUND(G79*H79*K79,0) | K79: 1 | L79: =ROUND(I79*8,0) | M79: =ROUND(J79*10,0)
A80: Ferro | B80: Cetro | C80: Cetro do Capelão Caído | E80: Pertencia a um capelão que benzia a guarda antes de cada turno. Parou de benzer. | F80: =INDEX(Tiers!$G$9:$G$22,MATCH($A80,Tiers!$B$9:$B$22,0)) | G80: =INDEX(Tiers!$H$9:$H$22,MATCH($A80,Tiers!$B$9:$B$22,0)) | H80: =INDEX($B$5:$B$11,MATCH($B80,$A$5:$A$11,0)) | I80: =ROUND(F80*H80*K80,0) | J80: =ROUND(G80*H80*K80,0) | K80: 1 | L80: =ROUND(I80*8,0) | M80: =ROUND(J80*10,0)
A81: Prata | B81: Espada | C81: Espada de Prata | E81: Lâmina polida que brilha fraco no escuro — feita pra crânios que não deviam se mexer mais. | F81: =INDEX(Tiers!$G$9:$G$22,MATCH($A81,Tiers!$B$9:$B$22,0)) | G81: =INDEX(Tiers!$H$9:$H$22,MATCH($A81,Tiers!$B$9:$B$22,0)) | H81: =INDEX($B$5:$B$11,MATCH($B81,$A$5:$A$11,0)) | I81: =ROUND(F81*H81*K81,0) | J81: =ROUND(G81*H81*K81,0) | K81: 1 | L81: =ROUND(I81*8,0) | M81: =ROUND(J81*10,0)
A82: Prata | B82: Espada | C82: Espada Abençoada | D82: Rouba Vida | E82: Benzida antes da forja esfriar — cura quem a empunha ao acertar um morto-vivo. | F82: =INDEX(Tiers!$G$9:$G$22,MATCH($A82,Tiers!$B$9:$B$22,0)) | G82: =INDEX(Tiers!$H$9:$H$22,MATCH($A82,Tiers!$B$9:$B$22,0)) | H82: =INDEX($B$5:$B$11,MATCH($B82,$A$5:$A$11,0)) | I82: =ROUND(F82*H82*K82,0) | J82: =ROUND(G82*H82*K82,0) | K82: 0.95 | L82: =ROUND(I82*8,0) | M82: =ROUND(J82*10,0)
A83: Prata | B83: Espada | C83: Espada Consagrada da Cripta | E83: Guardada num altar por gerações, até alguém decidir que era hora de usar. | F83: =INDEX(Tiers!$G$9:$G$22,MATCH($A83,Tiers!$B$9:$B$22,0)) | G83: =INDEX(Tiers!$H$9:$H$22,MATCH($A83,Tiers!$B$9:$B$22,0)) | H83: =INDEX($B$5:$B$11,MATCH($B83,$A$5:$A$11,0)) | I83: =ROUND(F83*H83*K83,0) | J83: =ROUND(G83*H83*K83,0) | K83: 1 | L83: =ROUND(I83*8,0) | M83: =ROUND(J83*10,0)
A84: Prata | B84: Espada | C84: Espada Cega pela Luz | E84: Reflete tanto que ofusca antes de cortar. | F84: =INDEX(Tiers!$G$9:$G$22,MATCH($A84,Tiers!$B$9:$B$22,0)) | G84: =INDEX(Tiers!$H$9:$H$22,MATCH($A84,Tiers!$B$9:$B$22,0)) | H84: =INDEX($B$5:$B$11,MATCH($B84,$A$5:$A$11,0)) | I84: =ROUND(F84*H84*K84,0) | J84: =ROUND(G84*H84*K84,0) | K84: 1 | L84: =ROUND(I84*8,0) | M84: =ROUND(J84*10,0)
A85: Prata | B85: Machado | C85: Machado de Prata | E85: Pesado o bastante pra rachar lápide, afiado o bastante pra fazer mais que isso. | F85: =INDEX(Tiers!$G$9:$G$22,MATCH($A85,Tiers!$B$9:$B$22,0)) | G85: =INDEX(Tiers!$H$9:$H$22,MATCH($A85,Tiers!$B$9:$B$22,0)) | H85: =INDEX($B$5:$B$11,MATCH($B85,$A$5:$A$11,0)) | I85: =ROUND(F85*H85*K85,0) | J85: =ROUND(G85*H85*K85,0) | K85: 1 | L85: =ROUND(I85*8,0) | M85: =ROUND(J85*10,0)
A86: Prata | B86: Machado | C86: Machado do Coveiro | E86: Servia pra abrir cova. Agora fecha uma de vez. | F86: =INDEX(Tiers!$G$9:$G$22,MATCH($A86,Tiers!$B$9:$B$22,0)) | G86: =INDEX(Tiers!$H$9:$H$22,MATCH($A86,Tiers!$B$9:$B$22,0)) | H86: =INDEX($B$5:$B$11,MATCH($B86,$A$5:$A$11,0)) | I86: =ROUND(F86*H86*K86,0) | J86: =ROUND(G86*H86*K86,0) | K86: 1 | L86: =ROUND(I86*8,0) | M86: =ROUND(J86*10,0)
A87: Prata | B87: Machado | C87: Machado Gravado com Preces | E87: Preces gravadas na lâmina, já quase apagadas de tanto uso. | F87: =INDEX(Tiers!$G$9:$G$22,MATCH($A87,Tiers!$B$9:$B$22,0)) | G87: =INDEX(Tiers!$H$9:$H$22,MATCH($A87,Tiers!$B$9:$B$22,0)) | H87: =INDEX($B$5:$B$11,MATCH($B87,$A$5:$A$11,0)) | I87: =ROUND(F87*H87*K87,0) | J87: =ROUND(G87*H87*K87,0) | K87: 1 | L87: =ROUND(I87*8,0) | M87: =ROUND(J87*10,0)
A88: Prata | B88: Machado | C88: Machado da Fraternidade Renegada | E88: Um dos poucos que restaram de antes do voto de silêncio. | F88: =INDEX(Tiers!$G$9:$G$22,MATCH($A88,Tiers!$B$9:$B$22,0)) | G88: =INDEX(Tiers!$H$9:$H$22,MATCH($A88,Tiers!$B$9:$B$22,0)) | H88: =INDEX($B$5:$B$11,MATCH($B88,$A$5:$A$11,0)) | I88: =ROUND(F88*H88*K88,0) | J88: =ROUND(G88*H88*K88,0) | K88: 1 | L88: =ROUND(I88*8,0) | M88: =ROUND(J88*10,0)
A89: Prata | B89: Arco | C89: Arco de Prata | E89: Corda fina, vibra num tom que só os mortos parecem notar. | F89: =INDEX(Tiers!$G$9:$G$22,MATCH($A89,Tiers!$B$9:$B$22,0)) | G89: =INDEX(Tiers!$H$9:$H$22,MATCH($A89,Tiers!$B$9:$B$22,0)) | H89: =INDEX($B$5:$B$11,MATCH($B89,$A$5:$A$11,0)) | I89: =ROUND(F89*H89*K89,0) | J89: =ROUND(G89*H89*K89,0) | K89: 1 | L89: =ROUND(I89*8,0) | M89: =ROUND(J89*10,0)
A90: Prata | B90: Arco | C90: Arco Consagrado | E90: Flechas que ele dispara saem levemente frias. | F90: =INDEX(Tiers!$G$9:$G$22,MATCH($A90,Tiers!$B$9:$B$22,0)) | G90: =INDEX(Tiers!$H$9:$H$22,MATCH($A90,Tiers!$B$9:$B$22,0)) | H90: =INDEX($B$5:$B$11,MATCH($B90,$A$5:$A$11,0)) | I90: =ROUND(F90*H90*K90,0) | J90: =ROUND(G90*H90*K90,0) | K90: 1 | L90: =ROUND(I90*8,0) | M90: =ROUND(J90*10,0)
A91: Prata | B91: Arco | C91: Arco do Guardião da Cripta | E91: Usado por quem vigiava a entrada antes da Fraternidade chegar. | F91: =INDEX(Tiers!$G$9:$G$22,MATCH($A91,Tiers!$B$9:$B$22,0)) | G91: =INDEX(Tiers!$H$9:$H$22,MATCH($A91,Tiers!$B$9:$B$22,0)) | H91: =INDEX($B$5:$B$11,MATCH($B91,$A$5:$A$11,0)) | I91: =ROUND(F91*H91*K91,0) | J91: =ROUND(G91*H91*K91,0) | K91: 1 | L91: =ROUND(I91*8,0) | M91: =ROUND(J91*10,0)
A92: Prata | B92: Arco | C92: Arco Silencioso | E92: Não faz barulho nenhum ao disparar — nem a corda, nem a flecha. | F92: =INDEX(Tiers!$G$9:$G$22,MATCH($A92,Tiers!$B$9:$B$22,0)) | G92: =INDEX(Tiers!$H$9:$H$22,MATCH($A92,Tiers!$B$9:$B$22,0)) | H92: =INDEX($B$5:$B$11,MATCH($B92,$A$5:$A$11,0)) | I92: =ROUND(F92*H92*K92,0) | J92: =ROUND(G92*H92*K92,0) | K92: 1 | L92: =ROUND(I92*8,0) | M92: =ROUND(J92*10,0)
A93: Prata | B93: Adaga | C93: Adaga de Prata | E93: Curta, fria ao toque, mesmo longe de qualquer gelo. | F93: =INDEX(Tiers!$G$9:$G$22,MATCH($A93,Tiers!$B$9:$B$22,0)) | G93: =INDEX(Tiers!$H$9:$H$22,MATCH($A93,Tiers!$B$9:$B$22,0)) | H93: =INDEX($B$5:$B$11,MATCH($B93,$A$5:$A$11,0)) | I93: =ROUND(F93*H93*K93,0) | J93: =ROUND(G93*H93*K93,0) | K93: 1 | L93: =ROUND(I93*8,0) | M93: =ROUND(J93*10,0)
A94: Prata | B94: Adaga | C94: Adaga do Ritual | E94: Usada em cerimônias de purificação — nunca pra matar vivo. | F94: =INDEX(Tiers!$G$9:$G$22,MATCH($A94,Tiers!$B$9:$B$22,0)) | G94: =INDEX(Tiers!$H$9:$H$22,MATCH($A94,Tiers!$B$9:$B$22,0)) | H94: =INDEX($B$5:$B$11,MATCH($B94,$A$5:$A$11,0)) | I94: =ROUND(F94*H94*K94,0) | J94: =ROUND(G94*H94*K94,0) | K94: 1 | L94: =ROUND(I94*8,0) | M94: =ROUND(J94*10,0)
... A96: Prata | B96: Maca | C96: Maça de Prata | E96: Cabeça maciça, prateada — machuca duplamente quem já devia estar morto. | F96: =INDEX(Tiers!$G$9:$G$22,MATCH($A96,Tiers!$B$9:$B$22,0)) | G96: =INDEX(Tiers!$H$9:$H$22,MATCH($A96,Tiers!$B$9:$B$22,0)) | H96: =INDEX($B$5:$B$11,MATCH($B96,$A$5:$A$11,0)) | I96: =ROUND(F96*H96*K96,0) | J96: =ROUND(G96*H96*K96,0) | K96: 1 | L96: =ROUND(I96*8,0) | M96: =ROUND(J96*10,0)
A97: Prata | B97: Maca | C97: Maça do Exorcista | D97: Rouba Vida | E97: Abençoada tantas vezes que cura quem a usa ao golpear um morto-vivo. | F97: =INDEX(Tiers!$G$9:$G$22,MATCH($A97,Tiers!$B$9:$B$22,0)) | G97: =INDEX(Tiers!$H$9:$H$22,MATCH($A97,Tiers!$B$9:$B$22,0)) | H97: =INDEX($B$5:$B$11,MATCH($B97,$A$5:$A$11,0)) | I97: =ROUND(F97*H97*K97,0) | J97: =ROUND(G97*H97*K97,0) | K97: 0.96 | L97: =ROUND(I97*8,0) | M97: =ROUND(J97*10,0)
A98: Prata | B98: Maca | C98: Maça Rachada da Cripta | E98: Achada perto de uma tumba arrombada — ninguém sabe quem a deixou lá. | F98: =INDEX(Tiers!$G$9:$G$22,MATCH($A98,Tiers!$B$9:$B$22,0)) | G98: =INDEX(Tiers!$H$9:$H$22,MATCH($A98,Tiers!$B$9:$B$22,0)) | H98: =INDEX($B$5:$B$11,MATCH($B98,$A$5:$A$11,0)) | I98: =ROUND(F98*H98*K98,0) | J98: =ROUND(G98*H98*K98,0) | K98: 1 | L98: =ROUND(I98*8,0) | M98: =ROUND(J98*10,0)
A99: Prata | B99: Manopla | C99: Manopla de Prata | E99: Nós reforçados com prata pura — cara demais pra briga de rua. | F99: =INDEX(Tiers!$G$9:$G$22,MATCH($A99,Tiers!$B$9:$B$22,0)) | G99: =INDEX(Tiers!$H$9:$H$22,MATCH($A99,Tiers!$B$9:$B$22,0)) | H99: =INDEX($B$5:$B$11,MATCH($B99,$A$5:$A$11,0)) | I99: =ROUND(F99*H99*K99,0) | J99: =ROUND(G99*H99*K99,0) | K99: 1 | L99: =ROUND(I99*8,0) | M99: =ROUND(J99*10,0)
A100: Prata | B100: Manopla | C100: Manopla do Purificador | E100: Usada por quem tocava os corpos antes do enterro. | F100: =INDEX(Tiers!$G$9:$G$22,MATCH($A100,Tiers!$B$9:$B$22,0)) | G100: =INDEX(Tiers!$H$9:$H$22,MATCH($A100,Tiers!$B$9:$B$22,0)) | H100: =INDEX($B$5:$B$11,MATCH($B100,$A$5:$A$11,0)) | I100: =ROUND(F100*H100*K100,0) | J100: =ROUND(G100*H100*K100,0) | K100: 1 | L100: =ROUND(I100*8,0) | M100: =ROUND(J100*10,0)
A101: Prata | B101: Cetro | C101: Cetro de Prata | E101: Vara fina, cristal claro — feito pra canalizar, não pra impressionar. | F101: =INDEX(Tiers!$G$9:$G$22,MATCH($A101,Tiers!$B$9:$B$22,0)) | G101: =INDEX(Tiers!$H$9:$H$22,MATCH($A101,Tiers!$B$9:$B$22,0)) | H101: =INDEX($B$5:$B$11,MATCH($B101,$A$5:$A$11,0)) | I101: =ROUND(F101*H101*K101,0) | J101: =ROUND(G101*H101*K101,0) | K101: 1 | L101: =ROUND(I101*8,0) | M101: =ROUND(J101*10,0)
A102: Prata | B102: Cetro | C102: Cetro da Última Prece | E102: Pertencia a um sacerdote que parou de rezar antes de terminar a última frase. | F102: =INDEX(Tiers!$G$9:$G$22,MATCH($A102,Tiers!$B$9:$B$22,0)) | G102: =INDEX(Tiers!$H$9:$H$22,MATCH($A102,Tiers!$B$9:$B$22,0)) | H102: =INDEX($B$5:$B$11,MATCH($B102,$A$5:$A$11,0)) | I102: =ROUND(F102*H102*K102,0) | J102: =ROUND(G102*H102*K102,0) | K102: 1 | L102: =ROUND(I102*8,0) | M102: =ROUND(J102*10,0)
A103: Aco Elfico | B103: Espada | C103: Espada de Aço Élfico | E103: Dobrada centenas de vezes sem soldas — vibra quando monstros se aproximam. | F103: =INDEX(Tiers!$G$9:$G$22,MATCH($A103,Tiers!$B$9:$B$22,0)) | G103: =INDEX(Tiers!$H$9:$H$22,MATCH($A103,Tiers!$B$9:$B$22,0)) | H103: =INDEX($B$5:$B$11,MATCH($B103,$A$5:$A$11,0)) | I103: =ROUND(F103*H103*K103,0) | J103: =ROUND(G103*H103*K103,0) | K103: 1 | L103: =ROUND(I103*8,0) | M103: =ROUND(J103*10,0)
A104: Aco Elfico | B104: Espada | C104: Espada Élfica Cantante | E104: Emite um zunido baixo ao cortar o ar, quase uma nota musical. | F104: =INDEX(Tiers!$G$9:$G$22,MATCH($A104,Tiers!$B$9:$B$22,0)) | G104: =INDEX(Tiers!$H$9:$H$22,MATCH($A104,Tiers!$B$9:$B$22,0)) | H104: =INDEX($B$5:$B$11,MATCH($B104,$A$5:$A$11,0)) | I104: =ROUND(F104*H104*K104,0) | J104: =ROUND(G104*H104*K104,0) | K104: 1 | L104: =ROUND(I104*8,0) | M104: =ROUND(J104*10,0)
A105: Aco Elfico | B105: Espada | C105: Espada da Vigília | E105: Usada pelas sentinelas da Vigília das Folhas de Prata, geração após geração. | F105: =INDEX(Tiers!$G$9:$G$22,MATCH($A105,Tiers!$B$9:$B$22,0)) | G105: =INDEX(Tiers!$H$9:$H$22,MATCH($A105,Tiers!$B$9:$B$22,0)) | H105: =INDEX($B$5:$B$11,MATCH($B105,$A$5:$A$11,0)) | I105: =ROUND(F105*H105*K105,0) | J105: =ROUND(G105*H105*K105,0) | K105: 1 | L105: =ROUND(I105*8,0) | M105: =ROUND(J105*10,0)
A106: Aco Elfico | B106: Espada | C106: Espada de Fio Único | E106: Forjada numa única dobra perfeita — corta antes de anunciar. | F106: =INDEX(Tiers!$G$9:$G$22,MATCH($A106,Tiers!$B$9:$B$22,0)) | G106: =INDEX(Tiers!$H$9:$H$22,MATCH($A106,Tiers!$B$9:$B$22,0)) | H106: =INDEX($B$5:$B$11,MATCH($B106,$A$5:$A$11,0)) | I106: =ROUND(F106*H106*K106,0) | J106: =ROUND(G106*H106*K106,0) | K106: 1 | L106: =ROUND(I106*8,0) | M106: =ROUND(J106*10,0)
A107: Aco Elfico | B107: Machado | C107: Machado de Aço Élfico | E107: Leve demais pra ser machado, afiado demais pra ser outra coisa. | F107: =INDEX(Tiers!$G$9:$G$22,MATCH($A107,Tiers!$B$9:$B$22,0)) | G107: =INDEX(Tiers!$H$9:$H$22,MATCH($A107,Tiers!$B$9:$B$22,0)) | H107: =INDEX($B$5:$B$11,MATCH($B107,$A$5:$A$11,0)) | I107: =ROUND(F107*H107*K107,0) | J107: =ROUND(G107*H107*K107,0) | K107: 1 | L107: =ROUND(I107*8,0) | M107: =ROUND(J107*10,0)
A108: Aco Elfico | B108: Machado | C108: Machado dos Ecos | E108: Ressoa fraco a cada golpe, como se o próprio ar discordasse do impacto. | F108: =INDEX(Tiers!$G$9:$G$22,MATCH($A108,Tiers!$B$9:$B$22,0)) | G108: =INDEX(Tiers!$H$9:$H$22,MATCH($A108,Tiers!$B$9:$B$22,0)) | H108: =INDEX($B$5:$B$11,MATCH($B108,$A$5:$A$11,0)) | I108: =ROUND(F108*H108*K108,0) | J108: =ROUND(G108*H108*K108,0) | K108: 1 | L108: =ROUND(I108*8,0) | M108: =ROUND(J108*10,0)
A109: Aco Elfico | B109: Machado | C109: Machado da Guarda Florestal | E109: Usado pra abrir caminho na mata sem derrubar mais do que precisa. | F109: =INDEX(Tiers!$G$9:$G$22,MATCH($A109,Tiers!$B$9:$B$22,0)) | G109: =INDEX(Tiers!$H$9:$H$22,MATCH($A109,Tiers!$B$9:$B$22,0)) | H109: =INDEX($B$5:$B$11,MATCH($B109,$A$5:$A$11,0)) | I109: =ROUND(F109*H109*K109,0) | J109: =ROUND(G109*H109*K109,0) | K109: 1 | L109: =ROUND(I109*8,0) | M109: =ROUND(J109*10,0)
... A113: Aco Elfico | B113: Arco | C113: Arco da Sentinela Perdida | E113: Pertencia a quem vigiava as ruínas antes delas virarem só ruínas. | F113: =INDEX(Tiers!$G$9:$G$22,MATCH($A113,Tiers!$B$9:$B$22,0)) | G113: =INDEX(Tiers!$H$9:$H$22,MATCH($A113,Tiers!$B$9:$B$22,0)) | H113: =INDEX($B$5:$B$11,MATCH($B113,$A$5:$A$11,0)) | I113: =ROUND(F113*H113*K113,0) | J113: =ROUND(G113*H113*K113,0) | K113: 1 | L113: =ROUND(I113*8,0) | M113: =ROUND(J113*10,0)
A114: Aco Elfico | B114: Arco | C114: Arco de Precisão Élfica | D114: Ignora Defesa | E114: Não erra por acaso — erra só quando quem atira erra primeiro. | F114: =INDEX(Tiers!$G$9:$G$22,MATCH($A114,Tiers!$B$9:$B$22,0)) | G114: =INDEX(Tiers!$H$9:$H$22,MATCH($A114,Tiers!$B$9:$B$22,0)) | H114: =INDEX($B$5:$B$11,MATCH($B114,$A$5:$A$11,0)) | I114: =ROUND(F114*H114*K114,0) | J114: =ROUND(G114*H114*K114,0) | K114: 0.97 | L114: =ROUND(I114*8,0) | M114: =ROUND(J114*10,0)
A115: Aco Elfico | B115: Adaga | C115: Adaga de Aço Élfico | E115: Fina, leve, quase invisível na mão fechada. | F115: =INDEX(Tiers!$G$9:$G$22,MATCH($A115,Tiers!$B$9:$B$22,0)) | G115: =INDEX(Tiers!$H$9:$H$22,MATCH($A115,Tiers!$B$9:$B$22,0)) | H115: =INDEX($B$5:$B$11,MATCH($B115,$A$5:$A$11,0)) | I115: =ROUND(F115*H115*K115,0) | J115: =ROUND(G115*H115*K115,0) | K115: 1 | L115: =ROUND(I115*8,0) | M115: =ROUND(J115*10,0)
...

Sheet Bestiario
A1: Bestiario Inicial
A2: HP/Dano/Defesa calculados pela Curva Mestra a partir do nivel. Troque nomes/nivel a vontade.
A4: Papel | B4: Multiplicador de Dano | C4: Bonus de Defesa | D4: Fator de XP | E4: Bonus Ataque Extra
A5: Comum | B5: 1 | C5: 0 | D5: 0.12 | E5: 0
A6: Elite | B6: 1.3 | C6: 2 | D6: 0.35 | E6: 2
A7: Boss | B7: 1.6 | C7: 4 | D7: 1 | E7: 4
A8: Cosmico | B8: 2.2 | C8: 5 | D8: 2.5 | E8: 6
A11: Tier | B11: Nome do Monstro | C11: Papel | D11: Nivel | E11: HP | F11: Dano | G11: Defesa | H11: Origem/Descricao | I11: Golpe Especial | J11: Efeito Mecânico | K11: Motivação / Ligação com a Infecção | L11: HP ★★ Médio | M11: Dano ★★ Médio | N11: Defesa ★★ Médio | O11: HP ★★★ Difícil | P11: Dano ★★★ Difícil | Q11: Defesa ★★★ Difícil | R11: Quests Relacionadas | S11: Bônus de Ataque | T11: Materiais Dropados | U11: Fraqueza (Knowledge 4-5) | V11: Estilo de Combate | W11: Condição de Spawn | X11: Fase 2 | Y11: Interação Ambiental | Z11: Reação à Facção | AA11: Loot Único
A12: Sucata Enferrujada | B12: Cão de Caça Sanguíneo | C12: Comum | D12: 1 | E12: =ROUND(INDEX('Curva Mestra'!$F$20:$F$94,MATCH(D12,'Curva Mestra'!$A$20:$A$94,0)),0) | F12: =ROUND(INDEX('Curva Mestra'!$C$20:$C$94,MATCH(D12,'Curva Mestra'!$A$20:$A$94,0))*INDEX($B$5:$B$8,MATCH(C12,$A$5:$A$8,0)),0) | G12: =ROUND(INDEX('Curva Mestra'!$D$20:$D$94,MATCH(D12,'Curva Mestra'!$A$20:$A$94,0))+INDEX($C$5:$C$8,MATCH(C12,$A$5:$A$8,0)),0) | H12: Ronda a regiao do tier Sucata Enferrujada | I12: Mordida Voraz | J12: Causa 1 de sangramento no próximo turno se acertar. | K12: Cão de guarda comum que lambeu sangue seco nas primeiras portas marcadas — agora rosna por instinto de caça, não fome. | L12: =IF(C12="Comum",ROUND(E12*1.3,0),"—") | M12: =IF(C12="Comum",ROUND(F12*1.15,0),"—") | N12: =IF(C12="Comum",G12+2,"—") | O12: =IF(C12="Comum",ROUND(E12*1.6,0),"—") | P12: =IF(C12="Comum",ROUND(F12*1.3,0),"—") | Q12: =IF(C12="Comum",G12+4,"—") | R12: Latidos na Neblina | S12: =ROUND(INDEX('Curva Mestra'!$D$20:$D$94,MATCH(D12,'Curva Mestra'!$A$20:$A$94,0))-IF(C12="Comum",9,IF(C12="Elite",6,IF(C12="Boss",4,3))),0) | T12: Ouro + Couro Áspero de Javali (chance rara) + Presa Sanguínea | U12: Sem fraqueza óbvia — precisa de Knowledge alto pra descobrir algo específico. | V12: DPS | W12: Bosque Sombrio
A13: Sucata Enferrujada | B13: Enxame de Moscas-Sangue | C13: Comum | D13: 1 | E13: =ROUND(INDEX('Curva Mestra'!$F$20:$F$94,MATCH(D13,'Curva Mestra'!$A$20:$A$94,0)),0) | F13: =ROUND(INDEX('Curva Mestra'!$C$20:$C$94,MATCH(D13,'Curva Mestra'!$A$20:$A$94,0))*INDEX($B$5:$B$8,MATCH(C13,$A$5:$A$8,0)),0) | G13: =ROUND(INDEX('Curva Mestra'!$D$20:$D$94,MATCH(D13,'Curva Mestra'!$A$20:$A$94,0))+INDEX($C$5:$C$8,MATCH(C13,$A$5:$A$8,0)),0) | H13: Ligado a Praga, região de Sucata Enferrujada. | I13: Sopro Nauseante | J13: Reduz o Bônus de Ataque do alvo em 1 no próximo turno. | K13: Insetos que se multiplicaram sobre as manchas de sangue seco nas primeiras casas marcadas — respiram a infecção antes de qualquer criatura maior. | L13: =IF(C13="Comum",ROUND(E13*1.3,0),"—") | M13: =IF(C13="Comum",ROUND(F13*1.15,0),"—") | N13: =IF(C13="Comum",G13+2,"—") | O13: =IF(C13="Comum",ROUND(E13*1.6,0),"—") | P13: =IF(C13="Comum",ROUND(F13*1.3,0),"—") | Q13: =IF(C13="Comum",G13+4,"—") | R13: O Enxame que Não Para de Crescer | S13: =ROUND(INDEX('Curva Mestra'!$D$20:$D$94,MATCH(D13,'Curva Mestra'!$A$20:$A$94,0))-IF(C13="Comum",9,IF(C13="Elite",6,IF(C13="Boss",4,3))),0) | T13: Ouro + Couro Áspero de Javali (chance rara) + Asa de Mosca-Sangue | U13: Sem fraqueza óbvia — precisa de Knowledge alto pra descobrir algo específico. | V13: DPS | W13: Bosque Sombrio
A14: Sucata Enferrujada | B14: Cão Rafado | C14: Comum | D14: 1 | E14: =ROUND(INDEX('Curva Mestra'!$F$20:$F$94,MATCH(D14,'Curva Mestra'!$A$20:$A$94,0)),0) | F14: =ROUND(INDEX('Curva Mestra'!$C$20:$C$94,MATCH(D14,'Curva Mestra'!$A$20:$A$94,0))*INDEX($B$5:$B$8,MATCH(C14,$A$5:$A$8,0)),0) | G14: =ROUND(INDEX('Curva Mestra'!$D$20:$D$94,MATCH(D14,'Curva Mestra'!$A$20:$A$94,0))+INDEX($C$5:$C$8,MATCH(C14,$A$5:$A$8,0)),0) | H14: Corre nos arredores da Estrada dos Bandidos, sempre à frente do bando principal. | I14: Ganido de Alerta | J14: Alerta: o próximo encontro no mesmo local vem com +1 monstro. | K14: Corre na frente do bando, marca presas pelo cheiro. | L14: =IF(C14="Comum",ROUND(E14*1.3,0),"—") | M14: =IF(C14="Comum",ROUND(F14*1.15,0),"—") | N14: =IF(C14="Comum",G14+2,"—") | O14: =IF(C14="Comum",ROUND(E14*1.6,0),"—") | P14: =IF(C14="Comum",ROUND(F14*1.3,0),"—") | Q14: =IF(C14="Comum",G14+4,"—") | S14: =ROUND(3+0.6*D14+IF(C14="Comum",0,IF(C14="Elite",2,IF(C14="Boss",4,6))),0) | T14: Couro Áspero de Javali + Canino Enferrujado | U14: Atordoamento | V14: Batedor | W14: Estrada dos Bandidos | X14: Foge a 30% de HP pra buscar reforço.
A15: Sucata Enferrujada | B15: Bandido Novato | C15: Comum | D15: 1 | E15: =ROUND(INDEX('Curva Mestra'!$F$20:$F$94,MATCH(D15,'Curva Mestra'!$A$20:$A$94,0)),0) | F15: =ROUND(INDEX('Curva Mestra'!$C$20:$C$94,MATCH(D15,'Curva Mestra'!$A$20:$A$94,0))*INDEX($B$5:$B$8,MATCH(C15,$A$5:$A$8,0)),0) | G15: =ROUND(INDEX('Curva Mestra'!$D$20:$D$94,MATCH(D15,'Curva Mestra'!$A$20:$A$94,0))+INDEX($C$5:$C$8,MATCH(C15,$A$5:$A$8,0)),0) | H15: Recruta recente do bando que assalta a Estrada dos Bandidos. | I15: Golpe Trêmulo | J15: 25% de chance de errar por conta própria (mão treme). | K15: Entrou no bando semana passada. Ainda não matou ninguém. | L15: =IF(C15="Comum",ROUND(E15*1.3,0),"—") | M15: =IF(C15="Comum",ROUND(F15*1.15,0),"—") | N15: =IF(C15="Comum",G15+2,"—") | O15: =IF(C15="Comum",ROUND(E15*1.6,0),"—") | P15: =IF(C15="Comum",ROUND(F15*1.3,0),"—") | Q15: =IF(C15="Comum",G15+4,"—") | S15: =ROUND(3+0.6*D15+IF(C15="Comum",0,IF(C15="Elite",2,IF(C15="Boss",4,6))),0) | T15: Sucata Retorcida + Faca Cega de Recruta + Pano Ensanguentado | U15: Atordoamento | V15: DPS fraco | W15: Estrada dos Bandidos | Y15: Rende-se a 25% de HP — pode ser poupado (gancho de quest). | Z15: Milícia dos Desamparados aceita entregá-lo vivo em troca de reputação.
A16: Sucata Enferrujada | B16: Criança Marcada | C16: Comum | D16: 1 | E16: =ROUND(INDEX('Curva Mestra'!$F$20:$F$94,MATCH(D16,'Curva Mestra'!$A$20:$A$94,0)),0) | F16: =ROUND(INDEX('Curva Mestra'!$C$20:$C$94,MATCH(D16,'Curva Mestra'!$A$20:$A$94,0))*INDEX($B$5:$B$8,MATCH(C16,$A$5:$A$8,0)),0) | G16: =ROUND(INDEX('Curva Mestra'!$D$20:$D$94,MATCH(D16,'Curva Mestra'!$A$20:$A$94,0))+INDEX($C$5:$C$8,MATCH(C16,$A$5:$A$8,0)),0) | H16: Encontrada perdida no Acampamento dos Marcados. | I16: (não ataca) | J16: Não-hostil: só ataca se atacada primeiro. Se poupada, revela um local secreto. | K16: Não entende o que aconteceu com ela. Ainda procura a mãe. | L16: =IF(C16="Comum",ROUND(E16*1.3,0),"—") | M16: =IF(C16="Comum",ROUND(F16*1.15,0),"—") | N16: =IF(C16="Comum",G16+2,"—") | O16: =IF(C16="Comum",ROUND(E16*1.6,0),"—") | P16: =IF(C16="Comum",ROUND(F16*1.3,0),"—") | Q16: =IF(C16="Comum",G16+4,"—") | S16: =ROUND(3+0.6*D16+IF(C16="Comum",0,IF(C16="Elite",2,IF(C16="Boss",4,6))),0) | T16: Ouro + Boneco de Pano Remendado | U16: Sem fraqueza óbvia — precisa de Knowledge alto pra descobrir algo específico. | V16: Não-hostil | W16: Acampamento dos Marcados | Y16: Segue o jogador em silêncio por 2 explorações se poupada.
A17: Sucata Enferrujada | B17: Acólito Recém-Marcado | C17: Comum | D17: 1 | E17: =ROUND(INDEX('Curva Mestra'!$F$20:$F$94,MATCH(D17,'Curva Mestra'!$A$20:$A$94,0)),0) | F17: =ROUND(INDEX('Curva Mestra'!$C$20:$C$94,MATCH(D17,'Curva Mestra'!$A$20:$A$94,0))*INDEX($B$5:$B$8,MATCH(C17,$A$5:$A$8,0)),0) | G17: =ROUND(INDEX('Curva Mestra'!$D$20:$D$94,MATCH(D17,'Curva Mestra'!$A$20:$A$94,0))+INDEX($C$5:$C$8,MATCH(C17,$A$5:$A$8,0)),0) | H17: Novo membro do culto, ainda no Acampamento dos Marcados. | I17: Corte Hesitante | J17: Nenhum efeito adicional. | K17: Marcou a própria porta ontem. Ainda tem a mão tremendo. | L17: =IF(C17="Comum",ROUND(E17*1.3,0),"—") | M17: =IF(C17="Comum",ROUND(F17*1.15,0),"—") | N17: =IF(C17="Comum",G17+2,"—") | O17: =IF(C17="Comum",ROUND(E17*1.6,0),"—") | P17: =IF(C17="Comum",ROUND(F17*1.3,0),"—") | Q17: =IF(C17="Comum",G17+4,"—") | S17: =ROUND(3+0.6*D17+IF(C17="Comum",0,IF(C17="Elite",2,IF(C17="Boss",4,6))),0) | T17: Ouro + Fragmento de Tinta Ritual + Pano do Culto Rasgado | U17: Ignora Defesa | V17: DPS fraco | W17: Acampamento dos Marcados
A18: Sucata Enferrujada | B18: Leitão Marcado | C18: Comum | D18: 1 | E18: =ROUND(INDEX('Curva Mestra'!$F$20:$F$94,MATCH(D18,'Curva Mestra'!$A$20:$A$94,0)),0) | F18: =ROUND(INDEX('Curva Mestra'!$C$20:$C$94,MATCH(D18,'Curva Mestra'!$A$20:$A$94,0))*INDEX($B$5:$B$8,MATCH(C18,$A$5:$A$8,0)),0) | G18: =ROUND(INDEX('Curva Mestra'!$D$20:$D$94,MATCH(D18,'Curva Mestra'!$A$20:$A$94,0))+INDEX($C$5:$C$8,MATCH(C18,$A$5:$A$8,0)),0) | H18: Filhote do Javali Alfa, encontrado no Bosque Sombrio. | I18: Mordidinha | J18: Nenhum efeito adicional — sempre aparecem em grupo de 3. | K18: Ninhada do Javali Alfa. Já nasceram com a marca. | L18: =IF(C18="Comum",ROUND(E18*1.3,0),"—") | M18: =IF(C18="Comum",ROUND(F18*1.15,0),"—") | N18: =IF(C18="Comum",G18+2,"—") | O18: =IF(C18="Comum",ROUND(E18*1.6,0),"—") | P18: =IF(C18="Comum",ROUND(F18*1.3,0),"—") | Q18: =IF(C18="Comum",G18+4,"—") | S18: =ROUND(3+0.6*D18+IF(C18="Comum",0,IF(C18="Elite",2,IF(C18="Boss",4,6))),0) | T18: Ouro + Presa de Leitão + Couro Marcado de Leitão | U18: Queimadura | V18: Enxame | W18: Bosque Sombrio | Y18: Chamam o Javali Alfa se todos morrerem (10% de chance).
A19: Sucata Enferrujada | B19: Carrapato Grande do Javali | C19: Comum | D19: 1 | E19: =ROUND(INDEX('Curva Mestra'!$F$20:$F$94,MATCH(D19,'Curva Mestra'!$A$20:$A$94,0)),0) | F19: =ROUND(INDEX('Curva Mestra'!$C$20:$C$94,MATCH(D19,'Curva Mestra'!$A$20:$A$94,0))*INDEX($B$5:$B$8,MATCH(C19,$A$5:$A$8,0)),0) | G19: =ROUND(INDEX('Curva Mestra'!$D$20:$D$94,MATCH(D19,'Curva Mestra'!$A$20:$A$94,0))+INDEX($C$5:$C$8,MATCH(C19,$A$5:$A$8,0)),0) | H19: Vive grudado no Javali Selvagem Alfa ou em seus filhotes. | I19: Fixar | J19: Rouba Vida (15%) — só aparece junto com Javali Alfa ou Leitão. | K19: Vive no lombo dos javalis marcados, bebe o sangue infectado. | L19: =IF(C19="Comum",ROUND(E19*1.3,0),"—") | M19: =IF(C19="Comum",ROUND(F19*1.15,0),"—") | N19: =IF(C19="Comum",G19+2,"—") | O19: =IF(C19="Comum",ROUND(E19*1.6,0),"—") | P19: =IF(C19="Comum",ROUND(F19*1.3,0),"—") | Q19: =IF(C19="Comum",G19+4,"—") | S19: =ROUND(3+0.6*D19+IF(C19="Comum",0,IF(C19="Elite",2,IF(C19="Boss",4,6))),0) | T19: Ouro + Glândula de Carrapato | U19: Queimadura | V19: Parasita | W19: Bosque Sombrio, só com Javali/Leitão presente | Y19: Se o hospedeiro morrer, fica 2x mais agressivo.
A20: Sucata Enferrujada | B20: Bandido de Estrada Marcado | C20: Comum | D20: 2 | E20: =ROUND(INDEX('Curva Mestra'!$F$20:$F$94,MATCH(D20,'Curva Mestra'!$A$20:$A$94,0)),0) | F20: =ROUND(INDEX('Curva Mestra'!$C$20:$C$94,MATCH(D20,'Curva Mestra'!$A$20:$A$94,0))*INDEX($B$5:$B$8,MATCH(C20,$A$5:$A$8,0)),0) | G20: =ROUND(INDEX('Curva Mestra'!$D$20:$D$94,MATCH(D20,'Curva Mestra'!$A$20:$A$94,0))+INDEX($C$5:$C$8,MATCH(C20,$A$5:$A$8,0)),0) | H20: Ronda a regiao do tier Sucata Enferrujada | I20: Faca Enferrujada | J20: Nada especial — ameaça pela quantidade, não pela força. | K20: Bandido comum que achou um caco do "Fragmento do Sangue" perdido na estrada e o carrega como amuleto de sorte, sem saber o que é. | L20: =IF(C20="Comum",ROUND(E20*1.3,0),"—") | M20: =IF(C20="Comum",ROUND(F20*1.15,0),"—") | N20: =IF(C20="Comum",G20+2,"—") | O20: =IF(C20="Comum",ROUND(E20*1.6,0),"—") | P20: =IF(C20="Comum",ROUND(F20*1.3,0),"—") | Q20: =IF(C20="Comum",G20+4,"—") | R20: A Estrada Insegura; O Baú do Salteador Afogado | S20: =ROUND(INDEX('Curva Mestra'!$D$20:$D$94,MATCH(D20,'Curva Mestra'!$A$20:$A$94,0))-IF(C20="Comum",9,IF(C20="Elite",6,IF(C20="Boss",4,3))),0) | T20: Ouro + Couro Áspero de Javali (chance rara) + Faca Enferrujada de Bandido | U20: Sem fraqueza óbvia — precisa de Knowledge alto pra descobrir algo específico. | V20: DPS | W20: Bosque Sombrio
A21: Sucata Enferrujada | B21: Peregrino Marcado | C21: Comum | D21: 2 | E21: =ROUND(INDEX('Curva Mestra'!$F$20:$F$94,MATCH(D21,'Curva Mestra'!$A$20:$A$94,0)),0) | F21: =ROUND(INDEX('Curva Mestra'!$C$20:$C$94,MATCH(D21,'Curva Mestra'!$A$20:$A$94,0))*INDEX($B$5:$B$8,MATCH(C21,$A$5:$A$8,0)),0) | G21: =ROUND(INDEX('Curva Mestra'!$D$20:$D$94,MATCH(D21,'Curva Mestra'!$A$20:$A$94,0))+INDEX($C$5:$C$8,MATCH(C21,$A$5:$A$8,0)),0) | H21: Ligado a Zumbi, região de Sucata Enferrujada. | I21: Abraço de Ferrugem | J21: Tenta imobilizar o alvo por 1 turno (teste FOR CD 10 pra escapar). | K21: Um camponês que tocou uma porta pintada com dedos ensanguentados por curiosidade. Ainda usa as roupas de viagem — só nunca chegou a lugar nenhum. | L21: =IF(C21="Comum",ROUND(E21*1.3,0),"—") | M21: =IF(C21="Comum",ROUND(F21*1.15,0),"—") | N21: =IF(C21="Comum",G21+2,"—") | O21: =IF(C21="Comum",ROUND(E21*1.6,0),"—") | P21: =IF(C21="Comum",ROUND(F21*1.3,0),"—") | Q21: =IF(C21="Comum",G21+4,"—") | R21: O Amigo que Sumiu | S21: =ROUND(INDEX('Curva Mestra'!$D$20:$D$94,MATCH(D21,'Curva Mestra'!$A$20:$A$94,0))-IF(C21="Comum",9,IF(C21="Elite",6,IF(C21="Boss",4,3))),0) | T21: Ouro + Couro Áspero de Javali (chance rara) + Manto Rasgado de Peregrino | U21: Sem fraqueza óbvia — precisa de Knowledge alto pra descobrir algo específico. | V21: Controle | W21: Bosque Sombrio
A22: Sucata Enferrujada | B22: Enxame de Vermes Pálidos | C22: Comum | D22: 2 | E22: =ROUND(INDEX('Curva Mestra'!$F$20:$F$94,MATCH(D22,'Curva Mestra'!$A$20:$A$94,0)),0) | F22: =ROUND(INDEX('Curva Mestra'!$C$20:$C$94,MATCH(D22,'Curva Mestra'!$A$20:$A$94,0))*INDEX($B$5:$B$8,MATCH(C22,$A$5:$A$8,0)),0) | G22: =ROUND(INDEX('Curva Mestra'!$D$20:$D$94,MATCH(D22,'Curva Mestra'!$A$20:$A$94,0))+INDEX($C$5:$C$8,MATCH(C22,$A$5:$A$8,0)),0) | H22: Infesta o Veio de Sucata, alimentando-se dos restos do minério. | I22: Mordida Ácida | J22: Veneno (1 dano/turno, 2 turnos). | K22: Vivem no minério enferrujado, comem o que sobra dos mineradores. | L22: =IF(C22="Comum",ROUND(E22*1.3,0),"—") | M22: =IF(C22="Comum",ROUND(F22*1.15,0),"—") | N22: =IF(C22="Comum",G22+2,"—") | O22: =IF(C22="Comum",ROUND(E22*1.6,0),"—") | P22: =IF(C22="Comum",ROUND(F22*1.3,0),"—") | Q22: =IF(C22="Comum",G22+4,"—") | S22: =ROUND(3+0.6*D22+IF(C22="Comum",0,IF(C22="Elite",2,IF(C22="Boss",4,6))),0) | T22: Sucata Retorcida + Casulo de Verme Pálido + Baba Corrosiva | U22: Queimadura | V22: Debuffer | W22: Veio de Sucata | Y22: Contamina o material coletado ali (perde 1 unidade).
A23: Sucata Enferrujada | B23: Casulo Pulsante | C23: Comum | D23: 2 | E23: =ROUND(INDEX('Curva Mestra'!$F$20:$F$94,MATCH(D23,'Curva Mestra'!$A$20:$A$94,0)),0) | F23: =ROUND(INDEX('Curva Mestra'!$C$20:$C$94,MATCH(D23,'Curva Mestra'!$A$20:$A$94,0))*INDEX($B$5:$B$8,MATCH(C23,$A$5:$A$8,0)),0) | G23: =ROUND(INDEX('Curva Mestra'!$D$20:$D$94,MATCH(D23,'Curva Mestra'!$A$20:$A$94,0))+INDEX($C$5:$C$8,MATCH(C23,$A$5:$A$8,0)),0) | H23: Plantado no Pântano dos Enxames por mãos desconhecidas. | I23: (não ataca) | J23: Explode ao morrer: 3 de dano + Veneno em quem matou. | K23: Não é criatura — é um berço. Alguém plantou ali de propósito. | L23: =IF(C23="Comum",ROUND(E23*1.3,0),"—") | M23: =IF(C23="Comum",ROUND(F23*1.15,0),"—") | N23: =IF(C23="Comum",G23+2,"—") | O23: =IF(C23="Comum",ROUND(E23*1.6,0),"—") | P23: =IF(C23="Comum",ROUND(F23*1.3,0),"—") | Q23: =IF(C23="Comum",G23+4,"—") | S23: =ROUND(3+0.6*D23+IF(C23="Comum",0,IF(C23="Elite",2,IF(C23="Boss",4,6))),0) | T23: Ouro + Membrana Pulsante | U23: Ignora Defesa | V23: Explosivo | W23: Pântano dos Enxames | Y23: Se ignorado por 3 turnos, vira Enxame de Vermes Pálidos.
A24: Sucata Enferrujada | B24: Mão Decepada Rastejante | C24: Comum | D24: 2 | E24: =ROUND(INDEX('Curva Mestra'!$F$20:$F$94,MATCH(D24,'Curva Mestra'!$A$20:$A$94,0)),0) | F24: =ROUND(INDEX('Curva Mestra'!$C$20:$C$94,MATCH(D24,'Curva Mestra'!$A$20:$A$94,0))*INDEX($B$5:$B$8,MATCH(C24,$A$5:$A$8,0)),0) | G24: =ROUND(INDEX('Curva Mestra'!$D$20:$D$94,MATCH(D24,'Curva Mestra'!$A$20:$A$94,0))+INDEX($C$5:$C$8,MATCH(C24,$A$5:$A$8,0)),0) | H24: Esconde-se entre os corpos do Acampamento dos Marcados. | I24: Agarrar a Garganta | J24: Sangramento + impede fuga por 1 turno. | K24: Alguém cortou a própria mão pra impedir a marca de subir. Não adiantou. | L24: =IF(C24="Comum",ROUND(E24*1.3,0),"—") | M24: =IF(C24="Comum",ROUND(F24*1.15,0),"—") | N24: =IF(C24="Comum",G24+2,"—") | O24: =IF(C24="Comum",ROUND(E24*1.6,0),"—") | P24: =IF(C24="Comum",ROUND(F24*1.3,0),"—") | Q24: =IF(C24="Comum",G24+4,"—") | S24: =ROUND(3+0.6*D24+IF(C24="Comum",0,IF(C24="Elite",2,IF(C24="Boss",4,6))),0) | T24: Ouro + Dedo Enrijecido + Anel Perdido | U24: Atordoamento | V24: Assassino | W24: Acampamento dos Marcados | Y24: Se esconde entre cadáveres — emboscada.
A25: Sucata Enferrujada | B25: Corvo Necrófago | C25: Comum | D25: 2 | E25: =ROUND(INDEX('Curva Mestra'!$F$20:$F$94,MATCH(D25,'Curva Mestra'!$A$20:$A$94,0)),0) | F25: =ROUND(INDEX('Curva Mestra'!$C$20:$C$94,MATCH(D25,'Curva Mestra'!$A$20:$A$94,0))*INDEX($B$5:$B$8,MATCH(C25,$A$5:$A$8,0)),0) | G25: =ROUND(INDEX('Curva Mestra'!$D$20:$D$94,MATCH(D25,'Curva Mestra'!$A$20:$A$94,0))+INDEX($C$5:$C$8,MATCH(C25,$A$5:$A$8,0)),0) | H25: Sobrevoa qualquer área da região onde um combate acabou de acontecer. | I25: Bicada nos Olhos | J25: -2 na chance de acerto do jogador por 1 turno. | K25: Segue os mortos. Onde ele pousa, alguém caiu. | L25: =IF(C25="Comum",ROUND(E25*1.3,0),"—") | M25: =IF(C25="Comum",ROUND(F25*1.15,0),"—") | N25: =IF(C25="Comum",G25+2,"—") | O25: =IF(C25="Comum",ROUND(E25*1.6,0),"—") | P25: =IF(C25="Comum",ROUND(F25*1.3,0),"—") | Q25: =IF(C25="Comum",G25+4,"—") | S25: =ROUND(3+0.6*D25+IF(C25="Comum",0,IF(C25="Elite",2,IF(C25="Boss",4,6))),0) | T25: Ouro + Pena Necrófaga + Bico de Corvo | U25: Atordoamento | V25: Necrófago | W25: Qualquer local, após um combate vencido | Y25: Cura 5 HP por cadáver presente no local.
A26: Sucata Enferrujada | B26: Corredor de Sangue | C26: Comum | D26: 2 | E26: =ROUND(INDEX('Curva Mestra'!$F$20:$F$94,MATCH(D26,'Curva Mestra'!$A$20:$A$94,0)),0) | F26: =ROUND(INDEX('Curva Mestra'!$C$20:$C$94,MATCH(D26,'Curva Mestra'!$A$20:$A$94,0))*INDEX($B$5:$B$8,MATCH(C26,$A$5:$A$8,0)),0) | G26: =ROUND(INDEX('Curva Mestra'!$D$20:$D$94,MATCH(D26,'Curva Mestra'!$A$20:$A$94,0))+INDEX($C$5:$C$8,MATCH(C26,$A$5:$A$8,0)),0) | H26: Golpeia e foge, nunca fica pra terminar a luta. | I26: Corte de Passagem | J26: Sangramento — sempre ataca e tenta fugir no turno seguinte. | K26: Bandido que prefere ferir e correr a lutar até o fim. | L26: =IF(C26="Comum",ROUND(E26*1.3,0),"—") | M26: =IF(C26="Comum",ROUND(F26*1.15,0),"—") | N26: =IF(C26="Comum",G26+2,"—") | O26: =IF(C26="Comum",ROUND(E26*1.6,0),"—") | P26: =IF(C26="Comum",ROUND(F26*1.3,0),"—") | Q26: =IF(C26="Comum",G26+4,"—") | S26: =ROUND(3+0.6*D26+IF(C26="Comum",0,IF(C26="Elite",2,IF(C26="Boss",4,6))),0) | T26: Ouro + Faca de Corte Rápido Quebrada | U26: Lentidão | V26: Batedor | W26: Estrada dos Bandidos
A27: Sucata Enferrujada | B27: Saqueador de Caravana | C27: Comum | D27: 3 | E27: =ROUND(INDEX('Curva Mestra'!$F$20:$F$94,MATCH(D27,'Curva Mestra'!$A$20:$A$94,0)),0) | F27: =ROUND(INDEX('Curva Mestra'!$C$20:$C$94,MATCH(D27,'Curva Mestra'!$A$20:$A$94,0))*INDEX($B$5:$B$8,MATCH(C27,$A$5:$A$8,0)),0) | G27: =ROUND(INDEX('Curva Mestra'!$D$20:$D$94,MATCH(D27,'Curva Mestra'!$A$20:$A$94,0))+INDEX($C$5:$C$8,MATCH(C27,$A$5:$A$8,0)),0) | H27: Ronda a Estrada dos Bandidos à espera de comerciantes desavisados. | I27: Bote Rápido | J27: Rouba 10% do seu Ouro e tenta fugir no turno seguinte. | K27: Não quer te matar. Quer o que você carrega. | L27: =IF(C27="Comum",ROUND(E27*1.3,0),"—") | M27: =IF(C27="Comum",ROUND(F27*1.15,0),"—") | N27: =IF(C27="Comum",G27+2,"—") | O27: =IF(C27="Comum",ROUND(E27*1.6,0),"—") | P27: =IF(C27="Comum",ROUND(F27*1.3,0),"—") | Q27: =IF(C27="Comum",G27+4,"—") | S27: =ROUND(3+0.6*D27+IF(C27="Comum",0,IF(C27="Elite",2,IF(C27="Boss",4,6))),0) | T27: Sucata Retorcida + Bolsa de Moedas Roubadas + Corda de Saque | U27: Lentidão | V27: Ladrão | W27: Estrada dos Bandidos | Y27: Foge com o ouro se sobreviver 3 turnos — rastreável (SAB).
A28: Sucata Enferrujada | B28: Peregrino Enlouquecido | C28: Comum | D28: 3 | E28: =ROUND(INDEX('Curva Mestra'!$F$20:$F$94,MATCH(D28,'Curva Mestra'!$A$20:$A$94,0)),0) | F28: =ROUND(INDEX('Curva Mestra'!$C$20:$C$94,MATCH(D28,'Curva Mestra'!$A$20:$A$94,0))*INDEX($B$5:$B$8,MATCH(C28,$A$5:$A$8,0)),0) | G28: =ROUND(INDEX('Curva Mestra'!$D$20:$D$94,MATCH(D28,'Curva Mestra'!$A$20:$A$94,0))+INDEX($C$5:$C$8,MATCH(C28,$A$5:$A$8,0)),0) | H28: Vaga pelo Acampamento dos Marcados repetindo sons sem sentido. | I28: Grito Sem Palavras | J28: Atordoamento (20% de chance). | K28: A marca chegou na garganta. Não fala mais, só grita. | L28: =IF(C28="Comum",ROUND(E28*1.3,0),"—") | M28: =IF(C28="Comum",ROUND(F28*1.15,0),"—") | N28: =IF(C28="Comum",G28+2,"—") | O28: =IF(C28="Comum",ROUND(E28*1.6,0),"—") | P28: =IF(C28="Comum",ROUND(F28*1.3,0),"—") | Q28: =IF(C28="Comum",G28+4,"—") | S28: =ROUND(3+0.6*D28+IF(C28="Comum",0,IF(C28="Elite",2,IF(C28="Boss",4,6))),0) | T28: Ouro + Farrapo de Peregrino + Fragmento de Grito Preso | U28: Queimadura | V28: Controle | W28: Acampamento dos Marcados | Y28: O grito acorda outros Marcados próximos.
A29: Sucata Enferrujada | B29: Sombra da Primeira Porta | C29: Comum | D29: 3 | E29: =ROUND(INDEX('Curva Mestra'!$F$20:$F$94,MATCH(D29,'Curva Mestra'!$A$20:$A$94,0)),0) | F29: =ROUND(INDEX('Curva Mestra'!$C$20:$C$94,MATCH(D29,'Curva Mestra'!$A$20:$A$94,0))*INDEX($B$5:$B$8,MATCH(C29,$A$5:$A$8,0)),0) | G29: =ROUND(INDEX('Curva Mestra'!$D$20:$D$94,MATCH(D29,'Curva Mestra'!$A$20:$A$94,0))+INDEX($C$5:$C$8,MATCH(C29,$A$5:$A$8,0)),0) | H29: Manifestação fraca da própria marca original. | I29: Toque da Marca Original | J29: Fragilidade — equipamento perde durabilidade mais rápido perto dele. | K29: Resíduo vivo da primeira porta que a Mão marcou nessa região. | L29: =IF(C29="Comum",ROUND(E29*1.3,0),"—") | M29: =IF(C29="Comum",ROUND(F29*1.15,0),"—") | N29: =IF(C29="Comum",G29+2,"—") | O29: =IF(C29="Comum",ROUND(E29*1.6,0),"—") | P29: =IF(C29="Comum",ROUND(F29*1.3,0),"—") | Q29: =IF(C29="Comum",G29+4,"—") | S29: =ROUND(3+0.6*D29+IF(C29="Comum",0,IF(C29="Elite",2,IF(C29="Boss",4,6))),0) | T29: Ouro + Estilhaço da Marca Original | U29: Queimadura | V29: DPS | W29: Acampamento dos Marcados
A30: Sucata Enferrujada | B30: Bandido Veterano | C30: Comum | D30: 4 | E30: =ROUND(INDEX('Curva Mestra'!$F$20:$F$94,MATCH(D30,'Curva Mestra'!$A$20:$A$94,0)),0) | F30: =ROUND(INDEX('Curva Mestra'!$C$20:$C$94,MATCH(D30,'Curva Mestra'!$A$20:$A$94,0))*INDEX($B$5:$B$8,MATCH(C30,$A$5:$A$8,0)),0) | G30: =ROUND(INDEX('Curva Mestra'!$D$20:$D$94,MATCH(D30,'Curva Mestra'!$A$20:$A$94,0))+INDEX($C$5:$C$8,MATCH(C30,$A$5:$A$8,0)),0) | H30: Sobrevivente de vários confrontos na Estrada dos Bandidos. | I30: Corte Duplo | J30: Ataca 2x por turno, dano reduzido em cada golpe. | K30: Sobreviveu a 3 marcações e continua na estrada. | L30: =IF(C30="Comum",ROUND(E30*1.3,0),"—") | M30: =IF(C30="Comum",ROUND(F30*1.15,0),"—") | N30: =IF(C30="Comum",G30+2,"—") | O30: =IF(C30="Comum",ROUND(E30*1.6,0),"—") | P30: =IF(C30="Comum",ROUND(F30*1.3,0),"—") | Q30: =IF(C30="Comum",G30+4,"—") | S30: =ROUND(3+0.6*D30+IF(C30="Comum",0,IF(C30="Elite",2,IF(C30="Boss",4,6))),0) | T30: Sucata Retorcida + Cicatriz de Couro Curtido + Machadinha Gasta | U30: Fragilidade | V30: DPS | W30: Estrada dos Bandidos | Y30: Ataca primeiro quem tem menos HP.
A31: Sucata Enferrujada | B31: Fanático dos Dedos Rubros | C31: Elite | D31: 2 | E31: =ROUND(INDEX('Curva Mestra'!$G$20:$G$94,MATCH(D31,'Curva Mestra'!$A$20:$A$94,0)),0) | F31: =ROUND(INDEX('Curva Mestra'!$C$20:$C$94,MATCH(D31,'Curva Mestra'!$A$20:$A$94,0))*INDEX($B$5:$B$8,MATCH(C31,$A$5:$A$8,0)),0) | G31: =ROUND(INDEX('Curva Mestra'!$D$20:$D$94,MATCH(D31,'Curva Mestra'!$A$20:$A$94,0))+INDEX($C$5:$C$8,MATCH(C31,$A$5:$A$8,0)),0) | H31: Encontro dificil dentro do tier Sucata Enferrujada | I31: Marca de Sangue | J31: Reduz a Defesa do herói em 1 até o fim do combate. | K31: Cultista que pintou o próprio rosto com sangue de vítimas — acredita que está "abrindo caminho" para a Mão. | L31: =IF(C31="Comum",ROUND(E31*1.3,0),"—") | M31: =IF(C31="Comum",ROUND(F31*1.15,0),"—") | N31: =IF(C31="Comum",G31+2,"—") | O31: =IF(C31="Comum",ROUND(E31*1.6,0),"—") | P31: =IF(C31="Comum",ROUND(F31*1.3,0),"—") | Q31: =IF(C31="Comum",G31+4,"—") | R31: As Portas Marcadas | S31: =ROUND(INDEX('Curva Mestra'!$D$20:$D$94,MATCH(D31,'Curva Mestra'!$A$20:$A$94,0))-IF(C31="Comum",9,IF(C31="Elite",6,IF(C31="Boss",4,3))),0) | T31: Fragmento de Fanático dos Dedos Rubros + Ouro + Couro Áspero de Javali (chance baixa) | U31: Perde o bônus de grupo se isolado dos outros cultistas em combate. | V31: DPS | W31: Bosque Sombrio
A32: Sucata Enferrujada | B32: Cadela-Mãe da Ninhada | C32: Elite | D32: 3 | E32: =ROUND(INDEX('Curva Mestra'!$G$20:$G$94,MATCH(D32,'Curva Mestra'!$A$20:$A$94,0)),0) | F32: =ROUND(INDEX('Curva Mestra'!$C$20:$C$94,MATCH(D32,'Curva Mestra'!$A$20:$A$94,0))*INDEX($B$5:$B$8,MATCH(C32,$A$5:$A$8,0)),0) | G32: =ROUND(INDEX('Curva Mestra'!$D$20:$D$94,MATCH(D32,'Curva Mestra'!$A$20:$A$94,0))+INDEX($C$5:$C$8,MATCH(C32,$A$5:$A$8,0)),0) | H32: Vive no Bosque Sombrio, escondida com a ninhada durante o dia. | I32: Chamado da Ninhada | J32: Invoca 2 Filhotes (Nv.1, HP baixo) ao chegar a 60% HP. | K32: Pariu no meio do sangue seco — os filhotes já nasceram marcados. | L32: =IF(C32="Comum",ROUND(E32*1.3,0),"—") | M32: =IF(C32="Comum",ROUND(F32*1.15,0),"—") | N32: =IF(C32="Comum",G32+2,"—") | O32: =IF(C32="Comum",ROUND(E32*1.6,0),"—") | P32: =IF(C32="Comum",ROUND(F32*1.3,0),"—") | Q32: =IF(C32="Comum",G32+4,"—") | S32: =ROUND(3+0.6*D32+IF(C32="Comum",0,IF(C32="Elite",2,IF(C32="Boss",4,6))),0) | T32: Couro Áspero de Javali, Presa | U32: Queimadura | V32: Invocador | W32: Bosque Sombrio, só à noite | X32: Enfurece se os 2 filhotes morrerem: +50% de dano. | Y32: Cava toca — some se você recuar.
A33: Sucata Enferrujada | B33: Sussurrador de Portas | C33: Elite | D33: 3 | E33: =ROUND(INDEX('Curva Mestra'!$G$20:$G$94,MATCH(D33,'Curva Mestra'!$A$20:$A$94,0)),0) | F33: =ROUND(INDEX('Curva Mestra'!$C$20:$C$94,MATCH(D33,'Curva Mestra'!$A$20:$A$94,0))*INDEX($B$5:$B$8,MATCH(C33,$A$5:$A$8,0)),0) | G33: =ROUND(INDEX('Curva Mestra'!$D$20:$D$94,MATCH(D33,'Curva Mestra'!$A$20:$A$94,0))+INDEX($C$5:$C$8,MATCH(C33,$A$5:$A$8,0)),0) | H33: Recita nomes de casas no centro do Acampamento dos Marcados. | I33: Ladainha da Mão | J33: Cura 3 HP/turno em todos os cultistas vivos no combate (não ataca). | K33: Recita os nomes das casas que ainda não foram marcadas. | L33: =IF(C33="Comum",ROUND(E33*1.3,0),"—") | M33: =IF(C33="Comum",ROUND(F33*1.15,0),"—") | N33: =IF(C33="Comum",G33+2,"—") | O33: =IF(C33="Comum",ROUND(E33*1.6,0),"—") | P33: =IF(C33="Comum",ROUND(F33*1.3,0),"—") | Q33: =IF(C33="Comum",G33+4,"—") | S33: =ROUND(3+0.6*D33+IF(C33="Comum",0,IF(C33="Elite",2,IF(C33="Boss",4,6))),0) | T33: Ouro + Voz Presa em Pano + Manto do Sussurrador | U33: Ignora Resistência Mágica | V33: Suporte | W33: Acampamento dos Marcados | Y33: Foge se for o último cultista vivo.
A34: Sucata Enferrujada | B34: Pintor de Portas | C34: Elite | D34: 3 | E34: =ROUND(INDEX('Curva Mestra'!$G$20:$G$94,MATCH(D34,'Curva Mestra'!$A$20:$A$94,0)),0) | F34: =ROUND(INDEX('Curva Mestra'!$C$20:$C$94,MATCH(D34,'Curva Mestra'!$A$20:$A$94,0))*INDEX($B$5:$B$8,MATCH(C34,$A$5:$A$8,0)),0) | G34: =ROUND(INDEX('Curva Mestra'!$D$20:$D$94,MATCH(D34,'Curva Mestra'!$A$20:$A$94,0))+INDEX($C$5:$C$8,MATCH(C34,$A$5:$A$8,0)),0) | H34: Circula pelo Acampamento dos Marcados marcando o que encontra. | I34: Marca na Testa | J34: Marca o jogador: +25% de dano recebido de cultistas por 3 turnos. | K34: Não luta. Marca. Outro vem terminar o serviço. | L34: =IF(C34="Comum",ROUND(E34*1.3,0),"—") | M34: =IF(C34="Comum",ROUND(F34*1.15,0),"—") | N34: =IF(C34="Comum",G34+2,"—") | O34: =IF(C34="Comum",ROUND(E34*1.6,0),"—") | P34: =IF(C34="Comum",ROUND(F34*1.3,0),"—") | Q34: =IF(C34="Comum",G34+4,"—") | S34: =ROUND(3+0.6*D34+IF(C34="Comum",0,IF(C34="Elite",2,IF(C34="Boss",4,6))),0) | T34: Ouro + Tinta Ritual Concentrada + Pincel de Ossos | U34: Atordoamento | V34: Debuffer | W34: Acampamento dos Marcados | Y34: Se sobreviver ao combate, o local ganha +1 Perigo permanente.
A35: Sucata Enferrujada | B35: Baú de Oferendas Falso | C35: Elite | D35: 3 | E35: =ROUND(INDEX('Curva Mestra'!$G$20:$G$94,MATCH(D35,'Curva Mestra'!$A$20:$A$94,0)),0) | F35: =ROUND(INDEX('Curva Mestra'!$C$20:$C$94,MATCH(D35,'Curva Mestra'!$A$20:$A$94,0))*INDEX($B$5:$B$8,MATCH(C35,$A$5:$A$8,0)),0) | G35: =ROUND(INDEX('Curva Mestra'!$D$20:$D$94,MATCH(D35,'Curva Mestra'!$A$20:$A$94,0))+INDEX($C$5:$C$8,MATCH(C35,$A$5:$A$8,0)),0) | H35: Disfarçado entre os pertences deixados na Estrada dos Bandidos. | I35: Mordida do Cofre | J35: Ignora Defesa + jogador perde 1 turno de surpresa. | K35: Cultistas deixam baús falsos nas estradas pra pegar saqueadores. | L35: =IF(C35="Comum",ROUND(E35*1.3,0),"—") | M35: =IF(C35="Comum",ROUND(F35*1.15,0),"—") | N35: =IF(C35="Comum",G35+2,"—") | O35: =IF(C35="Comum",ROUND(E35*1.6,0),"—") | P35: =IF(C35="Comum",ROUND(F35*1.3,0),"—") | Q35: =IF(C35="Comum",G35+4,"—") | S35: =ROUND(3+0.6*D35+IF(C35="Comum",0,IF(C35="Elite",2,IF(C35="Boss",4,6))),0) | T35: Sucata Retorcida x3 | U35: Atordoamento | V35: Mímico | W35: Estrada/Acampamento, 5% ao encontrar um baú | Y35: Parece loot comum — só revela a natureza ao ser interagido.
A36: Sucata Enferrujada | B36: Besouro-Cofre Enferrujado | C36: Elite | D36: 3 | E36: =ROUND(INDEX('Curva Mestra'!$G$20:$G$94,MATCH(D36,'Curva Mestra'!$A$20:$A$94,0)),0) | F36: =ROUND(INDEX('Curva Mestra'!$C$20:$C$94,MATCH(D36,'Curva Mestra'!$A$20:$A$94,0))*INDEX($B$5:$B$8,MATCH(C36,$A$5:$A$8,0)),0) | G36: =ROUND(INDEX('Curva Mestra'!$D$20:$D$94,MATCH(D36,'Curva Mestra'!$A$20:$A$94,0))+INDEX($C$5:$C$8,MATCH(C36,$A$5:$A$8,0)),0) | H36: Raramente visto no Veio de Sucata, atraído por metal solto. | I36: Ferrão de Fuga | J36: Não causa dano — foge no turno 3 se não for derrotado antes. | K36: Come metal. O que ele engoliu vale mais que ele. | L36: =IF(C36="Comum",ROUND(E36*1.3,0),"—") | M36: =IF(C36="Comum",ROUND(F36*1.15,0),"—") | N36: =IF(C36="Comum",G36+2,"—") | O36: =IF(C36="Comum",ROUND(E36*1.6,0),"—") | P36: =IF(C36="Comum",ROUND(F36*1.3,0),"—") | Q36: =IF(C36="Comum",G36+4,"—") | S36: =ROUND(3+0.6*D36+IF(C36="Comum",0,IF(C36="Elite",2,IF(C36="Boss",4,6))),0) | T36: Minério de Bronze Sulfuroso (material de Tier 2) | U36: Lentidão | V36: Superloot / Evasivo | W36: Veio de Sucata, spawn raro (2%)
A37: Sucata Enferrujada | B37: Caçador de Marcas | C37: Elite | D37: 4 | E37: =ROUND(INDEX('Curva Mestra'!$G$20:$G$94,MATCH(D37,'Curva Mestra'!$A$20:$A$94,0)),0) | F37: =ROUND(INDEX('Curva Mestra'!$C$20:$C$94,MATCH(D37,'Curva Mestra'!$A$20:$A$94,0))*INDEX($B$5:$B$8,MATCH(C37,$A$5:$A$8,0)),0) | G37: =ROUND(INDEX('Curva Mestra'!$D$20:$D$94,MATCH(D37,'Curva Mestra'!$A$20:$A$94,0))+INDEX($C$5:$C$8,MATCH(C37,$A$5:$A$8,0)),0) | H37: Ligado a Culto dos Primeiros Marcados, região de Sucata Enferrujada. | I37: Faro de Sangue | J37: Nunca sofre penalidade de Furtividade contra alvos que sangraram no combate atual. | K37: Rastreia famílias que tentam fugir de vilas marcadas — reporta a localização delas ao culto antes de atacar. É a fonte do "Segredo" no diário do Irmão Lucian. | L37: =IF(C37="Comum",ROUND(E37*1.3,0),"—") | M37: =IF(C37="Comum",ROUND(F37*1.15,0),"—") | N37: =IF(C37="Comum",G37+2,"—") | O37: =IF(C37="Comum",ROUND(E37*1.6,0),"—") | P37: =IF(C37="Comum",ROUND(F37*1.3,0),"—") | Q37: =IF(C37="Comum",G37+4,"—") | R37: As Portas Marcadas (revelação); O Caçador Caçado | S37: =ROUND(INDEX('Curva Mestra'!$D$20:$D$94,MATCH(D37,'Curva Mestra'!$A$20:$A$94,0))-IF(C37="Comum",9,IF(C37="Elite",6,IF(C37="Boss",4,3))),0) | T37: Fragmento de Caçador de Marcas + Ouro + Couro Áspero de Javali (chance baixa) | U37: Perde o bônus de grupo se isolado dos outros cultistas em combate. | V37: DPS | W37: Bosque Sombrio
A38: Sucata Enferrujada | B38: Espectro da Chuva Ferrosa | C38: Elite | D38: 4 | E38: =ROUND(INDEX('Curva Mestra'!$G$20:$G$94,MATCH(D38,'Curva Mestra'!$A$20:$A$94,0)),0) | F38: =ROUND(INDEX('Curva Mestra'!$C$20:$C$94,MATCH(D38,'Curva Mestra'!$A$20:$A$94,0))*INDEX($B$5:$B$8,MATCH(C38,$A$5:$A$8,0)),0) | G38: =ROUND(INDEX('Curva Mestra'!$D$20:$D$94,MATCH(D38,'Curva Mestra'!$A$20:$A$94,0))+INDEX($C$5:$C$8,MATCH(C38,$A$5:$A$8,0)),0) | H38: Só se manifesta quando a chuva cai sobre o ferro marcado da região. | I38: Toque Oxidado | J38: Fragilidade forte (equipamento perde durabilidade 3x mais rápido). | K38: Só se forma quando a chuva passa pelo ferro marcado da região. | L38: =IF(C38="Comum",ROUND(E38*1.3,0),"—") | M38: =IF(C38="Comum",ROUND(F38*1.15,0),"—") | N38: =IF(C38="Comum",G38+2,"—") | O38: =IF(C38="Comum",ROUND(E38*1.6,0),"—") | P38: =IF(C38="Comum",ROUND(F38*1.3,0),"—") | Q38: =IF(C38="Comum",G38+4,"—") | S38: =ROUND(3+0.6*D38+IF(C38="Comum",0,IF(C38="Elite",2,IF(C38="Boss",4,6))),0) | T38: Ouro + Gota de Chuva Cristalizada + Resíduo Espectral Ferroso | U38: Ignora Resistência Mágica | V38: Condicional | W38: Só durante o evento Chuva Ferrosa das Ruínas | Y38: Desaparece sozinho quando a chuva passa.
A39: Sucata Enferrujada | B39: Garr'th, o Primeiro Vira-Casaca | C39: Elite | D39: 5 | E39: =ROUND(INDEX('Curva Mestra'!$G$20:$G$94,MATCH(D39,'Curva Mestra'!$A$20:$A$94,0)),0) | F39: =ROUND(INDEX('Curva Mestra'!$C$20:$C$94,MATCH(D39,'Curva Mestra'!$A$20:$A$94,0))*INDEX($B$5:$B$8,MATCH(C39,$A$5:$A$8,0)),0) | G39: =ROUND(INDEX('Curva Mestra'!$D$20:$D$94,MATCH(D39,'Curva Mestra'!$A$20:$A$94,0))+INDEX($C$5:$C$8,MATCH(C39,$A$5:$A$8,0)),0) | H39: Aparece raramente na Estrada dos Bandidos, sempre sozinho. | I39: Lâmina do Arrependido | J39: Ignora Defesa + Rouba Vida (15%). | K39: Foi da Milícia dos Desamparados. Entregou a própria vila ao Culto em troca da vida da filha. | L39: =IF(C39="Comum",ROUND(E39*1.3,0),"—") | M39: =IF(C39="Comum",ROUND(F39*1.15,0),"—") | N39: =IF(C39="Comum",G39+2,"—") | O39: =IF(C39="Comum",ROUND(E39*1.6,0),"—") | P39: =IF(C39="Comum",ROUND(F39*1.3,0),"—") | Q39: =IF(C39="Comum",G39+4,"—") | S39: =ROUND(3+0.6*D39+IF(C39="Comum",0,IF(C39="Elite",2,IF(C39="Boss",4,6))),0) | T39: Ouro + Fragmento da Lâmina do Arrependido | U39: Ignora Resistência Mágica | V39: Nomeado / Mini-Boss | W39: Estrada dos Bandidos, spawn raro (3%) | X39: A 40% de HP pede pra ser morto — poupá-lo dá Título, matá-lo dá Loot Único. | Z39: Milícia dos Desamparados o caça ativamente: reputação ao derrotá-lo. | AA39: Anel do Traidor Perdoado [ver Artefatos e Relíquias]
A40: Sucata Enferrujada | B40: Javali Selvagem Alfa | C40: Boss | D40: 4 | E40: =ROUND(INDEX('Curva Mestra'!$H$20:$H$94,MATCH(D40,'Curva Mestra'!$A$20:$A$94,0)),0) | F40: =ROUND(INDEX('Curva Mestra'!$C$20:$C$94,MATCH(D40,'Curva Mestra'!$A$20:$A$94,0))*INDEX($B$5:$B$8,MATCH(C40,$A$5:$A$8,0)),0) | G40: =ROUND(INDEX('Curva Mestra'!$D$20:$D$94,MATCH(D40,'Curva Mestra'!$A$20:$A$94,0))+INDEX($C$5:$C$8,MATCH(C40,$A$5:$A$8,0)),0) | H40: Chefe / marco final do tier Sucata Enferrujada | I40: Investida Ensanguentada | J40: Empurra o alvo 2m e causa sangramento por 1 turno. | K40: A primeira fera a nascer já corrompida na região — sua presa quebrada virou o artefato "Anel de Dente do Javali Alfa". | L40: =IF(C40="Comum",ROUND(E40*1.3,0),"—") | M40: =IF(C40="Comum",ROUND(F40*1.15,0),"—") | N40: =IF(C40="Comum",G40+2,"—") | O40: =IF(C40="Comum",ROUND(E40*1.6,0),"—") | P40: =IF(C40="Comum",ROUND(F40*1.3,0),"—") | Q40: =IF(C40="Comum",G40+4,"—") | R40: A Estrada Insegura (item de origem: Anel de Dente do Javali Alfa) | S40: =ROUND(INDEX('Curva Mestra'!$D$20:$D$94,MATCH(D40,'Curva Mestra'!$A$20:$A$94,0))-IF(C40="Comum",9,IF(C40="Elite",6,IF(C40="Boss",4,3))),0) | T40: Presa de Javali Selvagem Alfa + Essência de Javali Selvagem Alfa + Ouro + Couro Áspero de Javali (chance baixa) | U40: Vulnerável a Ignora Defesa — pele grossa, mas com pontos fracos previsíveis. | V40: DPS | W40: Bosque Sombrio | AA40: Anel de Dente do Javali Alfa
A41: Sucata Enferrujada | B41: O Colhedor do Primeiro Sangue | C41: Boss | D41: 5 | E41: =ROUND(INDEX('Curva Mestra'!$H$20:$H$94,MATCH(D41,'Curva Mestra'!$A$20:$A$94,0)),0) | F41: =ROUND(INDEX('Curva Mestra'!$C$20:$C$94,MATCH(D41,'Curva Mestra'!$A$20:$A$94,0))*INDEX($B$5:$B$8,MATCH(C41,$A$5:$A$8,0)),0) | G41: =ROUND(INDEX('Curva Mestra'!$D$20:$D$94,MATCH(D41,'Curva Mestra'!$A$20:$A$94,0))+INDEX($C$5:$C$8,MATCH(C41,$A$5:$A$8,0)),0) | H41: Ligado a Culto dos Primeiros Marcados (líder local), região de Sucata Enferrujada. | I41: Ceifa Ritual | J41: Cura 20% do dano causado como HP para si mesmo. | K41: O cultista que pintou a primeira porta da região. Não é forte por poder próprio — é forte porque acredita que está certo. Guarda o segundo Fragmento do Sangue perdido. | L41: =IF(C41="Comum",ROUND(E41*1.3,0),"—") | M41: =IF(C41="Comum",ROUND(F41*1.15,0),"—") | N41: =IF(C41="Comum",G41+2,"—") | O41: =IF(C41="Comum",ROUND(E41*1.6,0),"—") | P41: =IF(C41="Comum",ROUND(F41*1.3,0),"—") | Q41: =IF(C41="Comum",G41+4,"—") | R41: O Colhedor do Primeiro Sangue (boss opcional, fecha o Tier) | S41: =ROUND(INDEX('Curva Mestra'!$D$20:$D$94,MATCH(D41,'Curva Mestra'!$A$20:$A$94,0))-IF(C41="Comum",9,IF(C41="Elite",6,IF(C41="Boss",4,3))),0) | T41: Amostra de Carne de O Colhedor do Primeiro Sangue + Essência de O Colhedor do Primeiro Sangue + Ouro + Couro Áspero de Javali (chance baixa) | U41: Perde o bônus de grupo se isolado dos outros cultistas em combate. | V41: Suporte | W41: Bosque Sombrio
A42: Bronze | B42: Cão de Mina Cego | C42: Comum | D42: 3 | E42: =ROUND(INDEX('Curva Mestra'!$F$20:$F$94,MATCH(D42,'Curva Mestra'!$A$20:$A$94,0)),0) | F42: =ROUND(INDEX('Curva Mestra'!$C$20:$C$94,MATCH(D42,'Curva Mestra'!$A$20:$A$94,0))*INDEX($B$5:$B$8,MATCH(C42,$A$5:$A$8,0)),0) | G42: =ROUND(INDEX('Curva Mestra'!$D$20:$D$94,MATCH(D42,'Curva Mestra'!$A$20:$A$94,0))+INDEX($C$5:$C$8,MATCH(C42,$A$5:$A$8,0)),0) | H42: Perambula pelos corredores da Mina de Bronze havia anos. | I42: (não ataca) | J42: Não-hostil: segue luz. Se poupado, guia até um ponto de coleta melhor (Qualidade Boa garantida). | K42: Ficou cego respirando gás há anos. Confia em quem carrega tocha. | L42: =IF(C42="Comum",ROUND(E42*1.3,0),"—") | M42: =IF(C42="Comum",ROUND(F42*1.15,0),"—") | N42: =IF(C42="Comum",G42+2,"—") | O42: =IF(C42="Comum",ROUND(E42*1.6,0),"—") | P42: =IF(C42="Comum",ROUND(F42*1.3,0),"—") | Q42: =IF(C42="Comum",G42+4,"—") | S42: =ROUND(3+0.6*D42+IF(C42="Comum",0,IF(C42="Elite",2,IF(C42="Boss",4,6))),0) | T42: Ouro + Pelo Embotado de Cão de Mina Cego + Faro Apurado de Cão de Mina Cego | U42: Sem fraqueza óbvia — precisa de Knowledge alto pra descobrir algo específico. | V42: Não-hostil | W42: Mina de Bronze | Y42: Segue o jogador em 1 exploração se poupado.
A43: Bronze | B43: Coletor Enferrujado da Mão | C43: Comum | D43: 4 | E43: =ROUND(INDEX('Curva Mestra'!$F$20:$F$94,MATCH(D43,'Curva Mestra'!$A$20:$A$94,0)),0) | F43: =ROUND(INDEX('Curva Mestra'!$C$20:$C$94,MATCH(D43,'Curva Mestra'!$A$20:$A$94,0))*INDEX($B$5:$B$8,MATCH(C43,$A$5:$A$8,0)),0) | G43: =ROUND(INDEX('Curva Mestra'!$D$20:$D$94,MATCH(D43,'Curva Mestra'!$A$20:$A$94,0))+INDEX($C$5:$C$8,MATCH(C43,$A$5:$A$8,0)),0) | H43: Ronda a regiao do tier Bronze | I43: Golpe de Sucata | J43: Sem efeito especial — ataque cru de metal retorcido. | K43: Coleta minério pra vender ao Barão Grimm mesmo sabendo que os túneis "sussurram" — o vício em ganhar a próxima moeda já é uma forma leve de infecção. | L43: =IF(C43="Comum",ROUND(E43*1.3,0),"—") | M43: =IF(C43="Comum",ROUND(F43*1.15,0),"—") | N43: =IF(C43="Comum",G43+2,"—") | O43: =IF(C43="Comum",ROUND(E43*1.6,0),"—") | P43: =IF(C43="Comum",ROUND(F43*1.3,0),"—") | Q43: =IF(C43="Comum",G43+4,"—") | R43: A Mina Sufocada | S43: =ROUND(INDEX('Curva Mestra'!$D$20:$D$94,MATCH(D43,'Curva Mestra'!$A$20:$A$94,0))-IF(C43="Comum",9,IF(C43="Elite",6,IF(C43="Boss",4,3))),0) | T43: Ouro + Saco de Minério Roubado + Picareta Cega do Coletor | U43: Sem fraqueza óbvia — precisa de Knowledge alto pra descobrir algo específico. | V43: DPS | W43: Mina de Bronze
A44: Bronze | B44: Mineiro Exausto | C44: Comum | D44: 4 | E44: =ROUND(INDEX('Curva Mestra'!$F$20:$F$94,MATCH(D44,'Curva Mestra'!$A$20:$A$94,0)),0) | F44: =ROUND(INDEX('Curva Mestra'!$C$20:$C$94,MATCH(D44,'Curva Mestra'!$A$20:$A$94,0))*INDEX($B$5:$B$8,MATCH(C44,$A$5:$A$8,0)),0) | G44: =ROUND(INDEX('Curva Mestra'!$D$20:$D$94,MATCH(D44,'Curva Mestra'!$A$20:$A$94,0))+INDEX($C$5:$C$8,MATCH(C44,$A$5:$A$8,0)),0) | H44: Trabalha nas galerias principais da Mina de Bronze desde antes da marca. | I44: Picareta Fraca | J44: Nenhum efeito — 20% de chance de simplesmente desistir de lutar. | K44: Trabalha desde antes da marca aparecer. Não tem mais forças. | L44: =IF(C44="Comum",ROUND(E44*1.3,0),"—") | M44: =IF(C44="Comum",ROUND(F44*1.15,0),"—") | N44: =IF(C44="Comum",G44+2,"—") | O44: =IF(C44="Comum",ROUND(E44*1.6,0),"—") | P44: =IF(C44="Comum",ROUND(F44*1.3,0),"—") | Q44: =IF(C44="Comum",G44+4,"—") | S44: =ROUND(3+0.6*D44+IF(C44="Comum",0,IF(C44="Elite",2,IF(C44="Boss",4,6))),0) | T44: Ouro + Lanterna Encardida de Mineiro Exausto + Luva Rasgada de Mineiro Exausto | U44: Atordoamento | V44: Não-hostil condicional | W44: Mina de Bronze — Galeria Principal | Y44: Se abordado sem arma sacada, não ataca — pode ser convencido a fugir da mina (quest). | Z44: A Guilda dos Picaretas Negros pune quem ajuda mineiros a fugir.
A45: Bronze | B45: Aranha Recém-Nascida | C45: Comum | D45: 4 | E45: =ROUND(INDEX('Curva Mestra'!$F$20:$F$94,MATCH(D45,'Curva Mestra'!$A$20:$A$94,0)),0) | F45: =ROUND(INDEX('Curva Mestra'!$C$20:$C$94,MATCH(D45,'Curva Mestra'!$A$20:$A$94,0))*INDEX($B$5:$B$8,MATCH(C45,$A$5:$A$8,0)),0) | G45: =ROUND(INDEX('Curva Mestra'!$D$20:$D$94,MATCH(D45,'Curva Mestra'!$A$20:$A$94,0))+INDEX($C$5:$C$8,MATCH(C45,$A$5:$A$8,0)),0) | H45: Ninhada nova encontrada nas galerias principais da mina. | I45: Picada Fraca | J45: Nenhum — sempre em grupo de 3-4. | K45: Ninhada nova da Matriarca. | L45: =IF(C45="Comum",ROUND(E45*1.3,0),"—") | M45: =IF(C45="Comum",ROUND(F45*1.15,0),"—") | N45: =IF(C45="Comum",G45+2,"—") | O45: =IF(C45="Comum",ROUND(E45*1.6,0),"—") | P45: =IF(C45="Comum",ROUND(F45*1.3,0),"—") | Q45: =IF(C45="Comum",G45+4,"—") | S45: =ROUND(3+0.6*D45+IF(C45="Comum",0,IF(C45="Elite",2,IF(C45="Boss",4,6))),0) | T45: Ouro + Fio de Teia Fresca | U45: Queimadura | V45: Enxame | W45: Mina de Bronze — Galeria Principal | Y45: Chamam a Matriarca se todas morrerem (8%).
A46: Bronze | B46: Aranha Operária | C46: Comum | D46: 5 | E46: =ROUND(INDEX('Curva Mestra'!$F$20:$F$94,MATCH(D46,'Curva Mestra'!$A$20:$A$94,0)),0) | F46: =ROUND(INDEX('Curva Mestra'!$C$20:$C$94,MATCH(D46,'Curva Mestra'!$A$20:$A$94,0))*INDEX($B$5:$B$8,MATCH(C46,$A$5:$A$8,0)),0) | G46: =ROUND(INDEX('Curva Mestra'!$D$20:$D$94,MATCH(D46,'Curva Mestra'!$A$20:$A$94,0))+INDEX($C$5:$C$8,MATCH(C46,$A$5:$A$8,0)),0) | H46: Tece teias pelas galerias abandonadas da Mina de Bronze. | I46: Fiar Teia | J46: Cria uma Teia no local: -15% de chance de Fuga enquanto ativa. | K46: Tece as galerias abandonadas da mina, prende quem tenta correr. | L46: =IF(C46="Comum",ROUND(E46*1.3,0),"—") | M46: =IF(C46="Comum",ROUND(F46*1.15,0),"—") | N46: =IF(C46="Comum",G46+2,"—") | O46: =IF(C46="Comum",ROUND(E46*1.6,0),"—") | P46: =IF(C46="Comum",ROUND(F46*1.3,0),"—") | Q46: =IF(C46="Comum",G46+4,"—") | S46: =ROUND(3+0.6*D46+IF(C46="Comum",0,IF(C46="Elite",2,IF(C46="Boss",4,6))),0) | T46: Ouro + Fio de Teia Grossa + Glândula de Seda da Operária | U46: Queimadura | V46: Controle/Obstáculo | W46: Mina de Bronze — Galeria Principal | Y46: A teia permanece 3 turnos mesmo se ela morrer.
A47: Bronze | B47: Nuvem de Gás Sulfuroso | C47: Comum | D47: 5 | E47: =ROUND(INDEX('Curva Mestra'!$F$20:$F$94,MATCH(D47,'Curva Mestra'!$A$20:$A$94,0)),0) | F47: =ROUND(INDEX('Curva Mestra'!$C$20:$C$94,MATCH(D47,'Curva Mestra'!$A$20:$A$94,0))*INDEX($B$5:$B$8,MATCH(C47,$A$5:$A$8,0)),0) | G47: =ROUND(INDEX('Curva Mestra'!$D$20:$D$94,MATCH(D47,'Curva Mestra'!$A$20:$A$94,0))+INDEX($C$5:$C$8,MATCH(C47,$A$5:$A$8,0)),0) | H47: Acumulada nos túneis fechados e mal ventilados da mina. | I47: Explosão de Gás | J47: 3 de dano em área ao ser tocada — não persegue, fica parada. | K47: Bolsa de gás que se acumulou nos túneis mal ventilados. | L47: =IF(C47="Comum",ROUND(E47*1.3,0),"—") | M47: =IF(C47="Comum",ROUND(F47*1.15,0),"—") | N47: =IF(C47="Comum",G47+2,"—") | O47: =IF(C47="Comum",ROUND(E47*1.6,0),"—") | P47: =IF(C47="Comum",ROUND(F47*1.3,0),"—") | Q47: =IF(C47="Comum",G47+4,"—") | S47: =ROUND(3+0.6*D47+IF(C47="Comum",0,IF(C47="Elite",2,IF(C47="Boss",4,6))),0) | T47: Frasco de Gás Sulfuroso Condensado + Resíduo Amarelado da Nuvem | U47: Ignora Defesa | V47: Condicional/Explosivo | W47: Mina de Bronze — Túneis Baixos, só em área fechada | Y47: Some sozinha depois de detonar uma vez.
A48: Bronze | B48: Verme Perfurador | C48: Comum | D48: 5 | E48: =ROUND(INDEX('Curva Mestra'!$F$20:$F$94,MATCH(D48,'Curva Mestra'!$A$20:$A$94,0)),0) | F48: =ROUND(INDEX('Curva Mestra'!$C$20:$C$94,MATCH(D48,'Curva Mestra'!$A$20:$A$94,0))*INDEX($B$5:$B$8,MATCH(C48,$A$5:$A$8,0)),0) | G48: =ROUND(INDEX('Curva Mestra'!$D$20:$D$94,MATCH(D48,'Curva Mestra'!$A$20:$A$94,0))+INDEX($C$5:$C$8,MATCH(C48,$A$5:$A$8,0)),0) | H48: Cava através da rocha mole dos túneis baixos da mina. | I48: Investida Subterrânea | J48: Ignora Defesa (perfura por baixo). | K48: Cava através da rocha mole — some e reaparece de outro ângulo. | L48: =IF(C48="Comum",ROUND(E48*1.3,0),"—") | M48: =IF(C48="Comum",ROUND(F48*1.15,0),"—") | N48: =IF(C48="Comum",G48+2,"—") | O48: =IF(C48="Comum",ROUND(E48*1.6,0),"—") | P48: =IF(C48="Comum",ROUND(F48*1.3,0),"—") | Q48: =IF(C48="Comum",G48+4,"—") | S48: =ROUND(3+0.6*D48+IF(C48="Comum",0,IF(C48="Elite",2,IF(C48="Boss",4,6))),0) | T48: Ouro + Mandíbula do Verme Perfurador + Segmento Escamoso de Verme | U48: Fragilidade | V48: Assassino | W48: Mina de Bronze — Túneis Baixos | Y48: Pode sumir e reaparecer em outro ponto do combate.
A49: Bronze | B49: Escravo da Rocha | C49: Comum | D49: 5 | E49: =ROUND(INDEX('Curva Mestra'!$F$20:$F$94,MATCH(D49,'Curva Mestra'!$A$20:$A$94,0)),0) | F49: =ROUND(INDEX('Curva Mestra'!$C$20:$C$94,MATCH(D49,'Curva Mestra'!$A$20:$A$94,0))*INDEX($B$5:$B$8,MATCH(C49,$A$5:$A$8,0)),0) | G49: =ROUND(INDEX('Curva Mestra'!$D$20:$D$94,MATCH(D49,'Curva Mestra'!$A$20:$A$94,0))+INDEX($C$5:$C$8,MATCH(C49,$A$5:$A$8,0)),0) | H49: Forçado a trabalhar nos túneis mais baixos da mina. | I49: Golpe de Corrente | J49: Nenhum — luta só porque é forçado, sem convicção. | K49: Prisioneiro que a Guilda comprou pra trabalho forçado. | L49: =IF(C49="Comum",ROUND(E49*1.3,0),"—") | M49: =IF(C49="Comum",ROUND(F49*1.15,0),"—") | N49: =IF(C49="Comum",G49+2,"—") | O49: =IF(C49="Comum",ROUND(E49*1.6,0),"—") | P49: =IF(C49="Comum",ROUND(F49*1.3,0),"—") | Q49: =IF(C49="Comum",G49+4,"—") | S49: =ROUND(3+0.6*D49+IF(C49="Comum",0,IF(C49="Elite",2,IF(C49="Boss",4,6))),0) | T49: Ouro + Corrente Enferrujada de Escravo da Rocha + Pano de Trabalho Forçado | U49: Atordoamento | V49: DPS fraco | W49: Mina de Bronze — Túneis Baixos | Y49: Se poupado, pode ser libertado (afeta reputação com Milícia dos Desamparados). | Z49: A Milícia dos Desamparados recompensa quem liberta escravos da Guilda.
A50: Bronze | B50: Aranha Tecelã Menor | C50: Comum | D50: 5 | E50: =ROUND(INDEX('Curva Mestra'!$F$20:$F$94,MATCH(D50,'Curva Mestra'!$A$20:$A$94,0)),0) | F50: =ROUND(INDEX('Curva Mestra'!$C$20:$C$94,MATCH(D50,'Curva Mestra'!$A$20:$A$94,0))*INDEX($B$5:$B$8,MATCH(C50,$A$5:$A$8,0)),0) | G50: =ROUND(INDEX('Curva Mestra'!$D$20:$D$94,MATCH(D50,'Curva Mestra'!$A$20:$A$94,0))+INDEX($C$5:$C$8,MATCH(C50,$A$5:$A$8,0)),0) | H50: Aranha jovem das galerias de entrada. | I50: Fio Fraco | J50: Nenhum — cria pequenas teias que atrasam fuga (-10%). | K50: Tece nas entradas dos túneis, mais fraca que a Operária. | L50: =IF(C50="Comum",ROUND(E50*1.3,0),"—") | M50: =IF(C50="Comum",ROUND(F50*1.15,0),"—") | N50: =IF(C50="Comum",G50+2,"—") | O50: =IF(C50="Comum",ROUND(E50*1.6,0),"—") | P50: =IF(C50="Comum",ROUND(F50*1.3,0),"—") | Q50: =IF(C50="Comum",G50+4,"—") | S50: =ROUND(3+0.6*D50+IF(C50="Comum",0,IF(C50="Elite",2,IF(C50="Boss",4,6))),0) | T50: Ouro + Fio de Teia Fina | U50: Queimadura | V50: Controle | W50: Mina de Bronze — Entrada
A51: Bronze | B51: Poeira Viva de Minério | C51: Comum | D51: 5 | E51: =ROUND(INDEX('Curva Mestra'!$F$20:$F$94,MATCH(D51,'Curva Mestra'!$A$20:$A$94,0)),0) | F51: =ROUND(INDEX('Curva Mestra'!$C$20:$C$94,MATCH(D51,'Curva Mestra'!$A$20:$A$94,0))*INDEX($B$5:$B$8,MATCH(C51,$A$5:$A$8,0)),0) | G51: =ROUND(INDEX('Curva Mestra'!$D$20:$D$94,MATCH(D51,'Curva Mestra'!$A$20:$A$94,0))+INDEX($C$5:$C$8,MATCH(C51,$A$5:$A$8,0)),0) | H51: Nuvem de poeira mineral corrompida. | I51: Sufocar | J51: Atordoamento (20%) — só ativo em túnel fechado. | K51: Poeira de anos de mineração que ganhou consciência própria. | L51: =IF(C51="Comum",ROUND(E51*1.3,0),"—") | M51: =IF(C51="Comum",ROUND(F51*1.15,0),"—") | N51: =IF(C51="Comum",G51+2,"—") | O51: =IF(C51="Comum",ROUND(E51*1.6,0),"—") | P51: =IF(C51="Comum",ROUND(F51*1.3,0),"—") | Q51: =IF(C51="Comum",G51+4,"—") | S51: =ROUND(3+0.6*D51+IF(C51="Comum",0,IF(C51="Elite",2,IF(C51="Boss",4,6))),0) | T51: Punhado de Poeira Viva + Cristal de Minério Consciente | U51: Ignora Resistência Mágica | V51: Condicional | W51: Mina de Bronze — Túneis Baixos, só em area fechada
A52: Bronze | B52: Segunda Aranha Recém-Nascida | C52: Comum | D52: 5 | E52: =ROUND(INDEX('Curva Mestra'!$F$20:$F$94,MATCH(D52,'Curva Mestra'!$A$20:$A$94,0)),0) | F52: =ROUND(INDEX('Curva Mestra'!$C$20:$C$94,MATCH(D52,'Curva Mestra'!$A$20:$A$94,0))*INDEX($B$5:$B$8,MATCH(C52,$A$5:$A$8,0)),0) | G52: =ROUND(INDEX('Curva Mestra'!$D$20:$D$94,MATCH(D52,'Curva Mestra'!$A$20:$A$94,0))+INDEX($C$5:$C$8,MATCH(C52,$A$5:$A$8,0)),0) | H52: Ninhada mais nova da Matriarca. | I52: Picada Fraca | J52: Nenhum — sempre em grupo com a Aranha Recém-Nascida original. | K52: Segunda ninhada da Matriarca, nasceu semanas depois. | L52: =IF(C52="Comum",ROUND(E52*1.3,0),"—") | M52: =IF(C52="Comum",ROUND(F52*1.15,0),"—") | N52: =IF(C52="Comum",G52+2,"—") | O52: =IF(C52="Comum",ROUND(E52*1.6,0),"—") | P52: =IF(C52="Comum",ROUND(F52*1.3,0),"—") | Q52: =IF(C52="Comum",G52+4,"—") | S52: =ROUND(3+0.6*D52+IF(C52="Comum",0,IF(C52="Elite",2,IF(C52="Boss",4,6))),0) | T52: Ouro + Fio de Teia Fresca | U52: Queimadura | V52: Enxame | W52: Mina de Bronze — Galeria Principal
A53: Bronze | B53: Aranha da Mina | C53: Comum | D53: 6 | E53: =ROUND(INDEX('Curva Mestra'!$F$20:$F$94,MATCH(D53,'Curva Mestra'!$A$20:$A$94,0)),0) | F53: =ROUND(INDEX('Curva Mestra'!$C$20:$C$94,MATCH(D53,'Curva Mestra'!$A$20:$A$94,0))*INDEX($B$5:$B$8,MATCH(C53,$A$5:$A$8,0)),0) | G53: =ROUND(INDEX('Curva Mestra'!$D$20:$D$94,MATCH(D53,'Curva Mestra'!$A$20:$A$94,0))+INDEX($C$5:$C$8,MATCH(C53,$A$5:$A$8,0)),0) | H53: Ronda a regiao do tier Bronze | I53: Teia Pegajosa | J53: Reduz a velocidade de fuga do alvo em 1 turno. | K53: Nativa das galerias, cresceu maior depois que os vapores do minério de bronze contaminado baixaram pelos túneis. | L53: =IF(C53="Comum",ROUND(E53*1.3,0),"—") | M53: =IF(C53="Comum",ROUND(F53*1.15,0),"—") | N53: =IF(C53="Comum",G53+2,"—") | O53: =IF(C53="Comum",ROUND(E53*1.6,0),"—") | P53: =IF(C53="Comum",ROUND(F53*1.3,0),"—") | Q53: =IF(C53="Comum",G53+4,"—") | R53: A Mina Sufocada; O Ninho Que Não Devia Crescer | S53: =ROUND(INDEX('Curva Mestra'!$D$20:$D$94,MATCH(D53,'Curva Mestra'!$A$20:$A$94,0))-IF(C53="Comum",9,IF(C53="Elite",6,IF(C53="Boss",4,3))),0) | T53: Ouro + Presa de Aranha da Mina + Quitina de Aranha das Cavernas (chance rara) | U53: Vulnerável a Atordoamento — travas mecânicas emperram com o dobro de chance. | V53: DPS | W53: Mina de Bronze
A54: Bronze | B54: Verme Sulfuroso | C54: Comum | D54: 6 | E54: =ROUND(INDEX('Curva Mestra'!$F$20:$F$94,MATCH(D54,'Curva Mestra'!$A$20:$A$94,0)),0) | F54: =ROUND(INDEX('Curva Mestra'!$C$20:$C$94,MATCH(D54,'Curva Mestra'!$A$20:$A$94,0))*INDEX($B$5:$B$8,MATCH(C54,$A$5:$A$8,0)),0) | G54: =ROUND(INDEX('Curva Mestra'!$D$20:$D$94,MATCH(D54,'Curva Mestra'!$A$20:$A$94,0))+INDEX($C$5:$C$8,MATCH(C54,$A$5:$A$8,0)),0) | H54: Ligado à Guilda dos Picaretas Negros, região de Bronze. | I54: Golpe Corrosivo | J54: Reduz a Defesa do alvo em 1 até o fim do combate (ácido). | K54: Criatura de túnel atraída pelos vapores sulfurosos do minério — corrói os suportes de madeira da mina, acelerando desabamentos que Grimm finge não notar. | L54: =IF(C54="Comum",ROUND(E54*1.3,0),"—") | M54: =IF(C54="Comum",ROUND(F54*1.15,0),"—") | N54: =IF(C54="Comum",G54+2,"—") | O54: =IF(C54="Comum",ROUND(E54*1.6,0),"—") | P54: =IF(C54="Comum",ROUND(F54*1.3,0),"—") | Q54: =IF(C54="Comum",G54+4,"—") | R54: Vermes na Rocha | S54: =ROUND(INDEX('Curva Mestra'!$D$20:$D$94,MATCH(D54,'Curva Mestra'!$A$20:$A$94,0))-IF(C54="Comum",9,IF(C54="Elite",6,IF(C54="Boss",4,3))),0) | T54: Ouro + Baba Sulfurosa de Verme + Quitina de Aranha das Cavernas (chance rara) | U54: Vulnerável a Atordoamento — travas mecânicas emperram com o dobro de chance. | V54: DPS | W54: Mina de Bronze
A55: Bronze | B55: Aranha Pútrida | C55: Comum | D55: 6 | E55: =ROUND(INDEX('Curva Mestra'!$F$20:$F$94,MATCH(D55,'Curva Mestra'!$A$20:$A$94,0)),0) | F55: =ROUND(INDEX('Curva Mestra'!$C$20:$C$94,MATCH(D55,'Curva Mestra'!$A$20:$A$94,0))*INDEX($B$5:$B$8,MATCH(C55,$A$5:$A$8,0)),0) | G55: =ROUND(INDEX('Curva Mestra'!$D$20:$D$94,MATCH(D55,'Curva Mestra'!$A$20:$A$94,0))+INDEX($C$5:$C$8,MATCH(C55,$A$5:$A$8,0)),0) | H55: Vive nos túneis mais fundos e mal ventilados da Mina de Bronze. | I55: Cuspe Corrosivo | J55: Veneno (1/turno, 2 turnos). | K55: Comeu carne infectada demais — o próprio veneno virou parte dela. | L55: =IF(C55="Comum",ROUND(E55*1.3,0),"—") | M55: =IF(C55="Comum",ROUND(F55*1.15,0),"—") | N55: =IF(C55="Comum",G55+2,"—") | O55: =IF(C55="Comum",ROUND(E55*1.6,0),"—") | P55: =IF(C55="Comum",ROUND(F55*1.3,0),"—") | Q55: =IF(C55="Comum",G55+4,"—") | S55: =ROUND(3+0.6*D55+IF(C55="Comum",0,IF(C55="Elite",2,IF(C55="Boss",4,6))),0) | T55: Ouro + Veneno Coagulado de Aranha Pútrida | U55: Queimadura | V55: Debuffer | W55: Mina de Bronze — Túneis Baixos
A56: Bronze | B56: Verme Carniceiro | C56: Comum | D56: 6 | E56: =ROUND(INDEX('Curva Mestra'!$F$20:$F$94,MATCH(D56,'Curva Mestra'!$A$20:$A$94,0)),0) | F56: =ROUND(INDEX('Curva Mestra'!$C$20:$C$94,MATCH(D56,'Curva Mestra'!$A$20:$A$94,0))*INDEX($B$5:$B$8,MATCH(C56,$A$5:$A$8,0)),0) | G56: =ROUND(INDEX('Curva Mestra'!$D$20:$D$94,MATCH(D56,'Curva Mestra'!$A$20:$A$94,0))+INDEX($C$5:$C$8,MATCH(C56,$A$5:$A$8,0)),0) | H56: Aparece em qualquer túnel onde um combate já aconteceu. | I56: Mordida Necrófaga | J56: Cura-se 5 HP se houver cadáver no local (combate vencido ali antes). | K56: Come o que sobra dos que não sobreviveram à mina. | L56: =IF(C56="Comum",ROUND(E56*1.3,0),"—") | M56: =IF(C56="Comum",ROUND(F56*1.15,0),"—") | N56: =IF(C56="Comum",G56+2,"—") | O56: =IF(C56="Comum",ROUND(E56*1.6,0),"—") | P56: =IF(C56="Comum",ROUND(F56*1.3,0),"—") | Q56: =IF(C56="Comum",G56+4,"—") | S56: =ROUND(3+0.6*D56+IF(C56="Comum",0,IF(C56="Elite",2,IF(C56="Boss",4,6))),0) | T56: Ouro + Presa Necrófaga de Verme Carniceiro | U56: Queimadura | V56: Necrófago | W56: Mina de Bronze, qualquer túnel após combate vencido
A57: Bronze | B57: Carrasco da Cota | C57: Comum | D57: 6 | E57: =ROUND(INDEX('Curva Mestra'!$F$20:$F$94,MATCH(D57,'Curva Mestra'!$A$20:$A$94,0)),0) | F57: =ROUND(INDEX('Curva Mestra'!$C$20:$C$94,MATCH(D57,'Curva Mestra'!$A$20:$A$94,0))*INDEX($B$5:$B$8,MATCH(C57,$A$5:$A$8,0)),0) | G57: =ROUND(INDEX('Curva Mestra'!$D$20:$D$94,MATCH(D57,'Curva Mestra'!$A$20:$A$94,0))+INDEX($C$5:$C$8,MATCH(C57,$A$5:$A$8,0)),0) | H57: Trabalha no escritório do capataz, punindo quem não rende o suficiente. | I57: Chicote de Corda | J57: Sangramento. | K57: Capataz menor que pune quem não bate a cota do dia. | L57: =IF(C57="Comum",ROUND(E57*1.3,0),"—") | M57: =IF(C57="Comum",ROUND(F57*1.15,0),"—") | N57: =IF(C57="Comum",G57+2,"—") | O57: =IF(C57="Comum",ROUND(E57*1.6,0),"—") | P57: =IF(C57="Comum",ROUND(F57*1.3,0),"—") | Q57: =IF(C57="Comum",G57+4,"—") | S57: =ROUND(3+0.6*D57+IF(C57="Comum",0,IF(C57="Elite",2,IF(C57="Boss",4,6))),0) | T57: Ouro + Chicote Encardido do Carrasco da Cota + Insígnia da Cota | U57: Ignora Defesa | V57: DPS | W57: Mina de Bronze — Escritório do Capataz | Z57: A Guilda dos Picaretas Negros o via como investimento, não gente.
A58: Bronze | B58: Picareta Selvagem | C58: Comum | D58: 6 | E58: =ROUND(INDEX('Curva Mestra'!$F$20:$F$94,MATCH(D58,'Curva Mestra'!$A$20:$A$94,0)),0) | F58: =ROUND(INDEX('Curva Mestra'!$C$20:$C$94,MATCH(D58,'Curva Mestra'!$A$20:$A$94,0))*INDEX($B$5:$B$8,MATCH(C58,$A$5:$A$8,0)),0) | G58: =ROUND(INDEX('Curva Mestra'!$D$20:$D$94,MATCH(D58,'Curva Mestra'!$A$20:$A$94,0))+INDEX($C$5:$C$8,MATCH(C58,$A$5:$A$8,0)),0) | H58: Objeto animado pela corrupção da mina. | I58: Golpe de Ferramenta | J58: Nenhum efeito adicional. | K58: Ferramenta abandonada que a Infecção fez se mover sozinha. | L58: =IF(C58="Comum",ROUND(E58*1.3,0),"—") | M58: =IF(C58="Comum",ROUND(F58*1.15,0),"—") | N58: =IF(C58="Comum",G58+2,"—") | O58: =IF(C58="Comum",ROUND(E58*1.6,0),"—") | P58: =IF(C58="Comum",ROUND(F58*1.3,0),"—") | Q58: =IF(C58="Comum",G58+4,"—") | S58: =ROUND(3+0.6*D58+IF(C58="Comum",0,IF(C58="Elite",2,IF(C58="Boss",4,6))),0) | T58: Ouro + Cabo Animado de Picareta Selvagem + Lâmina Corroída de Picareta Selvagem | U58: Fragilidade | V58: DPS | W58: Mina de Bronze — Galeria Principal
A59: Bronze | B59: Guilda-Batedor | C59: Comum | D59: 6 | E59: =ROUND(INDEX('Curva Mestra'!$F$20:$F$94,MATCH(D59,'Curva Mestra'!$A$20:$A$94,0)),0) | F59: =ROUND(INDEX('Curva Mestra'!$C$20:$C$94,MATCH(D59,'Curva Mestra'!$A$20:$A$94,0))*INDEX($B$5:$B$8,MATCH(C59,$A$5:$A$8,0)),0) | G59: =ROUND(INDEX('Curva Mestra'!$D$20:$D$94,MATCH(D59,'Curva Mestra'!$A$20:$A$94,0))+INDEX($C$5:$C$8,MATCH(C59,$A$5:$A$8,0)),0) | H59: Cobrador violento da Guilda. | I59: Corte de Cobrador | J59: Rouba 5% do Ouro do jogador se acertar. | K59: Cobrador da Guilda dos Picaretas Negros, cobra imposto até de quem não deve. | L59: =IF(C59="Comum",ROUND(E59*1.3,0),"—") | M59: =IF(C59="Comum",ROUND(F59*1.15,0),"—") | N59: =IF(C59="Comum",G59+2,"—") | O59: =IF(C59="Comum",ROUND(E59*1.6,0),"—") | P59: =IF(C59="Comum",ROUND(F59*1.3,0),"—") | Q59: =IF(C59="Comum",G59+4,"—") | S59: =ROUND(3+0.6*D59+IF(C59="Comum",0,IF(C59="Elite",2,IF(C59="Boss",4,6))),0) | T59: Ouro + Bolsa de Imposto da Guilda + Adaga Curta de Cobrador | U59: Lentidão | V59: Ladrão | W59: Mina de Bronze — Galeria Principal | Z59: A Guilda dos Picaretas Negros o paga por resultado, não por método.
A60: Bronze | B60: Cão de Guarda da Guilda | C60: Comum | D60: 6 | E60: =ROUND(INDEX('Curva Mestra'!$F$20:$F$94,MATCH(D60,'Curva Mestra'!$A$20:$A$94,0)),0) | F60: =ROUND(INDEX('Curva Mestra'!$C$20:$C$94,MATCH(D60,'Curva Mestra'!$A$20:$A$94,0))*INDEX($B$5:$B$8,MATCH(C60,$A$5:$A$8,0)),0) | G60: =ROUND(INDEX('Curva Mestra'!$D$20:$D$94,MATCH(D60,'Curva Mestra'!$A$20:$A$94,0))+INDEX($C$5:$C$8,MATCH(C60,$A$5:$A$8,0)),0) | H60: Cão de guarda oficial da Guilda dos Picaretas Negros. | I60: Mordida Territorial | J60: Nenhum efeito adicional. | K60: Treinado pela Guilda pra vigiar os veios mais ricos. | L60: =IF(C60="Comum",ROUND(E60*1.3,0),"—") | M60: =IF(C60="Comum",ROUND(F60*1.15,0),"—") | N60: =IF(C60="Comum",G60+2,"—") | O60: =IF(C60="Comum",ROUND(E60*1.6,0),"—") | P60: =IF(C60="Comum",ROUND(F60*1.3,0),"—") | Q60: =IF(C60="Comum",G60+4,"—") | S60: =ROUND(3+0.6*D60+IF(C60="Comum",0,IF(C60="Elite",2,IF(C60="Boss",4,6))),0) | T60: Ouro + Coleira da Guilda dos Picaretas Negros + Presa de Cão de Guarda da Guilda | U60: Atordoamento | V60: DPS | W60: Mina de Bronze — Veio Rico
A61: Bronze | B61: Aranha Caçadora | C61: Comum | D61: 7 | E61: =ROUND(INDEX('Curva Mestra'!$F$20:$F$94,MATCH(D61,'Curva Mestra'!$A$20:$A$94,0)),0) | F61: =ROUND(INDEX('Curva Mestra'!$C$20:$C$94,MATCH(D61,'Curva Mestra'!$A$20:$A$94,0))*INDEX($B$5:$B$8,MATCH(C61,$A$5:$A$8,0)),0) | G61: =ROUND(INDEX('Curva Mestra'!$D$20:$D$94,MATCH(D61,'Curva Mestra'!$A$20:$A$94,0))+INDEX($C$5:$C$8,MATCH(C61,$A$5:$A$8,0)),0) | H61: Espreita nas mesmas galerias onde a Aranha Operária tece. | I61: Salto Certeiro | J61: +15% de chance de acerto se a Aranha Operária estiver viva no mesmo combate. | K61: Espera a presa ficar presa na teia da Operária pra atacar. | L61: =IF(C61="Comum",ROUND(E61*1.3,0),"—") | M61: =IF(C61="Comum",ROUND(F61*1.15,0),"—") | N61: =IF(C61="Comum",G61+2,"—") | O61: =IF(C61="Comum",ROUND(E61*1.6,0),"—") | P61: =IF(C61="Comum",ROUND(F61*1.3,0),"—") | Q61: =IF(C61="Comum",G61+4,"—") | S61: =ROUND(3+0.6*D61+IF(C61="Comum",0,IF(C61="Elite",2,IF(C61="Boss",4,6))),0) | T61: Ouro + Garra Silenciosa de Aranha Caçadora | U61: Ignora Defesa | V61: DPS/Emboscada | W61: Mina de Bronze — Galeria Principal
A62: Bronze | B62: Mineiro Grimm | C62: Comum | D62: 8 | E62: =ROUND(INDEX('Curva Mestra'!$F$20:$F$94,MATCH(D62,'Curva Mestra'!$A$20:$A$94,0)),0) | F62: =ROUND(INDEX('Curva Mestra'!$C$20:$C$94,MATCH(D62,'Curva Mestra'!$A$20:$A$94,0))*INDEX($B$5:$B$8,MATCH(C62,$A$5:$A$8,0)),0) | G62: =ROUND(INDEX('Curva Mestra'!$D$20:$D$94,MATCH(D62,'Curva Mestra'!$A$20:$A$94,0))+INDEX($C$5:$C$8,MATCH(C62,$A$5:$A$8,0)),0) | H62: Ligado à Guilda dos Picaretas Negros, região de Bronze. | I62: Picareta Desesperada | J62: Sem efeito especial — luta por medo de perder a única renda que tem. | K62: Trabalhador endividado com o Barão Grimm, forçado a defender "a cota" mesmo sabendo dos riscos. Não é vilão — é vítima armada. | L62: =IF(C62="Comum",ROUND(E62*1.3,0),"—") | M62: =IF(C62="Comum",ROUND(F62*1.15,0),"—") | N62: =IF(C62="Comum",G62+2,"—") | O62: =IF(C62="Comum",ROUND(E62*1.6,0),"—") | P62: =IF(C62="Comum",ROUND(F62*1.3,0),"—") | Q62: =IF(C62="Comum",G62+4,"—") | R62: Salário Atrasado | S62: =ROUND(INDEX('Curva Mestra'!$D$20:$D$94,MATCH(D62,'Curva Mestra'!$A$20:$A$94,0))-IF(C62="Comum",9,IF(C62="Elite",6,IF(C62="Boss",4,3))),0) | T62: Ouro + Distintivo Endividado de Mineiro Grimm + Quitina de Aranha das Cavernas (chance rara) | U62: Sem fraqueza óbvia — precisa de Knowledge alto pra descobrir algo específico. | V62: DPS | W62: Mina de Bronze
A63: Bronze | B63: Matriarca da Colônia de Aranhas | C63: Elite | D63: 6 | E63: =ROUND(INDEX('Curva Mestra'!$G$20:$G$94,MATCH(D63,'Curva Mestra'!$A$20:$A$94,0)),0) | F63: =ROUND(INDEX('Curva Mestra'!$C$20:$C$94,MATCH(D63,'Curva Mestra'!$A$20:$A$94,0))*INDEX($B$5:$B$8,MATCH(C63,$A$5:$A$8,0)),0) | G63: =ROUND(INDEX('Curva Mestra'!$D$20:$D$94,MATCH(D63,'Curva Mestra'!$A$20:$A$94,0))+INDEX($C$5:$C$8,MATCH(C63,$A$5:$A$8,0)),0) | H63: Encontro dificil dentro do tier Bronze | I63: Teia Asfixiante | J63: O herói perde a ação de movimento/fuga no turno seguinte se atingido. | K63: Não serve à infecção — defende o próprio território dela com a mesma ferocidade que os cultistas usam para marcar portas. | L63: =IF(C63="Comum",ROUND(E63*1.3,0),"—") | M63: =IF(C63="Comum",ROUND(F63*1.15,0),"—") | N63: =IF(C63="Comum",G63+2,"—") | O63: =IF(C63="Comum",ROUND(E63*1.6,0),"—") | P63: =IF(C63="Comum",ROUND(F63*1.3,0),"—") | Q63: =IF(C63="Comum",G63+4,"—") | R63: O Ninho Que Não Devia Crescer | S63: =ROUND(INDEX('Curva Mestra'!$D$20:$D$94,MATCH(D63,'Curva Mestra'!$A$20:$A$94,0))-IF(C63="Comum",9,IF(C63="Elite",6,IF(C63="Boss",4,3))),0) | T63: Casco de Quitina de Matriarca da Colônia de Aranhas + Ouro + Quitina de Aranha das Cavernas (chance baixa) | U63: Perde o bônus de grupo se isolado dos outros cultistas em combate. | V63: DPS | W63: Mina de Bronze
A64: Bronze | B64: Veio de Minério Falso | C64: Elite | D64: 6 | E64: =ROUND(INDEX('Curva Mestra'!$G$20:$G$94,MATCH(D64,'Curva Mestra'!$A$20:$A$94,0)),0) | F64: =ROUND(INDEX('Curva Mestra'!$C$20:$C$94,MATCH(D64,'Curva Mestra'!$A$20:$A$94,0))*INDEX($B$5:$B$8,MATCH(C64,$A$5:$A$8,0)),0) | G64: =ROUND(INDEX('Curva Mestra'!$D$20:$D$94,MATCH(D64,'Curva Mestra'!$A$20:$A$94,0))+INDEX($C$5:$C$8,MATCH(C64,$A$5:$A$8,0)),0) | H64: Plantado pela Guilda no veio mais rico da mina. | I64: Mordida do Veio | J64: Ignora Defesa + jogador perde 1 turno de surpresa. | K64: A Guilda espalhou minério-armadilha pra pegar quem rouba sem pagar imposto. | L64: =IF(C64="Comum",ROUND(E64*1.3,0),"—") | M64: =IF(C64="Comum",ROUND(F64*1.15,0),"—") | N64: =IF(C64="Comum",G64+2,"—") | O64: =IF(C64="Comum",ROUND(E64*1.6,0),"—") | P64: =IF(C64="Comum",ROUND(F64*1.3,0),"—") | Q64: =IF(C64="Comum",G64+4,"—") | S64: =ROUND(3+0.6*D64+IF(C64="Comum",0,IF(C64="Elite",2,IF(C64="Boss",4,6))),0) | T64: Ouro + Minério de Bronze Sulfuroso (chance alta, x2) + Fragmento de Fechadura da Armadilha da Guilda | U64: Atordoamento | V64: Mímico | W64: Mina de Bronze — Veio Rico, 5% ao coletar | Z64: A Guilda dos Picaretas Negros os planta de propósito. | AA64: Minério de Bronze Sulfuroso x2 (falso — some ao ser revelado, sem uso real)
A65: Bronze | B65: Rato-Dourado da Mina | C65: Elite | D65: 6 | E65: =ROUND(INDEX('Curva Mestra'!$G$20:$G$94,MATCH(D65,'Curva Mestra'!$A$20:$A$94,0)),0) | F65: =ROUND(INDEX('Curva Mestra'!$C$20:$C$94,MATCH(D65,'Curva Mestra'!$A$20:$A$94,0))*INDEX($B$5:$B$8,MATCH(C65,$A$5:$A$8,0)),0) | G65: =ROUND(INDEX('Curva Mestra'!$D$20:$D$94,MATCH(D65,'Curva Mestra'!$A$20:$A$94,0))+INDEX($C$5:$C$8,MATCH(C65,$A$5:$A$8,0)),0) | H65: Raro, visto fugindo entre os veios de minério. | I65: Fuga Reluzente | J65: Não causa dano — foge no turno 3. | K65: Come poeira de minério há gerações. Brilha por dentro. | L65: =IF(C65="Comum",ROUND(E65*1.3,0),"—") | M65: =IF(C65="Comum",ROUND(F65*1.15,0),"—") | N65: =IF(C65="Comum",G65+2,"—") | O65: =IF(C65="Comum",ROUND(E65*1.6,0),"—") | P65: =IF(C65="Comum",ROUND(F65*1.3,0),"—") | Q65: =IF(C65="Comum",G65+4,"—") | S65: =ROUND(3+0.6*D65+IF(C65="Comum",0,IF(C65="Elite",2,IF(C65="Boss",4,6))),0) | T65: Ouro + Pelagem Dourada de Rato-Dourado + Bolsa de Poeira Reluzente | U65: Lentidão | V65: Superloot/Evasivo | W65: Mina de Bronze, spawn raro (2%) | AA65: Veio de Ferro Negro (material de Tier 3)
A66: Bronze | B66: Capataz Enforcado | C66: Elite | D66: 7 | E66: =ROUND(INDEX('Curva Mestra'!$G$20:$G$94,MATCH(D66,'Curva Mestra'!$A$20:$A$94,0)),0) | F66: =ROUND(INDEX('Curva Mestra'!$C$20:$C$94,MATCH(D66,'Curva Mestra'!$A$20:$A$94,0))*INDEX($B$5:$B$8,MATCH(C66,$A$5:$A$8,0)),0) | G66: =ROUND(INDEX('Curva Mestra'!$D$20:$D$94,MATCH(D66,'Curva Mestra'!$A$20:$A$94,0))+INDEX($C$5:$C$8,MATCH(C66,$A$5:$A$8,0)),0) | H66: Ligado à Guilda dos Picaretas Negros, região de Bronze. | I66: Cota Impossível | J66: Ataca duas vezes se o alvo estiver com menos de 50% de HP (não perdoa "fraqueza"). | K66: Foi morto por trabalhadores em uma revolta — voltou pra continuar cobrando a cota, mesmo sem patrão vivo pra reportar. Um morto ainda mais fiel que os vivos. | L66: =IF(C66="Comum",ROUND(E66*1.3,0),"—") | M66: =IF(C66="Comum",ROUND(F66*1.15,0),"—") | N66: =IF(C66="Comum",G66+2,"—") | O66: =IF(C66="Comum",ROUND(E66*1.6,0),"—") | P66: =IF(C66="Comum",ROUND(F66*1.3,0),"—") | Q66: =IF(C66="Comum",G66+4,"—") | R66: O Capataz Que Não Descansa | S66: =ROUND(INDEX('Curva Mestra'!$D$20:$D$94,MATCH(D66,'Curva Mestra'!$A$20:$A$94,0))-IF(C66="Comum",9,IF(C66="Elite",6,IF(C66="Boss",4,3))),0) | T66: Presa de Capataz Enforcado + Ouro + Quitina de Aranha das Cavernas (chance baixa) | U66: Vulnerável a Prata — armas de Prata ignoram 2 de Defesa a mais nele. | V66: DPS | W66: Mina de Bronze
A67: Bronze | B67: Contramestre Enlouquecido | C67: Elite | D67: 7 | E67: =ROUND(INDEX('Curva Mestra'!$G$20:$G$94,MATCH(D67,'Curva Mestra'!$A$20:$A$94,0)),0) | F67: =ROUND(INDEX('Curva Mestra'!$C$20:$C$94,MATCH(D67,'Curva Mestra'!$A$20:$A$94,0))*INDEX($B$5:$B$8,MATCH(C67,$A$5:$A$8,0)),0) | G67: =ROUND(INDEX('Curva Mestra'!$D$20:$D$94,MATCH(D67,'Curva Mestra'!$A$20:$A$94,0))+INDEX($C$5:$C$8,MATCH(C67,$A$5:$A$8,0)),0) | H67: Ocupa o antigo escritório do capataz na Mina de Bronze. | I67: Grito da Cota | J67: Reduz sua chance de acerto em 15% por 2 turnos (grita ordens impossíveis). | K67: A cota do Barão nunca foi atingível. Ele enlouqueceu tentando. | L67: =IF(C67="Comum",ROUND(E67*1.3,0),"—") | M67: =IF(C67="Comum",ROUND(F67*1.15,0),"—") | N67: =IF(C67="Comum",G67+2,"—") | O67: =IF(C67="Comum",ROUND(E67*1.6,0),"—") | P67: =IF(C67="Comum",ROUND(F67*1.3,0),"—") | Q67: =IF(C67="Comum",G67+4,"—") | S67: =ROUND(3+0.6*D67+IF(C67="Comum",0,IF(C67="Elite",2,IF(C67="Boss",4,6))),0) | T67: Ouro + Fragmento de Contramestre Enlouquecido + Corda Arrebentada da Enforca + Quitina de Aranha das Cavernas (chance baixa) | U67: Atordoamento | V67: Debuffer | W67: Mina de Bronze — Escritório do Capataz | Z67: A Guilda dos Picaretas Negros o considerava "eficiente" — não vai vingá-lo.
A68: Bronze | B68: Supervisor Ferido | C68: Elite | D68: 7 | E68: =ROUND(INDEX('Curva Mestra'!$G$20:$G$94,MATCH(D68,'Curva Mestra'!$A$20:$A$94,0)),0) | F68: =ROUND(INDEX('Curva Mestra'!$C$20:$C$94,MATCH(D68,'Curva Mestra'!$A$20:$A$94,0))*INDEX($B$5:$B$8,MATCH(C68,$A$5:$A$8,0)),0) | G68: =ROUND(INDEX('Curva Mestra'!$D$20:$D$94,MATCH(D68,'Curva Mestra'!$A$20:$A$94,0))+INDEX($C$5:$C$8,MATCH(C68,$A$5:$A$8,0)),0) | H68: Capataz sobrevivente, mais cruel depois do acidente. | I68: Golpe de Autoridade | J68: Ignora Defesa + concede Fragilidade ao equipamento do jogador. | K68: Um dos capatazes que sobreviveu ao desabamento de Kessa. Ficou pior depois. | L68: =IF(C68="Comum",ROUND(E68*1.3,0),"—") | M68: =IF(C68="Comum",ROUND(F68*1.15,0),"—") | N68: =IF(C68="Comum",G68+2,"—") | O68: =IF(C68="Comum",ROUND(E68*1.6,0),"—") | P68: =IF(C68="Comum",ROUND(F68*1.3,0),"—") | Q68: =IF(C68="Comum",G68+4,"—") | S68: =ROUND(3+0.6*D68+IF(C68="Comum",0,IF(C68="Elite",2,IF(C68="Boss",4,6))),0) | T68: Ouro + Fragmento de Supervisor Ferido + Bandagem Suja do Supervisor + Quitina de Aranha das Cavernas (chance baixa) | U68: Lentidão | V68: DPS | W68: Mina de Bronze — Escritório do Capataz
A69: Bronze | B69: Aranha da Névoa | C69: Elite | D69: 8 | E69: =ROUND(INDEX('Curva Mestra'!$G$20:$G$94,MATCH(D69,'Curva Mestra'!$A$20:$A$94,0)),0) | F69: =ROUND(INDEX('Curva Mestra'!$C$20:$C$94,MATCH(D69,'Curva Mestra'!$A$20:$A$94,0))*INDEX($B$5:$B$8,MATCH(C69,$A$5:$A$8,0)),0) | G69: =ROUND(INDEX('Curva Mestra'!$D$20:$D$94,MATCH(D69,'Curva Mestra'!$A$20:$A$94,0))+INDEX($C$5:$C$8,MATCH(C69,$A$5:$A$8,0)),0) | H69: Aparece nas bolsas de gás dos túneis baixos da mina. | I69: Névoa Sufocante | J69: Atordoamento em área (20% de chance, afeta todos no combate). | K69: Vive nas bolsas de gás da mina — a névoa que solta é parte dela. | L69: =IF(C69="Comum",ROUND(E69*1.3,0),"—") | M69: =IF(C69="Comum",ROUND(F69*1.15,0),"—") | N69: =IF(C69="Comum",G69+2,"—") | O69: =IF(C69="Comum",ROUND(E69*1.6,0),"—") | P69: =IF(C69="Comum",ROUND(F69*1.3,0),"—") | Q69: =IF(C69="Comum",G69+4,"—") | S69: =ROUND(3+0.6*D69+IF(C69="Comum",0,IF(C69="Elite",2,IF(C69="Boss",4,6))),0) | T69: Ouro + Glândula de Névoa de Aranha da Névoa + Quitina de Aranha das Cavernas (chance baixa) | U69: Ignora Resistência Mágica | V69: Controle | W69: Mina de Bronze — Túneis Baixos | Y69: Só aparece onde há Nuvem de Gás Sulfuroso por perto.
A70: Bronze | B70: Kessa, a Sobrevivente do Desabamento | C70: Elite | D70: 8 | E70: =ROUND(INDEX('Curva Mestra'!$G$20:$G$94,MATCH(D70,'Curva Mestra'!$A$20:$A$94,0)),0) | F70: =ROUND(INDEX('Curva Mestra'!$C$20:$C$94,MATCH(D70,'Curva Mestra'!$A$20:$A$94,0))*INDEX($B$5:$B$8,MATCH(C70,$A$5:$A$8,0)),0) | G70: =ROUND(INDEX('Curva Mestra'!$D$20:$D$94,MATCH(D70,'Curva Mestra'!$A$20:$A$94,0))+INDEX($C$5:$C$8,MATCH(C70,$A$5:$A$8,0)),0) | H70: Vista raramente na galeria que desabou anos atrás. | I70: Fúria da Sobrevivência | J70: Ignora Defesa + Rouba Vida (10%). | K70: Ficou presa 6 dias sob os escombros depois que Grimm mandou minerar rápido demais. Saiu diferente. | L70: =IF(C70="Comum",ROUND(E70*1.3,0),"—") | M70: =IF(C70="Comum",ROUND(F70*1.15,0),"—") | N70: =IF(C70="Comum",G70+2,"—") | O70: =IF(C70="Comum",ROUND(E70*1.6,0),"—") | P70: =IF(C70="Comum",ROUND(F70*1.3,0),"—") | Q70: =IF(C70="Comum",G70+4,"—") | S70: =ROUND(3+0.6*D70+IF(C70="Comum",0,IF(C70="Elite",2,IF(C70="Boss",4,6))),0) | T70: Ouro + Fragmento da Sobrevivente do Desabamento + Quitina de Aranha das Cavernas (chance baixa) | U70: Lentidão | V70: Nomeado / Mini-Boss | W70: Mina de Bronze — Galeria Colapsada, spawn raro (4%) | X70: A 30% de HP para de atacar e oferece ajudar o jogador contra Grimm. | Z70: A Guilda a considera morta — reaparecer é problema pra eles. | AA70: Amuleto da Sobrevivente (se derrotada em vez de poupada) [ver Artefatos e Relíquias]
A71: Bronze | B71: Rainha-Aranha da Mina | C71: Boss | D71: 8 | E71: =ROUND(INDEX('Curva Mestra'!$H$20:$H$94,MATCH(D71,'Curva Mestra'!$A$20:$A$94,0)),0) | F71: =ROUND(INDEX('Curva Mestra'!$C$20:$C$94,MATCH(D71,'Curva Mestra'!$A$20:$A$94,0))*INDEX($B$5:$B$8,MATCH(C71,$A$5:$A$8,0)),0) | G71: =ROUND(INDEX('Curva Mestra'!$D$20:$D$94,MATCH(D71,'Curva Mestra'!$A$20:$A$94,0))+INDEX($C$5:$C$8,MATCH(C71,$A$5:$A$8,0)),0) | H71: Chefe / marco final do tier Bronze | I71: Enxame de Filhotes | J71: Invoca 2 Aranhas da Mina adicionais no início do combate. Também aplica: Ignora 1 ponto de Defesa do alvo. | K71: A colônia inteira responde a ela. Cresceu rápido demais, no mesmo ritmo em que Grimm ignorou os alertas dos mineiros pra não perder produção. | L71: =IF(C71="Comum",ROUND(E71*1.3,0),"—") | M71: =IF(C71="Comum",ROUND(F71*1.15,0),"—") | N71: =IF(C71="Comum",G71+2,"—") | O71: =IF(C71="Comum",ROUND(E71*1.6,0),"—") | P71: =IF(C71="Comum",ROUND(F71*1.3,0),"—") | Q71: =IF(C71="Comum",G71+4,"—") | R71: O Ninho Que Não Devia Crescer | S71: =ROUND(INDEX('Curva Mestra'!$D$20:$D$94,MATCH(D71,'Curva Mestra'!$A$20:$A$94,0))-IF(C71="Comum",9,IF(C71="Elite",6,IF(C71="Boss",4,3))),0) | T71: Casco de Quitina de Rainha-Aranha da Mina + Essência de Rainha-Aranha da Mina + Ouro + Quitina de Aranha das Cavernas (chance baixa) | U71: Vulnerável a Ignora Defesa — pele grossa, mas com pontos fracos previsíveis. | V71: DPS | W71: Mina de Bronze
A72: Bronze | B72: Barão Aldous Grimm (Corrompido) | C72: Boss | D72: 10 | E72: =ROUND(INDEX('Curva Mestra'!$H$20:$H$94,MATCH(D72,'Curva Mestra'!$A$20:$A$94,0)),0) | F72: =ROUND(INDEX('Curva Mestra'!$C$20:$C$94,MATCH(D72,'Curva Mestra'!$A$20:$A$94,0))*INDEX($B$5:$B$8,MATCH(C72,$A$5:$A$8,0)),0) | G72: =ROUND(INDEX('Curva Mestra'!$D$20:$D$94,MATCH(D72,'Curva Mestra'!$A$20:$A$94,0))+INDEX($C$5:$C$8,MATCH(C72,$A$5:$A$8,0)),0) | H72: Ligado à Guilda dos Picaretas Negros, região de Bronze. | I72: Peso do Ouro | J72: No início do combate, reduz o Bônus de Ataque de todos os heróis em 1 (a ganância pesa no braço de quem luta por ela também). Também aplica: Ignora 1 ponto de Defesa do alvo. | K72: Respirou vapor contaminado por anos recusando fechar a mina. Sabia que os túneis profundos tocavam as criptas — escondeu isso por lucro, exatamente como está registrado nos Livros de Grimm. | L72: =IF(C72="Comum",ROUND(E72*1.3,0),"—") | M72: =IF(C72="Comum",ROUND(F72*1.15,0),"—") | N72: =IF(C72="Comum",G72+2,"—") | O72: =IF(C72="Comum",ROUND(E72*1.6,0),"—") | P72: =IF(C72="Comum",ROUND(F72*1.3,0),"—") | Q72: =IF(C72="Comum",G72+4,"—") | R72: A Ganância Não Morre | S72: =ROUND(INDEX('Curva Mestra'!$D$20:$D$94,MATCH(D72,'Curva Mestra'!$A$20:$A$94,0))-IF(C72="Comum",9,IF(C72="Elite",6,IF(C72="Boss",4,3))),0) | T72: Selo Pessoal de Barão Aldous Grimm (Corrompido) + Essência de Barão Aldous Grimm (Corrompido) + Ouro + Quitina de Aranha das Cavernas (chance baixa) | U72: Vulnerável a Atordoamento — travas mecânicas emperram com o dobro de chance. | V72: DPS | W72: Mina de Bronze
A73: Ferro | B73: Esqueleto Enferrujado | C73: Comum | D73: 8 | E73: =ROUND(INDEX('Curva Mestra'!$F$20:$F$94,MATCH(D73,'Curva Mestra'!$A$20:$A$94,0)),0) | F73: =ROUND(INDEX('Curva Mestra'!$C$20:$C$94,MATCH(D73,'Curva Mestra'!$A$20:$A$94,0))*INDEX($B$5:$B$8,MATCH(C73,$A$5:$A$8,0)),0) | G73: =ROUND(INDEX('Curva Mestra'!$D$20:$D$94,MATCH(D73,'Curva Mestra'!$A$20:$A$94,0))+INDEX($C$5:$C$8,MATCH(C73,$A$5:$A$8,0)),0) | H73: Ronda a regiao do tier Ferro | I73: Golpe Trêmulo | J73: Sem efeito especial. | K73: Guarda de fronteira comum morto no primeiro surto — a armadura de ferro fundiu-se aos ossos antes mesmo da carne apodrecer. | L73: =IF(C73="Comum",ROUND(E73*1.3,0),"—") | M73: =IF(C73="Comum",ROUND(F73*1.15,0),"—") | N73: =IF(C73="Comum",G73+2,"—") | O73: =IF(C73="Comum",ROUND(E73*1.6,0),"—") | P73: =IF(C73="Comum",ROUND(F73*1.3,0),"—") | Q73: =IF(C73="Comum",G73+4,"—") | R73: O Golem da Forja | S73: =ROUND(INDEX('Curva Mestra'!$D$20:$D$94,MATCH(D73,'Curva Mestra'!$A$20:$A$94,0))-IF(C73="Comum",9,IF(C73="Elite",6,IF(C73="Boss",4,3))),0) | T73: Ouro + Armadura Fundida ao Osso + Fragmento de Golem Corrompido (chance rara) | U73: Vulnerável a Prata — armas de Prata ignoram 2 de Defesa a mais nele. | V73: DPS | W73: Ruínas da Antiga Forja
A74: Ferro | B74: Acólito do Ferro | C74: Comum | D74: 8 | E74: =ROUND(INDEX('Curva Mestra'!$F$20:$F$94,MATCH(D74,'Curva Mestra'!$A$20:$A$94,0)),0) | F74: =ROUND(INDEX('Curva Mestra'!$C$20:$C$94,MATCH(D74,'Curva Mestra'!$A$20:$A$94,0))*INDEX($B$5:$B$8,MATCH(C74,$A$5:$A$8,0)),0) | G74: =ROUND(INDEX('Curva Mestra'!$D$20:$D$94,MATCH(D74,'Curva Mestra'!$A$20:$A$94,0))+INDEX($C$5:$C$8,MATCH(C74,$A$5:$A$8,0)),0) | H74: Recém-chegado ao culto, ainda perto da muralha externa. | I74: Golpe Hesitante | J74: Nenhum — 20% de chance de recusar atacar se abordado em paz. | K74: Entrou no culto por fome, não por fé. | L74: =IF(C74="Comum",ROUND(E74*1.3,0),"—") | M74: =IF(C74="Comum",ROUND(F74*1.15,0),"—") | N74: =IF(C74="Comum",G74+2,"—") | O74: =IF(C74="Comum",ROUND(E74*1.6,0),"—") | P74: =IF(C74="Comum",ROUND(F74*1.3,0),"—") | Q74: =IF(C74="Comum",G74+4,"—") | S74: =ROUND(3+0.6*D74+IF(C74="Comum",0,IF(C74="Elite",2,IF(C74="Boss",4,6))),0) | T74: Ouro + Pão Roubado do Acólito | U74: Atordoamento | V74: Não-hostil condicional | W74: Ruínas da Antiga Forja — Muralha Externa | Y74: Se abordado sem combate, pode ser convencido a desertar (quest). | Z74: A Milícia dos Desamparados aceita desertores do Culto.
A75: Ferro | B75: Ferrugem Viva | C75: Comum | D75: 8 | E75: =ROUND(INDEX('Curva Mestra'!$F$20:$F$94,MATCH(D75,'Curva Mestra'!$A$20:$A$94,0)),0) | F75: =ROUND(INDEX('Curva Mestra'!$C$20:$C$94,MATCH(D75,'Curva Mestra'!$A$20:$A$94,0))*INDEX($B$5:$B$8,MATCH(C75,$A$5:$A$8,0)),0) | G75: =ROUND(INDEX('Curva Mestra'!$D$20:$D$94,MATCH(D75,'Curva Mestra'!$A$20:$A$94,0))+INDEX($C$5:$C$8,MATCH(C75,$A$5:$A$8,0)),0) | H75: Cresce nas juntas dos golems da fundição. | I75: Corrosão | J75: Fragilidade — só aparece perto de Golems. | K75: Cresce nas juntas dos golems, come o próprio metal que os anima. | L75: =IF(C75="Comum",ROUND(E75*1.3,0),"—") | M75: =IF(C75="Comum",ROUND(F75*1.15,0),"—") | N75: =IF(C75="Comum",G75+2,"—") | O75: =IF(C75="Comum",ROUND(E75*1.6,0),"—") | P75: =IF(C75="Comum",ROUND(F75*1.3,0),"—") | Q75: =IF(C75="Comum",G75+4,"—") | S75: =ROUND(3+0.6*D75+IF(C75="Comum",0,IF(C75="Elite",2,IF(C75="Boss",4,6))),0) | T75: Casulo de Ferrugem Viva + Óxido Animado | U75: Queimadura | V75: Parasita | W75: Ruínas da Antiga Forja — Fundição, só com Golem presente
A76: Ferro | B76: Guardião Enferrujado | C76: Comum | D76: 8 | E76: =ROUND(INDEX('Curva Mestra'!$F$20:$F$94,MATCH(D76,'Curva Mestra'!$A$20:$A$94,0)),0) | F76: =ROUND(INDEX('Curva Mestra'!$C$20:$C$94,MATCH(D76,'Curva Mestra'!$A$20:$A$94,0))*INDEX($B$5:$B$8,MATCH(C76,$A$5:$A$8,0)),0) | G76: =ROUND(INDEX('Curva Mestra'!$D$20:$D$94,MATCH(D76,'Curva Mestra'!$A$20:$A$94,0))+INDEX($C$5:$C$8,MATCH(C76,$A$5:$A$8,0)),0) | H76: Postado permanentemente na muralha externa das ruínas. | I76: Golpe de Escudo | J76: Nenhum efeito adicional. | K76: Estátua de guarda que a Infecção fez andar de novo. | L76: =IF(C76="Comum",ROUND(E76*1.3,0),"—") | M76: =IF(C76="Comum",ROUND(F76*1.15,0),"—") | N76: =IF(C76="Comum",G76+2,"—") | O76: =IF(C76="Comum",ROUND(E76*1.6,0),"—") | P76: =IF(C76="Comum",ROUND(F76*1.3,0),"—") | Q76: =IF(C76="Comum",G76+4,"—") | S76: =ROUND(3+0.6*D76+IF(C76="Comum",0,IF(C76="Elite",2,IF(C76="Boss",4,6))),0) | T76: Ouro + Placa Enferrujada de Guardião + Elmo Fundido de Guardião | U76: Ignora Resistência Mágica | V76: DPS simples | W76: Ruínas da Antiga Forja — Muralha Externa
A77: Ferro | B77: Esqueleto Arqueiro | C77: Comum | D77: 9 | E77: =ROUND(INDEX('Curva Mestra'!$F$20:$F$94,MATCH(D77,'Curva Mestra'!$A$20:$A$94,0)),0) | F77: =ROUND(INDEX('Curva Mestra'!$C$20:$C$94,MATCH(D77,'Curva Mestra'!$A$20:$A$94,0))*INDEX($B$5:$B$8,MATCH(C77,$A$5:$A$8,0)),0) | G77: =ROUND(INDEX('Curva Mestra'!$D$20:$D$94,MATCH(D77,'Curva Mestra'!$A$20:$A$94,0))+INDEX($C$5:$C$8,MATCH(C77,$A$5:$A$8,0)),0) | H77: Posta-se na muralha externa das Ruínas da Antiga Forja. | I77: Flecha Enferrujada | J77: Sangramento (a ponta farpada rasga ao sair). | K77: Guarda arqueira da antiga forja, ainda de posto após séculos. | L77: =IF(C77="Comum",ROUND(E77*1.3,0),"—") | M77: =IF(C77="Comum",ROUND(F77*1.15,0),"—") | N77: =IF(C77="Comum",G77+2,"—") | O77: =IF(C77="Comum",ROUND(E77*1.6,0),"—") | P77: =IF(C77="Comum",ROUND(F77*1.3,0),"—") | Q77: =IF(C77="Comum",G77+4,"—") | S77: =ROUND(3+0.6*D77+IF(C77="Comum",0,IF(C77="Elite",2,IF(C77="Boss",4,6))),0) | T77: Ouro + Arco de Osso Frágil + Flecha Enferrujada de Esqueleto | U77: Ignora Defesa | V77: Ranged/DPS | W77: Ruínas da Antiga Forja — Muralha Externa
A78: Ferro | B78: Ossos Errantes | C78: Comum | D78: 9 | E78: =ROUND(INDEX('Curva Mestra'!$F$20:$F$94,MATCH(D78,'Curva Mestra'!$A$20:$A$94,0)),0) | F78: =ROUND(INDEX('Curva Mestra'!$C$20:$C$94,MATCH(D78,'Curva Mestra'!$A$20:$A$94,0))*INDEX($B$5:$B$8,MATCH(C78,$A$5:$A$8,0)),0) | G78: =ROUND(INDEX('Curva Mestra'!$D$20:$D$94,MATCH(D78,'Curva Mestra'!$A$20:$A$94,0))+INDEX($C$5:$C$8,MATCH(C78,$A$5:$A$8,0)),0) | H78: Fragmentos remontados encontrados pela muralha externa. | I78: Golpe Descoordenado | J78: Se destruído sem ser com golpe crítico, se remonta 1x com 30% do HP. | K78: Fragmentos soltos de vários esqueletos, remontados errado pela Infecção. | L78: =IF(C78="Comum",ROUND(E78*1.3,0),"—") | M78: =IF(C78="Comum",ROUND(F78*1.15,0),"—") | N78: =IF(C78="Comum",G78+2,"—") | O78: =IF(C78="Comum",ROUND(E78*1.6,0),"—") | P78: =IF(C78="Comum",ROUND(F78*1.3,0),"—") | Q78: =IF(C78="Comum",G78+4,"—") | S78: =ROUND(3+0.6*D78+IF(C78="Comum",0,IF(C78="Elite",2,IF(C78="Boss",4,6))),0) | T78: Ouro + Feixe de Ossos Remontados | U78: Ignora Defesa | V78: Tanque | W78: Ruínas da Antiga Forja — Muralha Externa | X78: Remonta 1x se não for finalizado com crítico.
A79: Ferro | B79: Guarda Espectral Menor | C79: Comum | D79: 9 | E79: =ROUND(INDEX('Curva Mestra'!$F$20:$F$94,MATCH(D79,'Curva Mestra'!$A$20:$A$94,0)),0) | F79: =ROUND(INDEX('Curva Mestra'!$C$20:$C$94,MATCH(D79,'Curva Mestra'!$A$20:$A$94,0))*INDEX($B$5:$B$8,MATCH(C79,$A$5:$A$8,0)),0) | G79: =ROUND(INDEX('Curva Mestra'!$D$20:$D$94,MATCH(D79,'Curva Mestra'!$A$20:$A$94,0))+INDEX($C$5:$C$8,MATCH(C79,$A$5:$A$8,0)),0) | H79: Vagueia pelo salão dos comandantes desde o primeiro cerco. | I79: Toque Gélido da Guarda | J79: Lentidão (perde ação de movimento). | K79: Sobra de guardas que morreram no primeiro cerco à forja. | L79: =IF(C79="Comum",ROUND(E79*1.3,0),"—") | M79: =IF(C79="Comum",ROUND(F79*1.15,0),"—") | N79: =IF(C79="Comum",G79+2,"—") | O79: =IF(C79="Comum",ROUND(E79*1.6,0),"—") | P79: =IF(C79="Comum",ROUND(F79*1.3,0),"—") | Q79: =IF(C79="Comum",G79+4,"—") | S79: =ROUND(3+0.6*D79+IF(C79="Comum",0,IF(C79="Elite",2,IF(C79="Boss",4,6))),0) | T79: Resíduo Espectral de Guarda Menor + Fragmento de Armadura Espectral | U79: Queimadura | V79: Controle | W79: Ruínas da Antiga Forja — Salão dos Comandantes
A80: Ferro | B80: Salteador Batedor | C80: Comum | D80: 9 | E80: =ROUND(INDEX('Curva Mestra'!$F$20:$F$94,MATCH(D80,'Curva Mestra'!$A$20:$A$94,0)),0) | F80: =ROUND(INDEX('Curva Mestra'!$C$20:$C$94,MATCH(D80,'Curva Mestra'!$A$20:$A$94,0))*INDEX($B$5:$B$8,MATCH(C80,$A$5:$A$8,0)),0) | G80: =ROUND(INDEX('Curva Mestra'!$D$20:$D$94,MATCH(D80,'Curva Mestra'!$A$20:$A$94,0))+INDEX($C$5:$C$8,MATCH(C80,$A$5:$A$8,0)),0) | H80: Vigia os arredores das Ruínas da Antiga Forja. | I80: Faca nas Costas | J80: Ignora Defesa + próximo encontro no local vem com +1 monstro. | K80: Vigia as ruínas de longe, avisa o resto do bando. | L80: =IF(C80="Comum",ROUND(E80*1.3,0),"—") | M80: =IF(C80="Comum",ROUND(F80*1.15,0),"—") | N80: =IF(C80="Comum",G80+2,"—") | O80: =IF(C80="Comum",ROUND(E80*1.6,0),"—") | P80: =IF(C80="Comum",ROUND(F80*1.3,0),"—") | Q80: =IF(C80="Comum",G80+4,"—") | S80: =ROUND(3+0.6*D80+IF(C80="Comum",0,IF(C80="Elite",2,IF(C80="Boss",4,6))),0) | T80: Ouro + Capuz Encardido de Batedor + Corda de Vigia | U80: Atordoamento | V80: Batedor | W80: Ruínas da Antiga Forja — arredores
A81: Ferro | B81: Espírito do Ferreiro Original | C81: Comum | D81: 9 | E81: =ROUND(INDEX('Curva Mestra'!$F$20:$F$94,MATCH(D81,'Curva Mestra'!$A$20:$A$94,0)),0) | F81: =ROUND(INDEX('Curva Mestra'!$C$20:$C$94,MATCH(D81,'Curva Mestra'!$A$20:$A$94,0))*INDEX($B$5:$B$8,MATCH(C81,$A$5:$A$8,0)),0) | G81: =ROUND(INDEX('Curva Mestra'!$D$20:$D$94,MATCH(D81,'Curva Mestra'!$A$20:$A$94,0))+INDEX($C$5:$C$8,MATCH(C81,$A$5:$A$8,0)),0) | H81: Vagueia pela forja ainda ativa das ruínas. | I81: (não ataca) | J81: Não-hostil: guia até um segredo da forja se poupado. | K81: O primeiro ferreiro da forja, morto antes mesmo da Infecção chegar. | L81: =IF(C81="Comum",ROUND(E81*1.3,0),"—") | M81: =IF(C81="Comum",ROUND(F81*1.15,0),"—") | N81: =IF(C81="Comum",G81+2,"—") | O81: =IF(C81="Comum",ROUND(E81*1.6,0),"—") | P81: =IF(C81="Comum",ROUND(F81*1.3,0),"—") | Q81: =IF(C81="Comum",G81+4,"—") | S81: =ROUND(3+0.6*D81+IF(C81="Comum",0,IF(C81="Elite",2,IF(C81="Boss",4,6))),0) | T81: Martelo Etéreo do Ferreiro Original + Fagulha do Primeiro Forjador | U81: Sem fraqueza óbvia — precisa de Knowledge alto pra descobrir algo específico. | V81: Não-hostil | W81: Ruínas da Antiga Forja — Forja Ativa | Y81: Revela a localização de um veio raro se poupado.
A82: Ferro | B82: Esqueleto Recém-Erguido | C82: Comum | D82: 9 | E82: =ROUND(INDEX('Curva Mestra'!$F$20:$F$94,MATCH(D82,'Curva Mestra'!$A$20:$A$94,0)),0) | F82: =ROUND(INDEX('Curva Mestra'!$C$20:$C$94,MATCH(D82,'Curva Mestra'!$A$20:$A$94,0))*INDEX($B$5:$B$8,MATCH(C82,$A$5:$A$8,0)),0) | G82: =ROUND(INDEX('Curva Mestra'!$D$20:$D$94,MATCH(D82,'Curva Mestra'!$A$20:$A$94,0))+INDEX($C$5:$C$8,MATCH(C82,$A$5:$A$8,0)),0) | H82: Esqueleto recém-reanimado. | I82: Golpe Descoordenado Fraco | J82: Nenhum efeito adicional — mais fraco que os outros esqueletos. | K82: Levantado há pouco tempo, ainda não recuperou a coordenação de quando vivo. | L82: =IF(C82="Comum",ROUND(E82*1.3,0),"—") | M82: =IF(C82="Comum",ROUND(F82*1.15,0),"—") | N82: =IF(C82="Comum",G82+2,"—") | O82: =IF(C82="Comum",ROUND(E82*1.6,0),"—") | P82: =IF(C82="Comum",ROUND(F82*1.3,0),"—") | Q82: =IF(C82="Comum",G82+4,"—") | S82: =ROUND(3+0.6*D82+IF(C82="Comum",0,IF(C82="Elite",2,IF(C82="Boss",4,6))),0) | T82: Ouro + Osso Desconjuntado | U82: Ignora Defesa | V82: DPS fraco | W82: Ruínas da Antiga Forja — Muralha Externa
A83: Ferro | B83: Sombra da Guarda Menor | C83: Comum | D83: 9 | E83: =ROUND(INDEX('Curva Mestra'!$F$20:$F$94,MATCH(D83,'Curva Mestra'!$A$20:$A$94,0)),0) | F83: =ROUND(INDEX('Curva Mestra'!$C$20:$C$94,MATCH(D83,'Curva Mestra'!$A$20:$A$94,0))*INDEX($B$5:$B$8,MATCH(C83,$A$5:$A$8,0)),0) | G83: =ROUND(INDEX('Curva Mestra'!$D$20:$D$94,MATCH(D83,'Curva Mestra'!$A$20:$A$94,0))+INDEX($C$5:$C$8,MATCH(C83,$A$5:$A$8,0)),0) | H83: Resíduo espectral menor da guarda original. | I83: Toque Gélido Fraco | J83: Lentidão fraca. | K83: Fragmento pequeno da Guarda Espectral Menor. | L83: =IF(C83="Comum",ROUND(E83*1.3,0),"—") | M83: =IF(C83="Comum",ROUND(F83*1.15,0),"—") | N83: =IF(C83="Comum",G83+2,"—") | O83: =IF(C83="Comum",ROUND(E83*1.6,0),"—") | P83: =IF(C83="Comum",ROUND(F83*1.3,0),"—") | Q83: =IF(C83="Comum",G83+4,"—") | S83: =ROUND(3+0.6*D83+IF(C83="Comum",0,IF(C83="Elite",2,IF(C83="Boss",4,6))),0) | T83: Resíduo Espectral de Sombra Menor | U83: Queimadura | V83: Controle | W83: Ruínas da Antiga Forja — Salão dos Comandantes
A84: Ferro | B84: Salteador Encapuzado | C84: Comum | D84: 10 | E84: =ROUND(INDEX('Curva Mestra'!$F$20:$F$94,MATCH(D84,'Curva Mestra'!$A$20:$A$94,0)),0) | F84: =ROUND(INDEX('Curva Mestra'!$C$20:$C$94,MATCH(D84,'Curva Mestra'!$A$20:$A$94,0))*INDEX($B$5:$B$8,MATCH(C84,$A$5:$A$8,0)),0) | G84: =ROUND(INDEX('Curva Mestra'!$D$20:$D$94,MATCH(D84,'Curva Mestra'!$A$20:$A$94,0))+INDEX($C$5:$C$8,MATCH(C84,$A$5:$A$8,0)),0) | H84: Ronda a regiao do tier Ferro | I84: Ataque Furtivo | J84: +2 no primeiro golpe do combate se o alvo não percebeu a emboscada. | K84: Sobrevivente da vila que decidiu que roubar viajantes era mais seguro que confiar em qualquer autoridade depois do surto. | L84: =IF(C84="Comum",ROUND(E84*1.3,0),"—") | M84: =IF(C84="Comum",ROUND(F84*1.15,0),"—") | N84: =IF(C84="Comum",G84+2,"—") | O84: =IF(C84="Comum",ROUND(E84*1.6,0),"—") | P84: =IF(C84="Comum",ROUND(F84*1.3,0),"—") | Q84: =IF(C84="Comum",G84+4,"—") | R84: Descanso pro Salteador | S84: =ROUND(INDEX('Curva Mestra'!$D$20:$D$94,MATCH(D84,'Curva Mestra'!$A$20:$A$94,0))-IF(C84="Comum",9,IF(C84="Elite",6,IF(C84="Boss",4,3))),0) | T84: Ouro + Capa Encardida de Salteador + Fragmento de Golem Corrompido (chance rara) | U84: Sem fraqueza óbvia — precisa de Knowledge alto pra descobrir algo específico. | V84: DPS | W84: Ruínas da Antiga Forja
A85: Ferro | B85: Zelote Fanático | C85: Comum | D85: 10 | E85: =ROUND(INDEX('Curva Mestra'!$F$20:$F$94,MATCH(D85,'Curva Mestra'!$A$20:$A$94,0)),0) | F85: =ROUND(INDEX('Curva Mestra'!$C$20:$C$94,MATCH(D85,'Curva Mestra'!$A$20:$A$94,0))*INDEX($B$5:$B$8,MATCH(C85,$A$5:$A$8,0)),0) | G85: =ROUND(INDEX('Curva Mestra'!$D$20:$D$94,MATCH(D85,'Curva Mestra'!$A$20:$A$94,0))+INDEX($C$5:$C$8,MATCH(C85,$A$5:$A$8,0)),0) | H85: Aguarda no salão dos comandantes, pronto para o sacrifício. | I85: Grito Incendiário | J85: Ao morrer, Queimadura em área (2 dano, 2 turnos, todos no combate). | K85: Se prepara pra morrer em nome do Ferro desde que entrou no culto. | L85: =IF(C85="Comum",ROUND(E85*1.3,0),"—") | M85: =IF(C85="Comum",ROUND(F85*1.15,0),"—") | N85: =IF(C85="Comum",G85+2,"—") | O85: =IF(C85="Comum",ROUND(E85*1.6,0),"—") | P85: =IF(C85="Comum",ROUND(F85*1.3,0),"—") | Q85: =IF(C85="Comum",G85+4,"—") | S85: =ROUND(3+0.6*D85+IF(C85="Comum",0,IF(C85="Elite",2,IF(C85="Boss",4,6))),0) | T85: Cinto de Cargas do Zelote Fanático + Fragmento de Ferro Ritual | U85: Lentidão | V85: Explosivo | W85: Ruínas da Antiga Forja — Salão dos Comandantes
A86: Ferro | B86: Ladrão de Relíquias | C86: Comum | D86: 10 | E86: =ROUND(INDEX('Curva Mestra'!$F$20:$F$94,MATCH(D86,'Curva Mestra'!$A$20:$A$94,0)),0) | F86: =ROUND(INDEX('Curva Mestra'!$C$20:$C$94,MATCH(D86,'Curva Mestra'!$A$20:$A$94,0))*INDEX($B$5:$B$8,MATCH(C86,$A$5:$A$8,0)),0) | G86: =ROUND(INDEX('Curva Mestra'!$D$20:$D$94,MATCH(D86,'Curva Mestra'!$A$20:$A$94,0))+INDEX($C$5:$C$8,MATCH(C86,$A$5:$A$8,0)),0) | H86: Circula pelas ruínas em busca do que a Guilda ainda não levou. | I86: Mão Rápida | J86: Rouba 1 unidade de material (se você tiver) em vez de dano, foge depois. | K86: Vive saqueando o que sobrou da forja antes que a Guilda leve tudo. | L86: =IF(C86="Comum",ROUND(E86*1.3,0),"—") | M86: =IF(C86="Comum",ROUND(F86*1.15,0),"—") | N86: =IF(C86="Comum",G86+2,"—") | O86: =IF(C86="Comum",ROUND(E86*1.6,0),"—") | P86: =IF(C86="Comum",ROUND(F86*1.3,0),"—") | Q86: =IF(C86="Comum",G86+4,"—") | S86: =ROUND(3+0.6*D86+IF(C86="Comum",0,IF(C86="Elite",2,IF(C86="Boss",4,6))),0) | T86: Ouro + Saco de Relíquias Menores + Gazua Enferrujada | U86: Lentidão | V86: Ladrão | W86: Ruínas da Antiga Forja | Y86: Foge com o item roubado se sobreviver 2 turnos.
A87: Ferro | B87: Golem Menor de Ferro | C87: Comum | D87: 10 | E87: =ROUND(INDEX('Curva Mestra'!$F$20:$F$94,MATCH(D87,'Curva Mestra'!$A$20:$A$94,0)),0) | F87: =ROUND(INDEX('Curva Mestra'!$C$20:$C$94,MATCH(D87,'Curva Mestra'!$A$20:$A$94,0))*INDEX($B$5:$B$8,MATCH(C87,$A$5:$A$8,0)),0) | G87: =ROUND(INDEX('Curva Mestra'!$D$20:$D$94,MATCH(D87,'Curva Mestra'!$A$20:$A$94,0))+INDEX($C$5:$C$8,MATCH(C87,$A$5:$A$8,0)),0) | H87: Fragmento funcional encontrado na fundição das ruínas. | I87: Punho de Sucata | J87: Nenhum efeito — só resistente. | K87: Fragmento pequeno do Golem maior, ainda funcional. | L87: =IF(C87="Comum",ROUND(E87*1.3,0),"—") | M87: =IF(C87="Comum",ROUND(F87*1.15,0),"—") | N87: =IF(C87="Comum",G87+2,"—") | O87: =IF(C87="Comum",ROUND(E87*1.6,0),"—") | P87: =IF(C87="Comum",ROUND(F87*1.3,0),"—") | Q87: =IF(C87="Comum",G87+4,"—") | S87: =ROUND(3+0.6*D87+IF(C87="Comum",0,IF(C87="Elite",2,IF(C87="Boss",4,6))),0) | T87: Placa de Ferro do Golem Menor + Núcleo Instável Menor | U87: Ignora Resistência Mágica | V87: Tanque | W87: Ruínas da Antiga Forja — Fundição
A88: Ferro | B88: Zelote Nascido na Forja | C88: Comum | D88: 10 | E88: =ROUND(INDEX('Curva Mestra'!$F$20:$F$94,MATCH(D88,'Curva Mestra'!$A$20:$A$94,0)),0) | F88: =ROUND(INDEX('Curva Mestra'!$C$20:$C$94,MATCH(D88,'Curva Mestra'!$A$20:$A$94,0))*INDEX($B$5:$B$8,MATCH(C88,$A$5:$A$8,0)),0) | G88: =ROUND(INDEX('Curva Mestra'!$D$20:$D$94,MATCH(D88,'Curva Mestra'!$A$20:$A$94,0))+INDEX($C$5:$C$8,MATCH(C88,$A$5:$A$8,0)),0) | H88: Não se afasta da forja ativa das ruínas. | I88: Golpe Incandescente | J88: Queimadura — só aparece perto de fogo/forja ativa. | K88: Nasceu literalmente dentro da Forja Ativa, marcado desde o primeiro choro. | L88: =IF(C88="Comum",ROUND(E88*1.3,0),"—") | M88: =IF(C88="Comum",ROUND(F88*1.15,0),"—") | N88: =IF(C88="Comum",G88+2,"—") | O88: =IF(C88="Comum",ROUND(E88*1.6,0),"—") | P88: =IF(C88="Comum",ROUND(F88*1.3,0),"—") | Q88: =IF(C88="Comum",G88+4,"—") | S88: =ROUND(3+0.6*D88+IF(C88="Comum",0,IF(C88="Elite",2,IF(C88="Boss",4,6))),0) | T88: Ouro + Marca de Nascença em Ferro + Pano Chamuscado da Forja | U88: Lentidão | V88: Condicional | W88: Ruínas da Antiga Forja — Forja Ativa, só com fogo aceso
A89: Ferro | B89: Zelote Ferreiro Menor | C89: Comum | D89: 10 | E89: =ROUND(INDEX('Curva Mestra'!$F$20:$F$94,MATCH(D89,'Curva Mestra'!$A$20:$A$94,0)),0) | F89: =ROUND(INDEX('Curva Mestra'!$C$20:$C$94,MATCH(D89,'Curva Mestra'!$A$20:$A$94,0))*INDEX($B$5:$B$8,MATCH(C89,$A$5:$A$8,0)),0) | G89: =ROUND(INDEX('Curva Mestra'!$D$20:$D$94,MATCH(D89,'Curva Mestra'!$A$20:$A$94,0))+INDEX($C$5:$C$8,MATCH(C89,$A$5:$A$8,0)),0) | H89: Aprendiz de ferreiro do culto. | I89: Bênção Fraca da Bigorna | J89: Cura 2 HP/turno em 1 aliado. | K89: Aprendiz do Zelote Ferreiro principal. | L89: =IF(C89="Comum",ROUND(E89*1.3,0),"—") | M89: =IF(C89="Comum",ROUND(F89*1.15,0),"—") | N89: =IF(C89="Comum",G89+2,"—") | O89: =IF(C89="Comum",ROUND(E89*1.6,0),"—") | P89: =IF(C89="Comum",ROUND(F89*1.3,0),"—") | Q89: =IF(C89="Comum",G89+4,"—") | S89: =ROUND(3+0.6*D89+IF(C89="Comum",0,IF(C89="Elite",2,IF(C89="Boss",4,6))),0) | T89: Ouro + Martelo Improvisado de Aprendiz + Avental Chamuscado | U89: Ignora Resistência Mágica | V89: Suporte | W89: Ruínas da Antiga Forja — Forja Ativa
A90: Ferro | B90: Golem de Sucata da Forja | C90: Comum | D90: 10 | E90: =ROUND(INDEX('Curva Mestra'!$F$20:$F$94,MATCH(D90,'Curva Mestra'!$A$20:$A$94,0)),0) | F90: =ROUND(INDEX('Curva Mestra'!$C$20:$C$94,MATCH(D90,'Curva Mestra'!$A$20:$A$94,0))*INDEX($B$5:$B$8,MATCH(C90,$A$5:$A$8,0)),0) | G90: =ROUND(INDEX('Curva Mestra'!$D$20:$D$94,MATCH(D90,'Curva Mestra'!$A$20:$A$94,0))+INDEX($C$5:$C$8,MATCH(C90,$A$5:$A$8,0)),0) | H90: Golem improvisado, feito de restos. | I90: Punho de Sucata Solta | J90: Nenhum efeito adicional — resistente. | K90: Montado às pressas com sucata da própria forja. | L90: =IF(C90="Comum",ROUND(E90*1.3,0),"—") | M90: =IF(C90="Comum",ROUND(F90*1.15,0),"—") | N90: =IF(C90="Comum",G90+2,"—") | O90: =IF(C90="Comum",ROUND(E90*1.6,0),"—") | P90: =IF(C90="Comum",ROUND(F90*1.3,0),"—") | Q90: =IF(C90="Comum",G90+4,"—") | S90: =ROUND(3+0.6*D90+IF(C90="Comum",0,IF(C90="Elite",2,IF(C90="Boss",4,6))),0) | T90: Placa de Sucata Reaproveitada + Engrenagem Torta da Forja | U90: Ignora Resistência Mágica | V90: Tanque | W90: Ruínas da Antiga Forja — Fundição
A91: Ferro | B91: Zelote de Ferro | C91: Comum | D91: 12 | E91: =ROUND(INDEX('Curva Mestra'!$F$20:$F$94,MATCH(D91,'Curva Mestra'!$A$20:$A$94,0)),0) | F91: =ROUND(INDEX('Curva Mestra'!$C$20:$C$94,MATCH(D91,'Curva Mestra'!$A$20:$A$94,0))*INDEX($B$5:$B$8,MATCH(C91,$A$5:$A$8,0)),0) | G91: =ROUND(INDEX('Curva Mestra'!$D$20:$D$94,MATCH(D91,'Curva Mestra'!$A$20:$A$94,0))+INDEX($C$5:$C$8,MATCH(C91,$A$5:$A$8,0)),0) | H91: Ligado ao Culto dos Primeiros Marcados, região de Ferro. | I91: Golpe do Devoto | J91: Sem efeito especial — ganha +1 de Ataque se lutar em grupo de 2+. | K91: Cultista que trocou a sucata improvisada por ferro de verdade — o culto está ficando mais forte na região, não mais fraco. | L91: =IF(C91="Comum",ROUND(E91*1.3,0),"—") | M91: =IF(C91="Comum",ROUND(F91*1.15,0),"—") | N91: =IF(C91="Comum",G91+2,"—") | O91: =IF(C91="Comum",ROUND(E91*1.6,0),"—") | P91: =IF(C91="Comum",ROUND(F91*1.3,0),"—") | Q91: =IF(C91="Comum",G91+4,"—") | R91: Zelotes na Ruína | S91: =ROUND(INDEX('Curva Mestra'!$D$20:$D$94,MATCH(D91,'Curva Mestra'!$A$20:$A$94,0))-IF(C91="Comum",9,IF(C91="Elite",6,IF(C91="Boss",4,3))),0) | T91: Ouro + Emblema do Culto do Ferro + Fragmento de Golem Corrompido (chance rara) | U91: Perde o bônus de grupo se isolado dos outros cultistas em combate. | V91: DPS | W91: Ruínas da Antiga Forja
A92: Ferro | B92: Fantasma da Guarda Caída | C92: Comum | D92: 13 | E92: =ROUND(INDEX('Curva Mestra'!$F$20:$F$94,MATCH(D92,'Curva Mestra'!$A$20:$A$94,0)),0) | F92: =ROUND(INDEX('Curva Mestra'!$C$20:$C$94,MATCH(D92,'Curva Mestra'!$A$20:$A$94,0))*INDEX($B$5:$B$8,MATCH(C92,$A$5:$A$8,0)),0) | G92: =ROUND(INDEX('Curva Mestra'!$D$20:$D$94,MATCH(D92,'Curva Mestra'!$A$20:$A$94,0))+INDEX($C$5:$C$8,MATCH(C92,$A$5:$A$8,0)),0) | H92: Ligado ao Culto dos Primeiros Marcados, região de Ferro. | I92: Ronda Eterna | J92: Ignora terreno difícil ao se mover — ainda "patrulha" como em vida. | K92: Um soldado raso que morreu defendendo a forja e nunca soube que a batalha acabou. Não é maligno — só não descansa. | L92: =IF(C92="Comum",ROUND(E92*1.3,0),"—") | M92: =IF(C92="Comum",ROUND(F92*1.15,0),"—") | N92: =IF(C92="Comum",G92+2,"—") | O92: =IF(C92="Comum",ROUND(E92*1.6,0),"—") | P92: =IF(C92="Comum",ROUND(F92*1.3,0),"—") | Q92: =IF(C92="Comum",G92+4,"—") | R92: O Fantasma Que Ainda Faz Ronda | S92: =ROUND(INDEX('Curva Mestra'!$D$20:$D$94,MATCH(D92,'Curva Mestra'!$A$20:$A$94,0))-IF(C92="Comum",9,IF(C92="Elite",6,IF(C92="Boss",4,3))),0) | T92: Ouro + Resíduo Espectral de Guarda Caída + Fragmento de Golem Corrompido (chance rara) | U92: Vulnerável a Prata — armas de Prata ignoram 2 de Defesa a mais nele. | V92: DPS | W92: Ruínas da Antiga Forja
A93: Ferro | B93: Guarda de Ferro Corrompido | C93: Elite | D93: 10 | E93: =ROUND(INDEX('Curva Mestra'!$G$20:$G$94,MATCH(D93,'Curva Mestra'!$A$20:$A$94,0)),0) | F93: =ROUND(INDEX('Curva Mestra'!$C$20:$C$94,MATCH(D93,'Curva Mestra'!$A$20:$A$94,0))*INDEX($B$5:$B$8,MATCH(C93,$A$5:$A$8,0)),0) | G93: =ROUND(INDEX('Curva Mestra'!$D$20:$D$94,MATCH(D93,'Curva Mestra'!$A$20:$A$94,0))+INDEX($C$5:$C$8,MATCH(C93,$A$5:$A$8,0)),0) | H93: Encontro dificil dentro do tier Ferro | I93: Golpe da Guarda Caída | J93: Ignora 1 ponto de Defesa do alvo. | K93: Foi capitão da guarda de fronteira antes do colapso da forja — sua espada gêmea é hoje a relíquia "A Lâmina da Guarda Quebrada". | L93: =IF(C93="Comum",ROUND(E93*1.3,0),"—") | M93: =IF(C93="Comum",ROUND(F93*1.15,0),"—") | N93: =IF(C93="Comum",G93+2,"—") | O93: =IF(C93="Comum",ROUND(E93*1.6,0),"—") | P93: =IF(C93="Comum",ROUND(F93*1.3,0),"—") | Q93: =IF(C93="Comum",G93+4,"—") | R93: O Cofre do Capitão | S93: =ROUND(INDEX('Curva Mestra'!$D$20:$D$94,MATCH(D93,'Curva Mestra'!$A$20:$A$94,0))-IF(C93="Comum",9,IF(C93="Elite",6,IF(C93="Boss",4,3))),0) | T93: Fragmento de Guarda de Ferro Corrompido + Ouro + Fragmento de Golem Corrompido (chance baixa) | U93: Sem fraqueza óbvia — precisa de Knowledge alto pra descobrir algo específico. | V93: DPS | W93: Ruínas da Antiga Forja
A94: Ferro | B94: O Executor da Forja Velha | C94: Elite | D94: 11 | E94: =ROUND(INDEX('Curva Mestra'!$G$20:$G$94,MATCH(D94,'Curva Mestra'!$A$20:$A$94,0)),0) | F94: =ROUND(INDEX('Curva Mestra'!$C$20:$C$94,MATCH(D94,'Curva Mestra'!$A$20:$A$94,0))*INDEX($B$5:$B$8,MATCH(C94,$A$5:$A$8,0)),0) | G94: =ROUND(INDEX('Curva Mestra'!$D$20:$D$94,MATCH(D94,'Curva Mestra'!$A$20:$A$94,0))+INDEX($C$5:$C$8,MATCH(C94,$A$5:$A$8,0)),0) | H94: Encontro opcional dentro do tier Ferro, na câmara secreta da forja antiga. | I94: Bigorna em Chamas | J94: No primeiro turno do combate causa dano de fogo em dobro. | K94: Autômato erguido pelos últimos ferreiros da vila pra proteger a forja — nunca recebeu ordem de parar, mesmo sem ninguém pra proteger. | L94: =IF(C94="Comum",ROUND(E94*1.3,0),"—") | M94: =IF(C94="Comum",ROUND(F94*1.15,0),"—") | N94: =IF(C94="Comum",G94+2,"—") | O94: =IF(C94="Comum",ROUND(E94*1.6,0),"—") | P94: =IF(C94="Comum",ROUND(F94*1.3,0),"—") | Q94: =IF(C94="Comum",G94+4,"—") | R94: O Segredo do Executor | S94: =ROUND(INDEX('Curva Mestra'!$D$20:$D$94,MATCH(D94,'Curva Mestra'!$A$20:$A$94,0))-IF(C94="Comum",9,IF(C94="Elite",6,IF(C94="Boss",4,3))),0) | T94: Fragmento de O Executor da Forja Velha + Ouro + Fragmento de Golem Corrompido (chance baixa) | U94: Vulnerável a Gelo/Água — queimadura recebida dura metade do tempo. | V94: DPS | W94: Ruínas da Antiga Forja
A95: Ferro | B95: Esqueleto Comandante | C95: Elite | D95: 11 | E95: =ROUND(INDEX('Curva Mestra'!$G$20:$G$94,MATCH(D95,'Curva Mestra'!$A$20:$A$94,0)),0) | F95: =ROUND(INDEX('Curva Mestra'!$C$20:$C$94,MATCH(D95,'Curva Mestra'!$A$20:$A$94,0))*INDEX($B$5:$B$8,MATCH(C95,$A$5:$A$8,0)),0) | G95: =ROUND(INDEX('Curva Mestra'!$D$20:$D$94,MATCH(D95,'Curva Mestra'!$A$20:$A$94,0))+INDEX($C$5:$C$8,MATCH(C95,$A$5:$A$8,0)),0) | H95: Comanda os demais esqueletos no salão dos comandantes. | I95: Grito de Comando | J95: +10% de chance de acerto pra todos os Esqueletos vivos no combate. | K95: Comandava a guarda em vida. A marca não apagou o hábito. | L95: =IF(C95="Comum",ROUND(E95*1.3,0),"—") | M95: =IF(C95="Comum",ROUND(F95*1.15,0),"—") | N95: =IF(C95="Comum",G95+2,"—") | O95: =IF(C95="Comum",ROUND(E95*1.6,0),"—") | P95: =IF(C95="Comum",ROUND(F95*1.3,0),"—") | Q95: =IF(C95="Comum",G95+4,"—") | S95: =ROUND(3+0.6*D95+IF(C95="Comum",0,IF(C95="Elite",2,IF(C95="Boss",4,6))),0) | T95: Ouro + Fragmento de Esqueleto Comandante + Estandarte Partido de Comando + Fragmento de Golem Corrompido (chance baixa) | U95: Ignora Resistência Mágica | V95: Suporte/Buffer | W95: Ruínas da Antiga Forja — Salão dos Comandantes
A96: Ferro | B96: Zelote Ferreiro | C96: Elite | D96: 11 | E96: =ROUND(INDEX('Curva Mestra'!$G$20:$G$94,MATCH(D96,'Curva Mestra'!$A$20:$A$94,0)),0) | F96: =ROUND(INDEX('Curva Mestra'!$C$20:$C$94,MATCH(D96,'Curva Mestra'!$A$20:$A$94,0))*INDEX($B$5:$B$8,MATCH(C96,$A$5:$A$8,0)),0) | G96: =ROUND(INDEX('Curva Mestra'!$D$20:$D$94,MATCH(D96,'Curva Mestra'!$A$20:$A$94,0))+INDEX($C$5:$C$8,MATCH(C96,$A$5:$A$8,0)),0) | H96: Trabalha na forja ainda ativa dentro das ruínas. | I96: Bênção da Bigorna | J96: Cura 3 HP/turno + concede Ignora Defesa a 1 aliado por combate. | K96: Forja armas "abençoadas" pela Mão para o Culto do Ferro. | L96: =IF(C96="Comum",ROUND(E96*1.3,0),"—") | M96: =IF(C96="Comum",ROUND(F96*1.15,0),"—") | N96: =IF(C96="Comum",G96+2,"—") | O96: =IF(C96="Comum",ROUND(E96*1.6,0),"—") | P96: =IF(C96="Comum",ROUND(F96*1.3,0),"—") | Q96: =IF(C96="Comum",G96+4,"—") | S96: =ROUND(3+0.6*D96+IF(C96="Comum",0,IF(C96="Elite",2,IF(C96="Boss",4,6))),0) | T96: Ouro + Fragmento de Zelote Ferreiro + Martelo Abençoado pela Mão + Fragmento de Golem Corrompido (chance baixa) | U96: Ignora Resistência Mágica | V96: Suporte | W96: Ruínas da Antiga Forja — Forja Ativa | Z96: A Guilda dos Picaretas Negros compra ferro dele, mesmo sabendo o que é.
A97: Ferro | B97: Bigorna Viva | C97: Elite | D97: 11 | E97: =ROUND(INDEX('Curva Mestra'!$G$20:$G$94,MATCH(D97,'Curva Mestra'!$A$20:$A$94,0)),0) | F97: =ROUND(INDEX('Curva Mestra'!$C$20:$C$94,MATCH(D97,'Curva Mestra'!$A$20:$A$94,0))*INDEX($B$5:$B$8,MATCH(C97,$A$5:$A$8,0)),0) | G97: =ROUND(INDEX('Curva Mestra'!$D$20:$D$94,MATCH(D97,'Curva Mestra'!$A$20:$A$94,0))+INDEX($C$5:$C$8,MATCH(C97,$A$5:$A$8,0)),0) | H97: Disfarçada entre as ferramentas da forja ativa. | I97: Golpe da Bigorna | J97: Ignora Defesa (alto) + jogador perde 1 turno de surpresa. | K97: Cultistas armam bigornas-armadilha pros que saqueiam sem permissão. | L97: =IF(C97="Comum",ROUND(E97*1.3,0),"—") | M97: =IF(C97="Comum",ROUND(F97*1.15,0),"—") | N97: =IF(C97="Comum",G97+2,"—") | O97: =IF(C97="Comum",ROUND(E97*1.6,0),"—") | P97: =IF(C97="Comum",ROUND(F97*1.3,0),"—") | Q97: =IF(C97="Comum",G97+4,"—") | S97: =ROUND(3+0.6*D97+IF(C97="Comum",0,IF(C97="Elite",2,IF(C97="Boss",4,6))),0) | T97: Ouro + Veio de Ferro Negro (chance alta, x2) + Fragmento de Bigorna Armadilhada | U97: Atordoamento | V97: Mímico | W97: Ruínas da Antiga Forja — Forja Ativa, 5% ao interagir | AA97: Veio de Ferro Negro x2
A98: Ferro | B98: Espírito Fugidio do Minério | C98: Elite | D98: 11 | E98: =ROUND(INDEX('Curva Mestra'!$G$20:$G$94,MATCH(D98,'Curva Mestra'!$A$20:$A$94,0)),0) | F98: =ROUND(INDEX('Curva Mestra'!$C$20:$C$94,MATCH(D98,'Curva Mestra'!$A$20:$A$94,0))*INDEX($B$5:$B$8,MATCH(C98,$A$5:$A$8,0)),0) | G98: =ROUND(INDEX('Curva Mestra'!$D$20:$D$94,MATCH(D98,'Curva Mestra'!$A$20:$A$94,0))+INDEX($C$5:$C$8,MATCH(C98,$A$5:$A$8,0)),0) | H98: Raramente visto tentando escapar das ruínas. | I98: Fuga Metálica | J98: Não causa dano — foge no turno 3. | K98: Alma presa num veio raro, tenta escapar de quem a encontra. | L98: =IF(C98="Comum",ROUND(E98*1.3,0),"—") | M98: =IF(C98="Comum",ROUND(F98*1.15,0),"—") | N98: =IF(C98="Comum",G98+2,"—") | O98: =IF(C98="Comum",ROUND(E98*1.6,0),"—") | P98: =IF(C98="Comum",ROUND(F98*1.3,0),"—") | Q98: =IF(C98="Comum",G98+4,"—") | S98: =ROUND(3+0.6*D98+IF(C98="Comum",0,IF(C98="Elite",2,IF(C98="Boss",4,6))),0) | T98: Ouro + Resíduo Etéreo do Espírito Fugidio | U98: Lentidão | V98: Superloot/Evasivo | W98: Ruínas da Antiga Forja, spawn raro (2%) | AA98: Veio de Prata Pálida (material de Tier 4)
A99: Ferro | B99: Capitão Vessel, o Que Não Se Rendeu | C99: Elite | D99: 12 | E99: =ROUND(INDEX('Curva Mestra'!$G$20:$G$94,MATCH(D99,'Curva Mestra'!$A$20:$A$94,0)),0) | F99: =ROUND(INDEX('Curva Mestra'!$C$20:$C$94,MATCH(D99,'Curva Mestra'!$A$20:$A$94,0))*INDEX($B$5:$B$8,MATCH(C99,$A$5:$A$8,0)),0) | G99: =ROUND(INDEX('Curva Mestra'!$D$20:$D$94,MATCH(D99,'Curva Mestra'!$A$20:$A$94,0))+INDEX($C$5:$C$8,MATCH(C99,$A$5:$A$8,0)),0) | H99: Aparece raramente no salão dos comandantes, sempre postado. | I99: Última Ordem | J99: Ignora Defesa + concede Atordoamento (15%) a 1 aliado por turno. | K99: Comandava a forja quando ela caiu. Ainda acha que está defendendo algo. | L99: =IF(C99="Comum",ROUND(E99*1.3,0),"—") | M99: =IF(C99="Comum",ROUND(F99*1.15,0),"—") | N99: =IF(C99="Comum",G99+2,"—") | O99: =IF(C99="Comum",ROUND(E99*1.6,0),"—") | P99: =IF(C99="Comum",ROUND(F99*1.3,0),"—") | Q99: =IF(C99="Comum",G99+4,"—") | S99: =ROUND(3+0.6*D99+IF(C99="Comum",0,IF(C99="Elite",2,IF(C99="Boss",4,6))),0) | T99: Ouro + Fragmento do Capitão Que Não Se Rendeu + Fragmento de Golem Corrompido (chance baixa) | U99: Ignora Resistência Mágica | V99: Nomeado / Mini-Boss | W99: Ruínas da Antiga Forja — Salão dos Comandantes, spawn raro (4%) | X99: A 30% de HP, para de lutar e "liberta o posto" se o jogador recusar continuar atacando — dá Título. | AA99: Brasão do Capitão Que Não Se Rendeu (se derrotado em vez de poupado) [ver Artefatos e Relíquias]
A100: Ferro | B100: Golem Fragmentado | C100: Elite | D100: 12 | E100: =ROUND(INDEX('Curva Mestra'!$G$20:$G$94,MATCH(D100,'Curva Mestra'!$A$20:$A$94,0)),0) | F100: =ROUND(INDEX('Curva Mestra'!$C$20:$C$94,MATCH(D100,'Curva Mestra'!$A$20:$A$94,0))*INDEX($B$5:$B$8,MATCH(C100,$A$5:$A$8,0)),0) | G100: =ROUND(INDEX('Curva Mestra'!$D$20:$D$94,MATCH(D100,'Curva Mestra'!$A$20:$A$94,0))+INDEX($C$5:$C$8,MATCH(C100,$A$5:$A$8,0)),0) | H100: Instável, permanece na fundição das ruínas. | I100: Colapso Controlado | J100: Ao ser destruído, libera 2 Golens Menores de Ferro com 50% HP. | K100: Um golem grande demais pra Infecção controlar direito — racha, não morre limpo. | L100: =IF(C100="Comum",ROUND(E100*1.3,0),"—") | M100: =IF(C100="Comum",ROUND(F100*1.15,0),"—") | N100: =IF(C100="Comum",G100+2,"—") | O100: =IF(C100="Comum",ROUND(E100*1.6,0),"—") | P100: =IF(C100="Comum",ROUND(F100*1.3,0),"—") | Q100: =IF(C100="Comum",G100+4,"—") | S100: =ROUND(3+0.6*D100+IF(C100="Comum",0,IF(C100="Elite",2,IF(C100="Boss",4,6))),0) | T100: Ouro + Fragmento de Golem Fragmentado + Núcleo Rachado + Fragmento de Golem Corrompido (chance baixa) | U100: Ignora Resistência Mágica | V100: Tanque/Invocador | W100: Ruínas da Antiga Forja — Fundição | X100: Ao chegar a 0 HP, libera 2 Golens Menores em vez de morrer.
A101: Ferro | B101: Zelote Superior do Ferro | C101: Elite | D101: 13 | E101: =ROUND(INDEX('Curva Mestra'!$G$20:$G$94,MATCH(D101,'Curva Mestra'!$A$20:$A$94,0)),0) | F101: =ROUND(INDEX('Curva Mestra'!$C$20:$C$94,MATCH(D101,'Curva Mestra'!$A$20:$A$94,0))*INDEX($B$5:$B$8,MATCH(C101,$A$5:$A$8,0)),0) | G101: =ROUND(INDEX('Curva Mestra'!$D$20:$D$94,MATCH(D101,'Curva Mestra'!$A$20:$A$94,0))+INDEX($C$5:$C$8,MATCH(C101,$A$5:$A$8,0)),0) | H101: Ligado ao Culto dos Primeiros Marcados, região de Ferro. | I101: Comando do Ferro | J101: Concede +1 de Ataque a todos os Zelotes de Ferro no mesmo combate. Também aplica: Ignora 1 ponto de Defesa do alvo. | K101: Lidera o contrabando de armas de ferro pro culto na região — captura viva revela pistas sobre a origem de tudo. | L101: =IF(C101="Comum",ROUND(E101*1.3,0),"—") | M101: =IF(C101="Comum",ROUND(F101*1.15,0),"—") | N101: =IF(C101="Comum",G101+2,"—") | O101: =IF(C101="Comum",ROUND(E101*1.6,0),"—") | P101: =IF(C101="Comum",ROUND(F101*1.3,0),"—") | Q101: =IF(C101="Comum",G101+4,"—") | R101: O Zelote Arrependido | S101: =ROUND(INDEX('Curva Mestra'!$D$20:$D$94,MATCH(D101,'Curva Mestra'!$A$20:$A$94,0))-IF(C101="Comum",9,IF(C101="Elite",6,IF(C101="Boss",4,3))),0) | T101: Relicário de Zelote Superior do Ferro + Ouro + Fragmento de Golem Corrompido (chance baixa) | U101: Perde o bônus de grupo se isolado dos outros cultistas em combate. | V101: DPS | W101: Ruínas da Antiga Forja
A102: Ferro | B102: Golem de Sucata | C102: Boss | D102: 13 | E102: =ROUND(INDEX('Curva Mestra'!$H$20:$H$94,MATCH(D102,'Curva Mestra'!$A$20:$A$94,0)),0) | F102: =ROUND(INDEX('Curva Mestra'!$C$20:$C$94,MATCH(D102,'Curva Mestra'!$A$20:$A$94,0))*INDEX($B$5:$B$8,MATCH(C102,$A$5:$A$8,0)),0) | G102: =ROUND(INDEX('Curva Mestra'!$D$20:$D$94,MATCH(D102,'Curva Mestra'!$A$20:$A$94,0))+INDEX($C$5:$C$8,MATCH(C102,$A$5:$A$8,0)),0) | H102: Chefe / marco final do tier Ferro | I102: Esmagamento de Detritos | J102: No primeiro turno de combate, causa dano em dobro. Também aplica: Ignora 1 ponto de Defesa do alvo. | K102: Última linha de defesa da forja, erguida às pressas quando os cultistas começaram a fortificar as ruínas. | L102: =IF(C102="Comum",ROUND(E102*1.3,0),"—") | M102: =IF(C102="Comum",ROUND(F102*1.15,0),"—") | N102: =IF(C102="Comum",G102+2,"—") | O102: =IF(C102="Comum",ROUND(E102*1.6,0),"—") | P102: =IF(C102="Comum",ROUND(F102*1.3,0),"—") | Q102: =IF(C102="Comum",G102+4,"—") | R102: O Golem da Forja | S102: =ROUND(INDEX('Curva Mestra'!$D$20:$D$94,MATCH(D102,'Curva Mestra'!$A$20:$A$94,0))-IF(C102="Comum",9,IF(C102="Elite",6,IF(C102="Boss",4,3))),0) | T102: Núcleo de Golem de Sucata + Essência de Golem de Sucata + Ouro + Fragmento de Golem Corrompido (chance baixa) | U102: Vulnerável a Atordoamento — travas mecânicas emperram com o dobro de chance. | V102: DPS | W102: Ruínas da Antiga Forja
A103: Ferro | B103: O Primeiro Marcado | C103: Boss | D103: 15 | E103: =ROUND(INDEX('Curva Mestra'!$H$20:$H$94,MATCH(D103,'Curva Mestra'!$A$20:$A$94,0)),0) | F103: =ROUND(INDEX('Curva Mestra'!$C$20:$C$94,MATCH(D103,'Curva Mestra'!$A$20:$A$94,0))*INDEX($B$5:$B$8,MATCH(C103,$A$5:$A$8,0)),0) | G103: =ROUND(INDEX('Curva Mestra'!$D$20:$D$94,MATCH(D103,'Curva Mestra'!$A$20:$A$94,0))+INDEX($C$5:$C$8,MATCH(C103,$A$5:$A$8,0)),0) | H103: Ligado ao Culto dos Primeiros Marcados, região de Ferro. | I103: Toque Original | J103: Ao acertar, marca o alvo: próximos ataques de qualquer cultista contra ele ganham +2 de Ataque. Também aplica: Ignora 1 ponto de Defesa do alvo. | K103: A primeira pessoa da região tocada pela influência da Mão Carmesim — hoje pouco mais que fé pura e vontade cega. Derrotá-lo fecha o Ato I. | L103: =IF(C103="Comum",ROUND(E103*1.3,0),"—") | M103: =IF(C103="Comum",ROUND(F103*1.15,0),"—") | N103: =IF(C103="Comum",G103+2,"—") | O103: =IF(C103="Comum",ROUND(E103*1.6,0),"—") | P103: =IF(C103="Comum",ROUND(F103*1.3,0),"—") | Q103: =IF(C103="Comum",G103+4,"—") | R103: O Primeiro Marcado (fecha o Ato I) | S103: =ROUND(INDEX('Curva Mestra'!$D$20:$D$94,MATCH(D103,'Curva Mestra'!$A$20:$A$94,0))-IF(C103="Comum",9,IF(C103="Elite",6,IF(C103="Boss",4,3))),0) | T103: Fragmento de O Primeiro Marcado + Essência de O Primeiro Marcado + Ouro + Fragmento de Golem Corrompido (chance baixa) | U103: Sem fraqueza óbvia — precisa de Knowledge alto pra descobrir algo específico. | V103: DPS | W103: Ruínas da Antiga Forja
...

Sheet Economia
A1: Economia de Ouro
A2: Preco sobe mais rapido que o ouro ganho, de proposito - isso evita ficar rico facil.
A4: Parametro | B4: Valor | C4: O que controla
A5: Ouro_por_HP_Comum | B5: 0.3 | C5: Ouro dropado por monstro comum = HP dele x este valor
A6: Mult_Ouro_Elite | B6: 2.5 | C6: Ouro de elite = ouro de comum x este valor
A7: Mult_Ouro_Boss | B7: 8 | C7: Ouro de boss = ouro de comum x este valor
A8: Expoente_Imposto_Regional | B8: 1.3 | C8: Preco = Dano do item ^ este expoente x fator - usado so pra TAXA/IMPOSTO de cidades gananciosas, nao pro preco base
A9: Fator_Imposto_Regional | B9: 4 | C9: Multiplicador geral de preco
A10: Monstros_por_Sessao | B10: 8 | C10: Quantos monstros comuns o grupo mata, em media, por sessao
A13: Tier | B13: Nivel Ref. | C13: Ouro/Monstro Comum | D13: Ouro/Elite | E13: Ouro/Boss | F13: Preco Item Comum | G13: Preco Item Raro | H13: Preco Item Lendario | I13: Sessoes p/ Pagar Comum
A14: Sucata Enferrujada | B14: =Tiers!E9 | C14: =ROUND(INDEX('Curva Mestra'!$F$20:$F$94,MATCH(B14,'Curva Mestra'!$A$20:$A$94,0))*$B$5,0) | D14: =ROUND(C14*$B$6,0) | E14: =ROUND(C14*$B$7,0) | F14: =ROUND((Tiers!G9^$B$8)*$B$9,0) | G14: =ROUND((Tiers!H9^$B$8)*$B$9,0) | H14: =ROUND((Tiers!I9^$B$8)*$B$9,0) | I14: =ROUND(F14/(C14*$B$10),1)
A15: Bronze | B15: =Tiers!E10 | C15: =ROUND(INDEX('Curva Mestra'!$F$20:$F$94,MATCH(B15,'Curva Mestra'!$A$20:$A$94,0))*$B$5,0) | D15: =ROUND(C15*$B$6,0) | E15: =ROUND(C15*$B$7,0) | F15: =ROUND((Tiers!G10^$B$8)*$B$9,0) | G15: =ROUND((Tiers!H10^$B$8)*$B$9,0) | H15: =ROUND((Tiers!I10^$B$8)*$B$9,0) | I15: =ROUND(F15/(C15*$B$10),1)
A16: Ferro | B16: =Tiers!E11 | C16: =ROUND(INDEX('Curva Mestra'!$F$20:$F$94,MATCH(B16,'Curva Mestra'!$A$20:$A$94,0))*$B$5,0) | D16: =ROUND(C16*$B$6,0) | E16: =ROUND(C16*$B$7,0) | F16: =ROUND((Tiers!G11^$B$8)*$B$9,0) | G16: =ROUND((Tiers!H11^$B$8)*$B$9,0) | H16: =ROUND((Tiers!I11^$B$8)*$B$9,0) | I16: =ROUND(F16/(C16*$B$10),1)
A17: Prata | B17: =Tiers!E12 | C17: =ROUND(INDEX('Curva Mestra'!$F$20:$F$94,MATCH(B17,'Curva Mestra'!$A$20:$A$94,0))*$B$5,0) | D17: =ROUND(C17*$B$6,0) | E17: =ROUND(C17*$B$7,0) | F17: =ROUND((Tiers!G12^$B$8)*$B$9,0) | G17: =ROUND((Tiers!H12^$B$8)*$B$9,0) | H17: =ROUND((Tiers!I12^$B$8)*$B$9,0) | I17: =ROUND(F17/(C17*$B$10),1)
A18: Aco Elfico | B18: =Tiers!E13 | C18: =ROUND(INDEX('Curva Mestra'!$F$20:$F$94,MATCH(B18,'Curva Mestra'!$A$20:$A$94,0))*$B$5,0) | D18: =ROUND(C18*$B$6,0) | E18: =ROUND(C18*$B$7,0) | F18: =ROUND((Tiers!G13^$B$8)*$B$9,0) | G18: =ROUND((Tiers!H13^$B$8)*$B$9,0) | H18: =ROUND((Tiers!I13^$B$8)*$B$9,0) | I18: =ROUND(F18/(C18*$B$10),1)
A19: Mecanismo Anao | B19: =Tiers!E14 | C19: =ROUND(INDEX('Curva Mestra'!$F$20:$F$94,MATCH(B19,'Curva Mestra'!$A$20:$A$94,0))*$B$5,0) | D19: =ROUND(C19*$B$6,0) | E19: =ROUND(C19*$B$7,0) | F19: =ROUND((Tiers!G14^$B$8)*$B$9,0) | G19: =ROUND((Tiers!H14^$B$8)*$B$9,0) | H19: =ROUND((Tiers!I14^$B$8)*$B$9,0) | I19: =ROUND(F19/(C19*$B$10),1)
A20: Vidro Vulcanico | B20: =Tiers!E15 | C20: =ROUND(INDEX('Curva Mestra'!$F$20:$F$94,MATCH(B20,'Curva Mestra'!$A$20:$A$94,0))*$B$5,0) | D20: =ROUND(C20*$B$6,0) | E20: =ROUND(C20*$B$7,0) | F20: =ROUND((Tiers!G15^$B$8)*$B$9,0) | G20: =ROUND((Tiers!H15^$B$8)*$B$9,0) | H20: =ROUND((Tiers!I15^$B$8)*$B$9,0) | I20: =ROUND(F20/(C20*$B$10),1)
A21: Ferro Orquico | B21: =Tiers!E16 | C21: =ROUND(INDEX('Curva Mestra'!$F$20:$F$94,MATCH(B21,'Curva Mestra'!$A$20:$A$94,0))*$B$5,0) | D21: =ROUND(C21*$B$6,0) | E21: =ROUND(C21*$B$7,0) | F21: =ROUND((Tiers!G16^$B$8)*$B$9,0) | G21: =ROUND((Tiers!H16^$B$8)*$B$9,0) | H21: =ROUND((Tiers!I16^$B$8)*$B$9,0) | I21: =ROUND(F21/(C21*$B$10),1)
A22: Mithril | B22: =Tiers!E17 | C22: =ROUND(INDEX('Curva Mestra'!$F$20:$F$94,MATCH(B22,'Curva Mestra'!$A$20:$A$94,0))*$B$5,0) | D22: =ROUND(C22*$B$6,0) | E22: =ROUND(C22*$B$7,0) | F22: =ROUND((Tiers!G17^$B$8)*$B$9,0) | G22: =ROUND((Tiers!H17^$B$8)*$B$9,0) | H22: =ROUND((Tiers!I17^$B$8)*$B$9,0) | I22: =ROUND(F22/(C22*$B$10),1)
A23: Ebano | B23: =Tiers!E18 | C23: =ROUND(INDEX('Curva Mestra'!$F$20:$F$94,MATCH(B23,'Curva Mestra'!$A$20:$A$94,0))*$B$5,0) | D23: =ROUND(C23*$B$6,0) | E23: =ROUND(C23*$B$7,0) | F23: =ROUND((Tiers!G18^$B$8)*$B$9,0) | G23: =ROUND((Tiers!H18^$B$8)*$B$9,0) | H23: =ROUND((Tiers!I18^$B$8)*$B$9,0) | I23: =ROUND(F23/(C23*$B$10),1)
A24: Adamantina | B24: =Tiers!E19 | C24: =ROUND(INDEX('Curva Mestra'!$F$20:$F$94,MATCH(B24,'Curva Mestra'!$A$20:$A$94,0))*$B$5,0) | D24: =ROUND(C24*$B$6,0) | E24: =ROUND(C24*$B$7,0) | F24: =ROUND((Tiers!G19^$B$8)*$B$9,0) | G24: =ROUND((Tiers!H19^$B$8)*$B$9,0) | H24: =ROUND((Tiers!I19^$B$8)*$B$9,0) | I24: =ROUND(F24/(C24*$B$10),1)
A25: Osso de Dragao | B25: =Tiers!E20 | C25: =ROUND(INDEX('Curva Mestra'!$F$20:$F$94,MATCH(B25,'Curva Mestra'!$A$20:$A$94,0))*$B$5,0) | D25: =ROUND(C25*$B$6,0) | E25: =ROUND(C25*$B$7,0) | F25: =ROUND((Tiers!G20^$B$8)*$B$9,0) | G25: =ROUND((Tiers!H20^$B$8)*$B$9,0) | H25: =ROUND((Tiers!I20^$B$8)*$B$9,0) | I25: =ROUND(F25/(C25*$B$10),1)
... A27: Estelar / Cosmico | B27: =Tiers!E22 | C27: =ROUND(INDEX('Curva Mestra'!$F$20:$F$94,MATCH(B27,'Curva Mestra'!$A$20:$A$94,0))*$B$5,0) | D27: =ROUND(C27*$B$6,0) | E27: =ROUND(C27*$B$7,0) | F27: =ROUND((Tiers!G22^$B$8)*$B$9,0) | G27: =ROUND((Tiers!H22^$B$8)*$B$9,0) | H27: =ROUND((Tiers!I22^$B$8)*$B$9,0) | I27: =ROUND(F27/(C27*$B$10),1)
A30: Preço de Compra e Venda (fórmula oficial)
A31: Preço de Compra = Preço de Venda (Armas!L/M ou Armaduras!L/M) x 1,5
A32: Preço de Venda ao Mercador = Preço de Compra x 40%
A33: Resultado: 1 arma Comum do seu tier atual custa ~1 sessão inteira de grind (8 monstros comuns), em todos os 14 tiers.
A34: Lendário nunca é vendido em loja — só via loot ou recompensa de missão (regra já existente).
A35: - Impostos ou pedagios em certas regioes (dá sabor de mundo vivo)

Sheet Missoes
A1: Missoes
A2: Uma missao principal por tier, recompensas calculadas a partir de Economia e Curva Mestra.
A4: Tipos de missao (framework):
A5: - Principal de Tier: fecha o tier e libera o proximo (as 14 abaixo). Uma por tier.
A6: - Secundaria de Combate: matar X monstros comuns/elite. Recompensa = 25% da Principal do mesmo tier.
A7: - Secundaria de Exploracao/Coleta: achar item/local. Recompensa = 20% da Principal do mesmo tier.
A8: - Secundaria Social/NPC: negociar, escoltar, investigar. Recompensa = 15% da Principal + reputacao (nao numerico).
A10: Parametro | B10: Valor | C10: O que controla
A11: Mult_Ouro_Missao_Principal | B11: 3 | C11: Recompensa de ouro da missao principal = Ouro/Boss do tier x este valor
A12: Mult_XP_Missao_Principal | B12: 2 | C12: Recompensa de XP da missao principal = XP do nivel de ref x fator Boss x este valor
A15: Tier | B15: Nome da Missao | C15: Nivel Sugerido | D15: Objetivo | E15: Recompensa Ouro | F15: Recompensa XP | G15: Recompensa Item
A16: Sucata Enferrujada | B16: A Estrada Insegura | C16: =Tiers!E9 | D16: Limpe a estrada de bandidos e javalis que assombram os arredores da vila inicial. | E16: =ROUND(Economia!E14*$B$11,0) | F16: =ROUND(INDEX('Curva Mestra'!$J$20:$J$94,MATCH(C16,'Curva Mestra'!$A$20:$A$94,0))*Bestiario!$D$7*$B$12,0) | G16: ="1 item Raro ou Lendario do tier "&A16
A17: Bronze | B17: A Mina Sufocada | C17: =Tiers!E10 | D17: Ajude os mineradores a reabrir a mina de bronze, infestada por vermes sulfurosos e pela colônia de aranhas — e descubra por que o Barão Grimm nunca chamou ajuda antes. | E17: =ROUND(Economia!E15*$B$11,0) | F17: =ROUND(INDEX('Curva Mestra'!$J$20:$J$94,MATCH(C17,'Curva Mestra'!$A$20:$A$94,0))*Bestiario!$D$7*$B$12,0) | G17: ="1 item Raro ou Lendario do tier "&A17
A18: Ferro | B18: O Golem da Forja | C18: =Tiers!E11 | D18: Repare a forja da vila derrotando o Golem de Sucata que a guarda. | E18: =ROUND(Economia!E16*$B$11,0) | F18: =ROUND(INDEX('Curva Mestra'!$J$20:$J$94,MATCH(C18,'Curva Mestra'!$A$20:$A$94,0))*Bestiario!$D$7*$B$12,0) | G18: ="1 item Raro ou Lendario do tier "&A18
A19: Prata | B19: O Expurgo da Cripta | C19: =Tiers!E12 | D19: Purifique as criptas tomadas pela Fraternidade dos Sem-Voz, encarando O Ceifador do Silêncio no fim. | E19: =ROUND(Economia!E17*$B$11,0) | F19: =ROUND(INDEX('Curva Mestra'!$J$20:$J$94,MATCH(C19,'Curva Mestra'!$A$20:$A$94,0))*Bestiario!$D$7*$B$12,0) | G19: ="1 item Raro ou Lendario do tier "&A19
A20: Aco Elfico | B20: Ecos da Ultima Elfa | C20: =Tiers!E13 | D20: Negocie ou invada as ruínas élficas guardadas pelo Espírito da Última Elfa, enquanto a Ordem do Silêncio Eterno se move nas sombras. | E20: =ROUND(Economia!E18*$B$11,0) | F20: =ROUND(INDEX('Curva Mestra'!$J$20:$J$94,MATCH(C20,'Curva Mestra'!$A$20:$A$94,0))*Bestiario!$D$7*$B$12,0) | G20: ="1 item Raro ou Lendario do tier "&A20
A21: Mecanismo Anao | B21: O Nucleo Silencioso | C21: =Tiers!E14 | D21: Desative o Núcleo Mecânico Ancestral antes que a Câmara Mecânica Anã desmorone sobre o Clã Martelo de Vapor — fecha o Ato II. | E21: =ROUND(Economia!E19*$B$11,0) | F21: =ROUND(INDEX('Curva Mestra'!$J$20:$J$94,MATCH(C21,'Curva Mestra'!$A$20:$A$94,0))*Bestiario!$D$7*$B$12,0) | G21: ="1 item Raro ou Lendario do tier "&A21
A22: Vidro Vulcanico | B22: O Guardiao da Fenda Ativa | C22: =Tiers!E15 | D22: Contenha o Guardião da Fenda Ativa enquanto os Zelotes da Mão Escarlate se preparam pra "coroar" o Rei sem corpo. | E22: =ROUND(Economia!E20*$B$11,0) | F22: =ROUND(INDEX('Curva Mestra'!$J$20:$J$94,MATCH(C22,'Curva Mestra'!$A$20:$A$94,0))*Bestiario!$D$7*$B$12,0) | G22: ="1 item Raro ou Lendario do tier "&A22
A23: Ferro Orquico | B23: A Guerra do Bando Orc | C23: =Tiers!E16 | D23: Ajude Malkor, o orc renegado, contra o Chefe do Bando que aceitou o sangue da Mão Carmesim pra ganhar força artificial. | E23: =ROUND(Economia!E21*$B$11,0) | F23: =ROUND(INDEX('Curva Mestra'!$J$20:$J$94,MATCH(C23,'Curva Mestra'!$A$20:$A$94,0))*Bestiario!$D$7*$B$12,0) | G23: ="1 item Raro ou Lendario do tier "&A23
A24: Mithril | B24: Nas Profundezas de Mithril | C24: =Tiers!E17 | D24: Explore as Cavernas Profundas de Mithril pro Almirante Cego Malakor, enfrentando O Devorador de Mithril no fim — fecha o Ato III. | E24: =ROUND(Economia!E22*$B$11,0) | F24: =ROUND(INDEX('Curva Mestra'!$J$20:$J$94,MATCH(C24,'Curva Mestra'!$A$20:$A$94,0))*Bestiario!$D$7*$B$12,0) | G24: ="1 item Raro ou Lendario do tier "&A24
A25: Ebano | B25: O Guardiao da Fenda Morta | C25: =Tiers!E18 | D25: Enfrente o Guardião da Fenda Morta e as primeiras fusões bem-sucedidas do Culto da Assimilação, que agora opera em força total. | E25: =ROUND(Economia!E23*$B$11,0) | F25: =ROUND(INDEX('Curva Mestra'!$J$20:$J$94,MATCH(C25,'Curva Mestra'!$A$20:$A$94,0))*Bestiario!$D$7*$B$12,0) | G25: ="1 item Raro ou Lendario do tier "&A25
A26: Adamantina | B26: A Queda do Titan | C26: =Tiers!E19 | D26: Ajude o Grão-Mestre Roderick a conter o Titã de Adamantina enquanto a Heresia do Titã Negro se infiltra na própria Ordem. | E26: =ROUND(Economia!E24*$B$11,0) | F26: =ROUND(INDEX('Curva Mestra'!$J$20:$J$94,MATCH(C26,'Curva Mestra'!$A$20:$A$94,0))*Bestiario!$D$7*$B$12,0) | G26: ="1 item Raro ou Lendario do tier "&A26
A27: Osso de Dragao | B27: A Caca ao Dragao Anciao | C27: =Tiers!E20 | D27: Explore os Picos Fumegantes a caça de dracoformos, e descubra por que o Dragão Ancião guarda o Pilar de Ossos sem hostilidade. | E27: =ROUND(Economia!E25*$B$11,0) | F27: =ROUND(INDEX('Curva Mestra'!$J$20:$J$94,MATCH(C27,'Curva Mestra'!$A$20:$A$94,0))*Bestiario!$D$7*$B$12,0) | G27: ="1 item Raro ou Lendario do tier "&A27
... A29: Estelar / Cosmico | B29: O Ultimo Portal | C29: =Tiers!E22 | D29: Reúna os 5 Fragmentos do Aspecto e atravesse o Portal Estelar pro confronto final contra O Aspecto da Infecção. | E29: =ROUND(Economia!E27*$B$11,0) | F29: =ROUND(INDEX('Curva Mestra'!$J$20:$J$94,MATCH(C29,'Curva Mestra'!$A$20:$A$94,0))*Bestiario!$D$7*$B$12,0) | G29: ="1 item Raro ou Lendario do tier "&A29
A31: Sucata Enferrujada | B31: Latidos na Neblina | C31: Combate (Modesta) | D31: Matar 3 Cães de Caça Sanguíneo que rondam a vila, a pedido do Irmão Lucian. | E31: 18 Ouro. Só isso — é trabalho de rotina. | I31: Combate (Grind) | J31: Comum (Honra 0) | K31: Capitão Vane
A32: Sucata Enferrujada | B32: O Enxame que Não Para de Crescer | C32: Caça (Modesta) | D32: Limpar o Enxame de Moscas-Sangue que infesta o poço da vila antes que contaminem a água. | E32: 20 Ouro. | I32: Combate (Grind) | J32: Comum (Honra 0) | K32: Capitão Vane
A33: Sucata Enferrujada | B33: Caça II — A Matilha Cresce | D33: Mate 8 monstros Comuns do Tier 1 (qualquer combinação) + 1 Elite. | I33: Combate (Grind) | J33: Veterano (Honra 50) | K33: Capitão Vane | M33: 1 item Raro do Tier 1
A34: Sucata Enferrujada | B34: Caça III — Limpeza Total | D34: Mate 12 monstros Comuns do Tier 1 + 2 Elites diferentes. | I34: Combate (Grind) | J34: Lendário (Honra 100) | K34: Capitão Vane | L34: Completar Caça II antes | M34: 1 item Lendário do Tier 1
A35: Sucata Enferrujada | B35: A Colheita de Sucata II | D35: Traga 5x Sucata Retorcida pro Gorim, pra ele reforçar o estoque. | I35: Coleta | J35: Veterano (Honra 50) | K35: Gorim o Caolho | M35: Ouro + 1 Poção de Cura
A36: Sucata Enferrujada | B36: A Colheita de Sucata III | D36: Traga 2x Fragmento de Fanático dos Dedos Rubros — Gorim quer testar uma liga nova. | I36: Coleta | J36: Lendário (Honra 100) | K36: Gorim o Caolho | L36: Completar Coleta II antes | M36: 1 item Raro do Tier 1
A37: Sucata Enferrujada | B37: A Colheita de Sucata I | D37: Traga 3x Sucata Retorcida pro Gorim, que perdeu parte do estoque pra bandidos. | I37: Coleta | J37: Comum (Honra 0) | K37: Gorim o Caolho | M37: Ouro
A38: Sucata Enferrujada | B38: O Caçador Caçado | C38: Caça de Elite (Significativa) | D38: Impeça o Caçador de Marcas de reportar a localização da família de refugiados escondida no celeiro. | E38: 50 Ouro + 1 item Raro do tier. | I38: Elite | J38: Veterano (Honra 50) | K38: Capitão Vane
A39: Sucata Enferrujada | B39: O Colhedor do Primeiro Sangue | C39: Boss Opcional (Definidora — risco alto) | D39: Enfrente o líder do culto local antes que ele complete o ritual de marcação da vila inteira. | E39: 100 Ouro + 1 item Lendário + 1 Fragmento do Sangue (progride a trama principal do Ato I). | I39: Elite | J39: Lendário (Honra 100) | K39: Capitão Vane
A40: Sucata Enferrujada | B40: O Desafio do Fanático | D40: Derrote o Fanático dos Dedos Rubros sozinho, sem ajuda. | I40: Elite | J40: Comum (Honra 0) | K40: Capitão Vane | M40: Ouro + XP extra
A41: Sucata Enferrujada | B41: Dois Marcados | D41: Derrote 2 Elites diferentes do Tier 1 (qualquer combinação). | I41: Elite | J41: Veterano (Honra 50) | K41: Capitão Vane | L41: Completar O Desafio do Fanático antes | M41: 1 item Raro do Tier 1
A42: Sucata Enferrujada | B42: O Chá da Velha Martha | C42: Social/Escolta (Gente Humilde) | D42: Escoltar a Velha Martha até a Estrada dos Bandidos pra colher Raiz de Sangue-Seco. | E42: 10 Ouro + ela ensina a receita da Poção de Cura Básica de graça (fica permanente na sua lista de crafting) + vira aliada (reputação). | I42: Social | J42: Comum (Honra 0) | K42: Velha Martha
A43: Sucata Enferrujada | B43: O Amigo que Sumiu | C43: Traição (dilema — recompensa varia) | D43: Um morador pede ajuda pra achar o amigo desaparecido. Você o encontra como Peregrino Marcado. | E43: Contar a verdade: 10 Ouro + reputação com a vila. Mentir e poupar a família da dor: NPC vira devedor (favor futuro), mas reputação não sobe. | F43: A Milícia dos Desamparados | G43: +10 se contar a verdade / +0 se mentir (favor pessoal, não reputação) | I43: Social | J43: Comum (Honra 0) | K43: Capitão Vane
A44: Sucata Enferrujada | B44: A Disputa da Vila | D44: Capitão Vane quer caçar os bandidos à força. Irmão Lucian quer negociar e curar os Marcados. Escolha um lado. | I44: Social | J44: Veterano (Honra 50) | K44: Capitão Vane / Irmão Lucian | M44: +20 de Reputação com o lado escolhido, -10 com o outro
A45: Sucata Enferrujada | B45: O Perdão do Recruta | D45: Bandido Novato se rende a 25% de HP. Poupe-o (ele desiste do bando) ou termine o combate. | I45: Social | J45: Lendário (Honra 100) | K45: Capitão Vane | M45: Poupar: +50 Reputação com a Milícia. Matar: item Único de loot.
A46: Sucata Enferrujada | B46: O Baú do Salteador Afogado | C46: Tesouro (Significativa) | D46: Um bandido morreu tentando atravessar o rio com o saque de uma caravana. Ache o baú no leito raso. | E46: 35 Ouro + 1 item Raro do tier. | I46: Exploração | J46: Comum (Honra 0) | K46: Jarek o Carroceiro
A47: Sucata Enferrujada | B47: As Portas Marcadas | C47: Segredo (Gente Humilde) | D47: Descubra por que certas casas têm dedos ensanguentados pintados na porta antes da próxima. | E47: 15 Ouro + Irmão Lucian revela a existência do Caçador de Marcas (destrava a quest seguinte). | I47: Exploração | J47: Veterano (Honra 50) | K47: Irmão Lucian
